Workbook

Sheet README
A1: McCahill & Co. — Cash Position & Planning Model
A2: Paste your bank data into TRANSACTIONS. Everything else calculates. Nothing here is filled with real numbers yet.
B4: HOW TO USE THIS
B5: Step 1 | C5: ACCOUNT MAP — list every account you have and say which entity owns it. Enter the balance immediately before Feb 1. Nothing works until this is done.
B6: Step 2 | C6: TRANSACTIONS — paste every bank line from every account. One row per transaction. Money IN is positive, money OUT is negative.
B7: Step 3 | C7: TRANSACTIONS column F — pick a category for each row from the dropdown. This is the only real work. Anything you are unsure of, pick '! UNCLEAR - NEEDS REVIEW'.
B8: Step 4 | C8: TRANSACTIONS column H — for any transfer between your own accounts, put the SAME pair id (T1, T2, T3...) on both sides. This is what stops transfers being counted as income.
B9: Step 5 | C9: Read CASH RECONCILIATION. If ending cash does not match your real bank balance, the gap is listed on FLAGS. Fix it there, do not force it.
B11: COLOUR CODE
B12: Yellow fill | C12: You fill this in.
B13: Blue text | C13: A number you typed. Change it freely.
B14: Black text | C14: A formula. Do not overwrite it.
B15: Green text | C15: Pulled from another tab.
B17: THE RULES THIS MODEL ENFORCES
B18: Transfers | C18: Money moved between your own accounts is never revenue and never an expense. It changes ending cash only.
B19: GST | C19: GST collected is not revenue. It is money you are holding for CRA. Enter it in column J and it is stripped out of the revenue figures.
B20: Receivables | C20: Unpaid invoices are not cash. Only money that has actually landed in an account belongs in TRANSACTIONS.
B21: Non-cash assets | C21: Vehicles, equipment, tools and inventory are not liquid cash. They appear in planning, never in the cash total.
B22: Cash is not profit | C22: Ending cash reflects loan payments, owner draws, GST timing and equipment purchases. BUSINESS PERFORMANCE shows the difference.
B23: Entity separation | C23: Sole prop (Feb 1 - Jun 30) and corporation (Jul 1 - Jan 31) are never combined. They are legally different taxpayers.
B25: TABS
B26: ACCOUNT MAP | C26: Your accounts, their entity, and opening balances.
B27: CATEGORIES | C27: The category list and what each one counts as. Reference only.
B28: TRANSACTIONS | C28: Where your data goes.
B29: CASH RECONCILIATION | C29: Opening + in - out = closing, per entity. The core check.
B30: MONTH BY MONTH | C30: Feb through Jan, split sole prop / corp / personal.
B31: BUSINESS PERFORMANCE | C31: Sole prop vs corporation, GST stripped out.
B32: CASH QUALITY | C32: Burn rate, runway, tax reserve, deployable capital.
B33: VEHICLE SCENARIOS | C33: What a $20k / $30k / $40k / $50k purchase does to your reserves.
B34: SCENARIOS | C34: Conservative / base / aggressive for next season.
B35: FLAGS | C35: Everything that does not tie, is uncategorised, or needs your answer.

Sheet ASSUMPTIONS
A1: Assumptions & Rates
A2: Blue cells are levers — change them and the whole model moves. Anything marked VERIFY must be checked against the current CRA figure before you rely on it.
A4: # | B4: Assumption | C4: Value | D4: Status | E4: Where it came from / what to check
A5: 1 | B5: Business start date | C5: 2026-02-01 | D5: Confirmed | E5: You confirmed Feb 2026 is the start of operations.
A6: 2 | B6: Sole prop period ends | C6: 2026-06-30 | D6: Confirmed
A7: 3 | B7: Corporation period starts | C7: 2026-07-01 | D7: Confirmed
A8: 4 | B8: Corporate fiscal year end | C8: 2027-01-31 | D8: Your choice | E8: You chose Jan 31. Confirm this is what was actually filed — it is set at incorporation and drives every tax deadline.
A9: 5 | B9: Crew wage — Kierran | C9: 27 | D9: Confirmed | E9: You confirmed $27.00/hr.
A10: 6 | B10: Owner draw from corporation, per month | C10: 4000 | D10: Confirmed | E10: You confirmed $4,000/month since July 1. Currently a shareholder loan unless declared as salary or dividend.
A11: 7 | B11: GST rate | C11: 0.05 | D11: Confirmed | E11: BC — GST only on landscaping services. No PST on the service itself.
A12: 8 | B12: CPP contribution rate (employee) | C12: 0.0595 | D12: VERIFY | E12: 2025 rate shown. Confirm the 2026 rate at canada.ca before relying on the liability estimate.
A13: 9 | B13: CPP basic exemption (annual) | C13: 3500 | D13: VERIFY | E13: 2025 figure. Confirm 2026.
A14: 10 | B14: EI premium rate (employee) | C14: 0.0164 | D14: VERIFY | E14: 2025 rate. Confirm 2026.
A15: 11 | B15: EI employer multiplier | C15: 1.4 | D15: VERIFY | E15: Employer pays 1.4x the employee premium. Confirm.
A16: 12 | B16: Income tax withheld — estimated rate | C16: 0.12 | D16: ESTIMATE | E16: A rough blended rate for a BC employee at this wage. Replace with the actual figure from your payroll calculation.
A17: 13 | B17: Late remittance penalty rate | C17: 0.1 | D17: ESTIMATE | E17: CRA charges 10% on a first failure to remit, 20% if repeated or grossly negligent. Interest accrues on top.
A18: 14 | B18: Corporate small business tax rate (BC) | C18: 0.11 | D18: ESTIMATE | E18: Roughly 9% federal + 2% BC on active business income under the small business limit. Confirm with your accountant.
A19: 15 | B19: Personal tax reserve rate (sole prop income) | C19: 0.25 | D19: ESTIMATE | E19: A holding rate until your actual return is prepared. Your real rate depends on total income and credits.
A20: 16 | B20: Target operating reserve (months) | C20: 3 | D20: Your lever | E20: Months of payroll plus fixed costs to keep untouched. 3 is a common floor for seasonal trades.
A21: 17 | B21: Months of the year that generate revenue | C21: 9 | D21: Your lever | E21: Landscaping in Victoria. Drives the winter burn calculation.

Sheet ACCOUNT MAP
A1: Account Map
A2: Every account you hold. Yellow cells are yours to fill. The entity you assign here drives the entire model.
A4: Account name (use this exact name in TRANSACTIONS) | B4: Bank / institution | C4: Entity | D4: Account type | E4: Balance immediately before Feb 1 | F4: Liquid? | G4: Notes
A5: EXAMPLE - BMO Business Chq 1234 | B5: BMO | C5: Sole Prop | D5: Chequing | E5: 0 | F5: Yes | G5: Delete this row once you add your own
A6: EQ - Sole Prop Chequing | B6: EQ Bank | C6: Sole Prop | D6: Chequing | E6: 0 | F6: Yes | G6: Statements Feb 9 - Aug 31, 2026 loaded. Opening balance $0.00 - first transaction Feb 9 established the account.
A7: EQ - Corporation Chequing | B7: EQ Bank | C7: Corporation | D7: Chequing | E7: 0 | F7: Yes | G7: Statement Aug 28 - Aug 31, 2026 loaded. Account opened Aug 28, NOT July 1.
A8: TD - Personal Chequing | B8: TD | C8: Personal | D8: Chequing | F8: Yes | G8: ENTER your TD balance as at Jan 31, 2026.
A9: Wealthsimple - Investments | B9: Wealthsimple | C9: Personal | D9: Investment | F9: Partly | G9: ENTER balance at Jan 31, 2026. Set Liquid to Yes only if you would genuinely sell. Confirm registered vs non-registered.
A46: OPENING CASH BEFORE FEB 1
A47: Personal | E47: =SUMIFS($E$6:$E$44,$C$6:$C$44,$A47,$F$6:$F$44,"Yes")
A48: Sole Prop | E48: =SUMIFS($E$6:$E$44,$C$6:$C$44,$A48,$F$6:$F$44,"Yes")
A49: Corporation | E49: =SUMIFS($E$6:$E$44,$C$6:$C$44,$A49,$F$6:$F$44,"Yes")
A50: TOTAL OPENING LIQUID CASH | E50: =SUM(E47:E49)
A52: Only accounts marked Liquid = "Yes" count toward cash. Mark a locked-in GIC or an RRSP you would not actually draw on as "No".

Sheet CATEGORIES
A1: Categories
A2: Reference. Column C is what the model does with each category. Do not rename anything here — TRANSACTIONS looks these up by exact text.
A4: # | B4: Category (appears in the TRANSACTIONS dropdown) | C4: Treated as | D4: What it means
A5: 1 | B5: Client payment received | C5: Revenue | D5: Money from a customer that actually landed. Enter GST separately in column J.
A6: 2 | B6: Deposit received (work not yet done) | C6: Revenue | D6: Cash you hold but have not earned. Real cash, but do not treat it as profit.
A7: 3 | B7: Other business income | C7: Revenue | D7: Rebates, insurance proceeds, equipment sold.
A8: 4 | B8: Materials and plants | C8: COGS | D8: Supplier purchases that go into a job.
A9: 5 | B9: Subcontractor | C9: COGS | D9: Paid to another business for job work.
A10: 6 | B10: Equipment rental | C10: COGS | D10: Rented for a specific job.
A11: 7 | B11: Disposal and dump fees | C11: COGS | D11: Tipping fees, debris hauling.
A12: 8 | B12: Fuel | C12: Operating Expense | D12: All vehicle fuel.
A13: 9 | B13: Vehicle repairs and maintenance | C13: Operating Expense | D13: Parts, service, tires.
A14: 10 | B14: Vehicle insurance | C14: Operating Expense | D14: ICBC and commercial coverage.
A15: 11 | B15: Liability insurance | C15: Operating Expense | D15: General business liability.
A16: 12 | B16: WorkSafeBC premiums | C16: Operating Expense | D16: Statutory coverage.
A17: 13 | B17: Rent, yard or storage | C17: Operating Expense | D17: Fixed premises cost.
A18: 14 | B18: Phone and internet | C18: Operating Expense
A19: 15 | B19: Software and subscriptions | C19: Operating Expense
A20: 16 | B20: Accounting and bookkeeping | C20: Operating Expense
A21: 17 | B21: Legal | C21: Operating Expense
A22: 18 | B22: Advertising and marketing | C22: Operating Expense
A23: 19 | B23: Bank and merchant fees | C23: Operating Expense | D23: Includes card processing fees.
A24: 20 | B24: Small tools and consumables | C24: Operating Expense | D24: Under the capitalisation threshold.
A25: 21 | B25: Other operating expense | C25: Operating Expense | D25: Use sparingly. A large balance here weakens the analysis.
A26: 22 | B26: Crew wages (net pay out) | C26: Payroll | D26: Net amount that left the bank to crew.
A27: 23 | B27: Payroll service fees | C27: Payroll
A28: 24 | B28: CRA source deductions remitted | C28: Tax/Remittance | D28: CPP, EI and income tax sent to CRA.
A29: 25 | B29: GST remitted to CRA | C29: Tax/Remittance | D29: Never an expense. You were holding this money.
A30: 26 | B30: Personal tax instalment | C30: Tax/Remittance | D30: Paid from whichever account it actually left.
A31: 27 | B31: Corporate tax instalment | C31: Tax/Remittance
A32: 28 | B32: Owner draw (sole prop) | C32: Owner Draw/Comp | D32: Not an expense. Reduces cash, not profit.
A33: 29 | B33: Owner salary (corporation) | C33: Owner Draw/Comp | D33: Through payroll, with source deductions.
A34: 30 | B34: Dividend paid to owner | C34: Owner Draw/Comp
A35: 31 | B35: Shareholder loan repaid to owner | C35: Owner Draw/Comp | D35: Money the corporation owed you, returned.
A36: 32 | B36: Vehicle purchase | C36: Capital Purchase | D36: Cash out now, expensed over years. A major cash-vs-profit gap.
A37: 33 | B37: Equipment purchase | C37: Capital Purchase | D37: Same treatment as a vehicle.
A38: 34 | B38: Loan or lease payment | C38: Financing | D38: The principal portion is not an expense.
A39: 35 | B39: Loan or financing proceeds | C39: Financing | D39: Cash in, but it is debt, not income.
A40: 36 | B40: Capital contributed by owner | C40: Financing | D40: Your money into the business. Never revenue.
A41: 37 | B41: Transfer - Personal <-> Sole Prop | C41: Transfer | D41: Excluded from revenue and expenses. Pair it in column H.
A42: 38 | B42: Transfer - Personal <-> Corporation | C42: Transfer | D42: Excluded. Pair it in column H.
A43: 39 | B43: Transfer - Sole Prop <-> Corporation | C43: Transfer | D43: Excluded. Pair it in column H. Also tell your accountant.
A44: 40 | B44: Transfer - between my own accounts, same entity | C44: Transfer | D44: Chequing to savings, etc. Excluded.
A45: 41 | B45: Personal income (not from business) | C45: Personal Income | D45: Partner income, other work, benefits.
A46: 42 | B46: Personal expense | C46: Personal Expense | D46: Household, living, personal debt.
... A49: 45 | B49: ! UNCLEAR - NEEDS REVIEW | C49: Review | D49: Use this freely. It lands on FLAGS instead of quietly distorting the numbers.

Sheet TRANSACTIONS
A1: Transactions
A2: Paste every bank line here, every account. Money IN positive, money OUT negative. Fill the yellow columns; grey columns calculate themselves.
B3: Type an account name EXACTLY as spelled on ACCOUNT MAP | F3: Type a category EXACTLY as spelled on the CATEGORIES tab
A4: Date | B4: Account (must match ACCOUNT MAP) | C4: Description from statement | D4: Amount (+ in / - out) | E4: Entity | F4: Category (pick from list) | G4: Treated as | H4: Transfer pair id | I4: GST included in this line | J4: Month key | K4: Your note
A5: 46062 | B5: EQ - Sole Prop Chequing | C5: Interac e-Transfer received from KYLE JOHN BENJAMIN MCCAHILL | D5: 100 | E5: =IF($B5="","",IFERROR(INDEX('ACCOUNT MAP'!$C$6:$C$44,MATCH($B5,'ACCOUNT MAP'!$A$6:$A$44,0)),"! UNMAPPED ACCOUNT")) | F5: Capital contributed by owner | G5: =IF($F5="","",IFERROR(INDEX(CATEGORIES!$C$5:$C$49,MATCH($F5,CATEGORIES!$B$5:$B$49,0)),"! UNKNOWN CATEGORY")) | J5: =IF($A5="","",YEAR($A5)*100+MONTH($A5))
A6: 46063 | B6: EQ - Sole Prop Chequing | C6: Interac e-Transfer received from KYLE JOHN BENJAMIN MCCAHILL | D6: 1500 | E6: =IF($B6="","",IFERROR(INDEX('ACCOUNT MAP'!$C$6:$C$44,MATCH($B6,'ACCOUNT MAP'!$A$6:$A$44,0)),"! UNMAPPED ACCOUNT")) | F6: Capital contributed by owner | G6: =IF($F6="","",IFERROR(INDEX(CATEGORIES!$C$5:$C$49,MATCH($F6,CATEGORIES!$B$5:$B$49,0)),"! UNKNOWN CATEGORY")) | J6: =IF($A6="","",YEAR($A6)*100+MONTH($A6))
A7: 46064 | B7: EQ - Sole Prop Chequing | C7: Interac e-Transfer received from PACIFIC CITY DEVELOPMENTS INC. | D7: 3490 | E7: =IF($B7="","",IFERROR(INDEX('ACCOUNT MAP'!$C$6:$C$44,MATCH($B7,'ACCOUNT MAP'!$A$6:$A$44,0)),"! UNMAPPED ACCOUNT")) | F7: Client payment received | G7: =IF($F7="","",IFERROR(INDEX(CATEGORIES!$C$5:$C$49,MATCH($F7,CATEGORIES!$B$5:$B$49,0)),"! UNKNOWN CATEGORY")) | I7: 166.19 | J7: =IF($A7="","",YEAR($A7)*100+MONTH($A7))
A8: 46068 | B8: EQ - Sole Prop Chequing | C8: Mobile cheque deposit | D8: 7500 | E8: =IF($B8="","",IFERROR(INDEX('ACCOUNT MAP'!$C$6:$C$44,MATCH($B8,'ACCOUNT MAP'!$A$6:$A$44,0)),"! UNMAPPED ACCOUNT")) | F8: Client payment received | G8: =IF($F8="","",IFERROR(INDEX(CATEGORIES!$C$5:$C$49,MATCH($F8,CATEGORIES!$B$5:$B$49,0)),"! UNKNOWN CATEGORY")) | I8: 357.14 | J8: =IF($A8="","",YEAR($A8)*100+MONTH($A8))
A9: 46069 | B9: EQ - Sole Prop Chequing | C9: Mobile cheque deposit | D9: 12500 | E9: =IF($B9="","",IFERROR(INDEX('ACCOUNT MAP'!$C$6:$C$44,MATCH($B9,'ACCOUNT MAP'!$A$6:$A$44,0)),"! UNMAPPED ACCOUNT")) | F9: Client payment received | G9: =IF($F9="","",IFERROR(INDEX(CATEGORIES!$C$5:$C$49,MATCH($F9,CATEGORIES!$B$5:$B$49,0)),"! UNKNOWN CATEGORY")) | I9: 595.24 | J9: =IF($A9="","",YEAR($A9)*100+MONTH($A9))
A10: 46076 | B10: EQ - Sole Prop Chequing | C10: Interac e-Transfer sent to PND GRAVEL MART | D10: -560 | E10: =IF($B10="","",IFERROR(INDEX('ACCOUNT MAP'!$C$6:$C$44,MATCH($B10,'ACCOUNT MAP'!$A$6:$A$44,0)),"! UNMAPPED ACCOUNT")) | F10: Materials and plants | G10: =IF($F10="","",IFERROR(INDEX(CATEGORIES!$C$5:$C$49,MATCH($F10,CATEGORIES!$B$5:$B$49,0)),"! UNKNOWN CATEGORY")) | J10: =IF($A10="","",YEAR($A10)*100+MONTH($A10))
A11: 46078 | B11: EQ - Sole Prop Chequing | C11: Mobile cheque deposit | D11: 3526.39 | E11: =IF($B11="","",IFERROR(INDEX('ACCOUNT MAP'!$C$6:$C$44,MATCH($B11,'ACCOUNT MAP'!$A$6:$A$44,0)),"! UNMAPPED ACCOUNT")) | F11: Client payment received | G11: =IF($F11="","",IFERROR(INDEX(CATEGORIES!$C$5:$C$49,MATCH($F11,CATEGORIES!$B$5:$B$49,0)),"! UNKNOWN CATEGORY")) | I11: 167.92 | J11: =IF($A11="","",YEAR($A11)*100+MONTH($A11))
A12: 46078 | B12: EQ - Sole Prop Chequing | C12: Interac e-Transfer sent to K2 Stone | D12: -7284.72 | E12: =IF($B12="","",IFERROR(INDEX('ACCOUNT MAP'!$C$6:$C$44,MATCH($B12,'ACCOUNT MAP'!$A$6:$A$44,0)),"! UNMAPPED ACCOUNT")) | F12: Materials and plants | G12: =IF($F12="","",IFERROR(INDEX(CATEGORIES!$C$5:$C$49,MATCH($F12,CATEGORIES!$B$5:$B$49,0)),"! UNKNOWN CATEGORY")) | J12: =IF($A12="","",YEAR($A12)*100+MONTH($A12))
A13: 46078 | B13: EQ - Sole Prop Chequing | C13: Interac e-Transfer sent to Myles (YGGDRASIL HORTICUL | D13: -1020 | E13: =IF($B13="","",IFERROR(INDEX('ACCOUNT MAP'!$C$6:$C$44,MATCH($B13,'ACCOUNT MAP'!$A$6:$A$44,0)),"! UNMAPPED ACCOUNT")) | F13: Materials and plants | G13: =IF($F13="","",IFERROR(INDEX(CATEGORIES!$C$5:$C$49,MATCH($F13,CATEGORIES!$B$5:$B$49,0)),"! UNKNOWN CATEGORY")) | J13: =IF($A13="","",YEAR($A13)*100+MONTH($A13))
A14: 46079 | B14: EQ - Sole Prop Chequing | C14: Mobile cheque deposit | D14: 10000 | E14: =IF($B14="","",IFERROR(INDEX('ACCOUNT MAP'!$C$6:$C$44,MATCH($B14,'ACCOUNT MAP'!$A$6:$A$44,0)),"! UNMAPPED ACCOUNT")) | F14: Client payment received | G14: =IF($F14="","",IFERROR(INDEX(CATEGORIES!$C$5:$C$49,MATCH($F14,CATEGORIES!$B$5:$B$49,0)),"! UNKNOWN CATEGORY")) | I14: 476.19 | J14: =IF($A14="","",YEAR($A14)*100+MONTH($A14))
A15: 46079 | B15: EQ - Sole Prop Chequing | C15: Interac e-Transfer sent to K2 Stone | D15: -2262.85 | E15: =IF($B15="","",IFERROR(INDEX('ACCOUNT MAP'!$C$6:$C$44,MATCH($B15,'ACCOUNT MAP'!$A$6:$A$44,0)),"! UNMAPPED ACCOUNT")) | F15: Materials and plants | G15: =IF($F15="","",IFERROR(INDEX(CATEGORIES!$C$5:$C$49,MATCH($F15,CATEGORIES!$B$5:$B$49,0)),"! UNKNOWN CATEGORY")) | J15: =IF($A15="","",YEAR($A15)*100+MONTH($A15))
A16: 46079 | B16: EQ - Sole Prop Chequing | C16: Interac e-Transfer sent to PND GRAVEL MART | D16: -280 | E16: =IF($B16="","",IFERROR(INDEX('ACCOUNT MAP'!$C$6:$C$44,MATCH($B16,'ACCOUNT MAP'!$A$6:$A$44,0)),"! UNMAPPED ACCOUNT")) | F16: Materials and plants | G16: =IF($F16="","",IFERROR(INDEX(CATEGORIES!$C$5:$C$49,MATCH($F16,CATEGORIES!$B$5:$B$49,0)),"! UNKNOWN CATEGORY")) | J16: =IF($A16="","",YEAR($A16)*100+MONTH($A16))
A17: 46079 | B17: EQ - Sole Prop Chequing | C17: Auto-withdrawal by AMEX BILL PYMT | D17: -1063.19 | E17: =IF($B17="","",IFERROR(INDEX('ACCOUNT MAP'!$C$6:$C$44,MATCH($B17,'ACCOUNT MAP'!$A$6:$A$44,0)),"! UNMAPPED ACCOUNT")) | F17: ! UNCLEAR - NEEDS REVIEW | G17: =IF($F17="","",IFERROR(INDEX(CATEGORIES!$C$5:$C$49,MATCH($F17,CATEGORIES!$B$5:$B$49,0)),"! UNKNOWN CATEGORY")) | J17: =IF($A17="","",YEAR($A17)*100+MONTH($A17)) | K17: Credit card payment — AMEX BILL PYMT
A18: 46081 | B18: EQ - Sole Prop Chequing | C18: Interest received | D18: 22.01 | E18: =IF($B18="","",IFERROR(INDEX('ACCOUNT MAP'!$C$6:$C$44,MATCH($B18,'ACCOUNT MAP'!$A$6:$A$44,0)),"! UNMAPPED ACCOUNT")) | F18: Other business income | G18: =IF($F18="","",IFERROR(INDEX(CATEGORIES!$C$5:$C$49,MATCH($F18,CATEGORIES!$B$5:$B$49,0)),"! UNKNOWN CATEGORY")) | J18: =IF($A18="","",YEAR($A18)*100+MONTH($A18))
A19: 46083 | B19: EQ - Sole Prop Chequing | C19: Interac e-Transfer sent to GC Excavation | D19: -2520 | E19: =IF($B19="","",IFERROR(INDEX('ACCOUNT MAP'!$C$6:$C$44,MATCH($B19,'ACCOUNT MAP'!$A$6:$A$44,0)),"! UNMAPPED ACCOUNT")) | F19: Subcontractor | G19: =IF($F19="","",IFERROR(INDEX(CATEGORIES!$C$5:$C$49,MATCH($F19,CATEGORIES!$B$5:$B$49,0)),"! UNKNOWN CATEGORY")) | J19: =IF($A19="","",YEAR($A19)*100+MONTH($A19))
A20: 46084 | B20: EQ - Sole Prop Chequing | C20: Interac e-Transfer sent to Michelle | D20: -5175 | E20: =IF($B20="","",IFERROR(INDEX('ACCOUNT MAP'!$C$6:$C$44,MATCH($B20,'ACCOUNT MAP'!$A$6:$A$44,0)),"! UNMAPPED ACCOUNT")) | F20: ! UNCLEAR - NEEDS REVIEW | G20: =IF($F20="","",IFERROR(INDEX(CATEGORIES!$C$5:$C$49,MATCH($F20,CATEGORIES!$B$5:$B$49,0)),"! UNKNOWN CATEGORY")) | J20: =IF($A20="","",YEAR($A20)*100+MONTH($A20)) | K20: ? Crew or sub — Michelle
A21: 46084 | B21: EQ - Sole Prop Chequing | C21: Interac e-Transfer sent to Canopyco | D21: -250 | E21: =IF($B21="","",IFERROR(INDEX('ACCOUNT MAP'!$C$6:$C$44,MATCH($B21,'ACCOUNT MAP'!$A$6:$A$44,0)),"! UNMAPPED ACCOUNT")) | F21: ! UNCLEAR - NEEDS REVIEW | G21: =IF($F21="","",IFERROR(INDEX(CATEGORIES!$C$5:$C$49,MATCH($F21,CATEGORIES!$B$5:$B$49,0)),"! UNKNOWN CATEGORY")) | J21: =IF($A21="","",YEAR($A21)*100+MONTH($A21)) | K21: ? Canopyco — UNIDENTIFIED
A22: 46088 | B22: EQ - Sole Prop Chequing | C22: Interac e-Transfer sent to Kierran Kivinen | D22: -435.42 | E22: =IF($B22="","",IFERROR(INDEX('ACCOUNT MAP'!$C$6:$C$44,MATCH($B22,'ACCOUNT MAP'!$A$6:$A$44,0)),"! UNMAPPED ACCOUNT")) | F22: Crew wages (net pay out) | G22: =IF($F22="","",IFERROR(INDEX(CATEGORIES!$C$5:$C$49,MATCH($F22,CATEGORIES!$B$5:$B$49,0)),"! UNKNOWN CATEGORY")) | J22: =IF($A22="","",YEAR($A22)*100+MONTH($A22))
A23: 46090 | B23: EQ - Sole Prop Chequing | C23: Mobile cheque deposit | D23: 1925.83 | E23: =IF($B23="","",IFERROR(INDEX('ACCOUNT MAP'!$C$6:$C$44,MATCH($B23,'ACCOUNT MAP'!$A$6:$A$44,0)),"! UNMAPPED ACCOUNT")) | F23: Client payment received | G23: =IF($F23="","",IFERROR(INDEX(CATEGORIES!$C$5:$C$49,MATCH($F23,CATEGORIES!$B$5:$B$49,0)),"! UNKNOWN CATEGORY")) | I23: 91.71 | J23: =IF($A23="","",YEAR($A23)*100+MONTH($A23))
A24: 46091 | B24: EQ - Sole Prop Chequing | C24: Mobile cheque deposit | D24: 1020.14 | E24: =IF($B24="","",IFERROR(INDEX('ACCOUNT MAP'!$C$6:$C$44,MATCH($B24,'ACCOUNT MAP'!$A$6:$A$44,0)),"! UNMAPPED ACCOUNT")) | F24: Client payment received | G24: =IF($F24="","",IFERROR(INDEX(CATEGORIES!$C$5:$C$49,MATCH($F24,CATEGORIES!$B$5:$B$49,0)),"! UNKNOWN CATEGORY")) | I24: 48.58 | J24: =IF($A24="","",YEAR($A24)*100+MONTH($A24))
A25: 46091 | B25: EQ - Sole Prop Chequing | C25: Mobile cheque deposit | D25: 1797.06 | E25: =IF($B25="","",IFERROR(INDEX('ACCOUNT MAP'!$C$6:$C$44,MATCH($B25,'ACCOUNT MAP'!$A$6:$A$44,0)),"! UNMAPPED ACCOUNT")) | F25: Client payment received | G25: =IF($F25="","",IFERROR(INDEX(CATEGORIES!$C$5:$C$49,MATCH($F25,CATEGORIES!$B$5:$B$49,0)),"! UNKNOWN CATEGORY")) | I25: 85.57 | J25: =IF($A25="","",YEAR($A25)*100+MONTH($A25))
A26: 46091 | B26: EQ - Sole Prop Chequing | C26: Auto-withdrawal by Wave PYRL | D26: -1105.7 | E26: =IF($B26="","",IFERROR(INDEX('ACCOUNT MAP'!$C$6:$C$44,MATCH($B26,'ACCOUNT MAP'!$A$6:$A$44,0)),"! UNMAPPED ACCOUNT")) | F26: Crew wages (net pay out) | G26: =IF($F26="","",IFERROR(INDEX(CATEGORIES!$C$5:$C$49,MATCH($F26,CATEGORIES!$B$5:$B$49,0)),"! UNKNOWN CATEGORY")) | J26: =IF($A26="","",YEAR($A26)*100+MONTH($A26))
A27: 46091 | B27: EQ - Sole Prop Chequing | C27: Interac e-Transfer sent to Canopyco | D27: -5000 | E27: =IF($B27="","",IFERROR(INDEX('ACCOUNT MAP'!$C$6:$C$44,MATCH($B27,'ACCOUNT MAP'!$A$6:$A$44,0)),"! UNMAPPED ACCOUNT")) | F27: ! UNCLEAR - NEEDS REVIEW | G27: =IF($F27="","",IFERROR(INDEX(CATEGORIES!$C$5:$C$49,MATCH($F27,CATEGORIES!$B$5:$B$49,0)),"! UNKNOWN CATEGORY")) | J27: =IF($A27="","",YEAR($A27)*100+MONTH($A27)) | K27: ? Canopyco — UNIDENTIFIED
A28: 46092 | B28: EQ - Sole Prop Chequing | C28: Mobile cheque deposit | D28: 10569.01 | E28: =IF($B28="","",IFERROR(INDEX('ACCOUNT MAP'!$C$6:$C$44,MATCH($B28,'ACCOUNT MAP'!$A$6:$A$44,0)),"! UNMAPPED ACCOUNT")) | F28: Client payment received | G28: =IF($F28="","",IFERROR(INDEX(CATEGORIES!$C$5:$C$49,MATCH($F28,CATEGORIES!$B$5:$B$49,0)),"! UNKNOWN CATEGORY")) | I28: 503.29 | J28: =IF($A28="","",YEAR($A28)*100+MONTH($A28))
A29: 46092 | B29: EQ - Sole Prop Chequing | C29: Mobile cheque deposit | D29: -10569.01 | E29: =IF($B29="","",IFERROR(INDEX('ACCOUNT MAP'!$C$6:$C$44,MATCH($B29,'ACCOUNT MAP'!$A$6:$A$44,0)),"! UNMAPPED ACCOUNT")) | F29: Client payment received | G29: =IF($F29="","",IFERROR(INDEX(CATEGORIES!$C$5:$C$49,MATCH($F29,CATEGORIES!$B$5:$B$49,0)),"! UNKNOWN CATEGORY")) | J29: =IF($A29="","",YEAR($A29)*100+MONTH($A29))
A30: 46093 | B30: EQ - Sole Prop Chequing | C30: Mobile cheque deposit | D30: 10569.01 | E30: =IF($B30="","",IFERROR(INDEX('ACCOUNT MAP'!$C$6:$C$44,MATCH($B30,'ACCOUNT MAP'!$A$6:$A$44,0)),"! UNMAPPED ACCOUNT")) | F30: Client payment received | G30: =IF($F30="","",IFERROR(INDEX(CATEGORIES!$C$5:$C$49,MATCH($F30,CATEGORIES!$B$5:$B$49,0)),"! UNKNOWN CATEGORY")) | I30: 503.29 | J30: =IF($A30="","",YEAR($A30)*100+MONTH($A30))
A31: 46093 | B31: EQ - Sole Prop Chequing | C31: Interac e-Transfer sent to PND GRAVEL MART | D31: -151.2 | E31: =IF($B31="","",IFERROR(INDEX('ACCOUNT MAP'!$C$6:$C$44,MATCH($B31,'ACCOUNT MAP'!$A$6:$A$44,0)),"! UNMAPPED ACCOUNT")) | F31: Materials and plants | G31: =IF($F31="","",IFERROR(INDEX(CATEGORIES!$C$5:$C$49,MATCH($F31,CATEGORIES!$B$5:$B$49,0)),"! UNKNOWN CATEGORY")) | J31: =IF($A31="","",YEAR($A31)*100+MONTH($A31))
A32: 46093 | B32: EQ - Sole Prop Chequing | C32: Interac e-Transfer sent to PND GRAVEL MART | D32: -112 | E32: =IF($B32="","",IFERROR(INDEX('ACCOUNT MAP'!$C$6:$C$44,MATCH($B32,'ACCOUNT MAP'!$A$6:$A$44,0)),"! UNMAPPED ACCOUNT")) | F32: Materials and plants | G32: =IF($F32="","",IFERROR(INDEX(CATEGORIES!$C$5:$C$49,MATCH($F32,CATEGORIES!$B$5:$B$49,0)),"! UNKNOWN CATEGORY")) | J32: =IF($A32="","",YEAR($A32)*100+MONTH($A32))
A33: 46093 | B33: EQ - Sole Prop Chequing | C33: Interac e-Transfer sent to PND GRAVEL MART | D33: -398.72 | E33: =IF($B33="","",IFERROR(INDEX('ACCOUNT MAP'!$C$6:$C$44,MATCH($B33,'ACCOUNT MAP'!$A$6:$A$44,0)),"! UNMAPPED ACCOUNT")) | F33: Materials and plants | G33: =IF($F33="","",IFERROR(INDEX(CATEGORIES!$C$5:$C$49,MATCH($F33,CATEGORIES!$B$5:$B$49,0)),"! UNKNOWN CATEGORY")) | J33: =IF($A33="","",YEAR($A33)*100+MONTH($A33))
A34: 46093 | B34: EQ - Sole Prop Chequing | C34: Interac e-Transfer sent to PND GRAVEL MART | D34: -1267.84 | E34: =IF($B34="","",IFERROR(INDEX('ACCOUNT MAP'!$C$6:$C$44,MATCH($B34,'ACCOUNT MAP'!$A$6:$A$44,0)),"! UNMAPPED ACCOUNT")) | F34: Materials and plants | G34: =IF($F34="","",IFERROR(INDEX(CATEGORIES!$C$5:$C$49,MATCH($F34,CATEGORIES!$B$5:$B$49,0)),"! UNKNOWN CATEGORY")) | J34: =IF($A34="","",YEAR($A34)*100+MONTH($A34))
A35: 46093 | B35: EQ - Sole Prop Chequing | C35: Mobile cheque deposit | D35: -10569.01 | E35: =IF($B35="","",IFERROR(INDEX('ACCOUNT MAP'!$C$6:$C$44,MATCH($B35,'ACCOUNT MAP'!$A$6:$A$44,0)),"! UNMAPPED ACCOUNT")) | F35: Client payment received | G35: =IF($F35="","",IFERROR(INDEX(CATEGORIES!$C$5:$C$49,MATCH($F35,CATEGORIES!$B$5:$B$49,0)),"! UNKNOWN CATEGORY")) | J35: =IF($A35="","",YEAR($A35)*100+MONTH($A35))
A36: 46096 | B36: EQ - Sole Prop Chequing | C36: Interac e-Transfer received from BEVERLY DEVRIES | D36: 840 | E36: =IF($B36="","",IFERROR(INDEX('ACCOUNT MAP'!$C$6:$C$44,MATCH($B36,'ACCOUNT MAP'!$A$6:$A$44,0)),"! UNMAPPED ACCOUNT")) | F36: Client payment received | G36: =IF($F36="","",IFERROR(INDEX(CATEGORIES!$C$5:$C$49,MATCH($F36,CATEGORIES!$B$5:$B$49,0)),"! UNKNOWN CATEGORY")) | I36: 40 | J36: =IF($A36="","",YEAR($A36)*100+MONTH($A36))
A37: 46096 | B37: EQ - Sole Prop Chequing | C37: Interac e-Transfer sent to Kierran Kivinen | D37: -622.29 | E37: =IF($B37="","",IFERROR(INDEX('ACCOUNT MAP'!$C$6:$C$44,MATCH($B37,'ACCOUNT MAP'!$A$6:$A$44,0)),"! UNMAPPED ACCOUNT")) | F37: Crew wages (net pay out) | G37: =IF($F37="","",IFERROR(INDEX(CATEGORIES!$C$5:$C$49,MATCH($F37,CATEGORIES!$B$5:$B$49,0)),"! UNKNOWN CATEGORY")) | J37: =IF($A37="","",YEAR($A37)*100+MONTH($A37))
A38: 46098 | B38: EQ - Sole Prop Chequing | C38: Auto-withdrawal by Gore Mutual | D38: -93.8 | E38: =IF($B38="","",IFERROR(INDEX('ACCOUNT MAP'!$C$6:$C$44,MATCH($B38,'ACCOUNT MAP'!$A$6:$A$44,0)),"! UNMAPPED ACCOUNT")) | F38: Liability insurance | G38: =IF($F38="","",IFERROR(INDEX(CATEGORIES!$C$5:$C$49,MATCH($F38,CATEGORIES!$B$5:$B$49,0)),"! UNKNOWN CATEGORY")) | J38: =IF($A38="","",YEAR($A38)*100+MONTH($A38))
A39: 46099 | B39: EQ - Sole Prop Chequing | C39: Mobile cheque deposit | D39: 11532 | E39: =IF($B39="","",IFERROR(INDEX('ACCOUNT MAP'!$C$6:$C$44,MATCH($B39,'ACCOUNT MAP'!$A$6:$A$44,0)),"! UNMAPPED ACCOUNT")) | F39: Client payment received | G39: =IF($F39="","",IFERROR(INDEX(CATEGORIES!$C$5:$C$49,MATCH($F39,CATEGORIES!$B$5:$B$49,0)),"! UNKNOWN CATEGORY")) | I39: 549.14 | J39: =IF($A39="","",YEAR($A39)*100+MONTH($A39))
A40: 46101 | B40: EQ - Sole Prop Chequing | C40: Interac e-Transfer received from PACIFIC CITY DEVELOPMENTS INC. | D40: 2136.79 | E40: =IF($B40="","",IFERROR(INDEX('ACCOUNT MAP'!$C$6:$C$44,MATCH($B40,'ACCOUNT MAP'!$A$6:$A$44,0)),"! UNMAPPED ACCOUNT")) | F40: Client payment received | G40: =IF($F40="","",IFERROR(INDEX(CATEGORIES!$C$5:$C$49,MATCH($F40,CATEGORIES!$B$5:$B$49,0)),"! UNKNOWN CATEGORY")) | I40: 101.75 | J40: =IF($A40="","",YEAR($A40)*100+MONTH($A40))
A41: 46107 | B41: EQ - Sole Prop Chequing | C41: Interac e-Transfer sent to PND GRAVEL MART | D41: -53.2 | E41: =IF($B41="","",IFERROR(INDEX('ACCOUNT MAP'!$C$6:$C$44,MATCH($B41,'ACCOUNT MAP'!$A$6:$A$44,0)),"! UNMAPPED ACCOUNT")) | F41: Materials and plants | G41: =IF($F41="","",IFERROR(INDEX(CATEGORIES!$C$5:$C$49,MATCH($F41,CATEGORIES!$B$5:$B$49,0)),"! UNKNOWN CATEGORY")) | J41: =IF($A41="","",YEAR($A41)*100+MONTH($A41))
A42: 46107 | B42: EQ - Sole Prop Chequing | C42: Interac e-Transfer sent to PND GRAVEL MART | D42: -364 | E42: =IF($B42="","",IFERROR(INDEX('ACCOUNT MAP'!$C$6:$C$44,MATCH($B42,'ACCOUNT MAP'!$A$6:$A$44,0)),"! UNMAPPED ACCOUNT")) | F42: Materials and plants | G42: =IF($F42="","",IFERROR(INDEX(CATEGORIES!$C$5:$C$49,MATCH($F42,CATEGORIES!$B$5:$B$49,0)),"! UNKNOWN CATEGORY")) | J42: =IF($A42="","",YEAR($A42)*100+MONTH($A42))
A43: 46107 | B43: EQ - Sole Prop Chequing | C43: Interac e-Transfer sent to PND GRAVEL MART | D43: -316.41 | E43: =IF($B43="","",IFERROR(INDEX('ACCOUNT MAP'!$C$6:$C$44,MATCH($B43,'ACCOUNT MAP'!$A$6:$A$44,0)),"! UNMAPPED ACCOUNT")) | F43: Materials and plants | G43: =IF($F43="","",IFERROR(INDEX(CATEGORIES!$C$5:$C$49,MATCH($F43,CATEGORIES!$B$5:$B$49,0)),"! UNKNOWN CATEGORY")) | J43: =IF($A43="","",YEAR($A43)*100+MONTH($A43))
A44: 46108 | B44: EQ - Sole Prop Chequing | C44: Auto-withdrawal by AMEX BILL PYMT | D44: -7117.29 | E44: =IF($B44="","",IFERROR(INDEX('ACCOUNT MAP'!$C$6:$C$44,MATCH($B44,'ACCOUNT MAP'!$A$6:$A$44,0)),"! UNMAPPED ACCOUNT")) | F44: ! UNCLEAR - NEEDS REVIEW | G44: =IF($F44="","",IFERROR(INDEX(CATEGORIES!$C$5:$C$49,MATCH($F44,CATEGORIES!$B$5:$B$49,0)),"! UNKNOWN CATEGORY")) | J44: =IF($A44="","",YEAR($A44)*100+MONTH($A44)) | K44: Credit card payment — AMEX BILL PYMT
A45: 46111 | B45: EQ - Sole Prop Chequing | C45: Interac e-Transfer sent to Kierran Kivinen | D45: -566.8 | E45: =IF($B45="","",IFERROR(INDEX('ACCOUNT MAP'!$C$6:$C$44,MATCH($B45,'ACCOUNT MAP'!$A$6:$A$44,0)),"! UNMAPPED ACCOUNT")) | F45: Crew wages (net pay out) | G45: =IF($F45="","",IFERROR(INDEX(CATEGORIES!$C$5:$C$49,MATCH($F45,CATEGORIES!$B$5:$B$49,0)),"! UNKNOWN CATEGORY")) | J45: =IF($A45="","",YEAR($A45)*100+MONTH($A45))
A46: 46111 | B46: EQ - Sole Prop Chequing | C46: Interac e-Transfer sent to Kierran Kivinen | D46: -542.42 | E46: =IF($B46="","",IFERROR(INDEX('ACCOUNT MAP'!$C$6:$C$44,MATCH($B46,'ACCOUNT MAP'!$A$6:$A$44,0)),"! UNMAPPED ACCOUNT")) | F46: Crew wages (net pay out) | G46: =IF($F46="","",IFERROR(INDEX(CATEGORIES!$C$5:$C$49,MATCH($F46,CATEGORIES!$B$5:$B$49,0)),"! UNKNOWN CATEGORY")) | J46: =IF($A46="","",YEAR($A46)*100+MONTH($A46))
A47: 46112 | B47: EQ - Sole Prop Chequing | C47: Interac e-Transfer sent to Patrick Wong | D47: -312.37 | E47: =IF($B47="","",IFERROR(INDEX('ACCOUNT MAP'!$C$6:$C$44,MATCH($B47,'ACCOUNT MAP'!$A$6:$A$44,0)),"! UNMAPPED ACCOUNT")) | F47: ! UNCLEAR - NEEDS REVIEW | G47: =IF($F47="","",IFERROR(INDEX(CATEGORIES!$C$5:$C$49,MATCH($F47,CATEGORIES!$B$5:$B$49,0)),"! UNKNOWN CATEGORY")) | J47: =IF($A47="","",YEAR($A47)*100+MONTH($A47)) | K47: ? Crew or sub — Patrick Wong
A48: 46112 | B48: EQ - Sole Prop Chequing | C48: Interest received | D48: 40.56 | E48: =IF($B48="","",IFERROR(INDEX('ACCOUNT MAP'!$C$6:$C$44,MATCH($B48,'ACCOUNT MAP'!$A$6:$A$44,0)),"! UNMAPPED ACCOUNT")) | F48: Other business income | G48: =IF($F48="","",IFERROR(INDEX(CATEGORIES!$C$5:$C$49,MATCH($F48,CATEGORIES!$B$5:$B$49,0)),"! UNKNOWN CATEGORY")) | J48: =IF($A48="","",YEAR($A48)*100+MONTH($A48))
A49: 46113 | B49: EQ - Sole Prop Chequing | C49: Interac e-Transfer received from CAROL-ANN SAARI | D49: 10000 | E49: =IF($B49="","",IFERROR(INDEX('ACCOUNT MAP'!$C$6:$C$44,MATCH($B49,'ACCOUNT MAP'!$A$6:$A$44,0)),"! UNMAPPED ACCOUNT")) | F49: Client payment received | G49: =IF($F49="","",IFERROR(INDEX(CATEGORIES!$C$5:$C$49,MATCH($F49,CATEGORIES!$B$5:$B$49,0)),"! UNKNOWN CATEGORY")) | I49: 476.19 | J49: =IF($A49="","",YEAR($A49)*100+MONTH($A49))
A50: 46114 | B50: EQ - Sole Prop Chequing | C50: Interac e-Transfer sent to Myles (YGGDRASIL HORTICUL | D50: -1301.02 | E50: =IF($B50="","",IFERROR(INDEX('ACCOUNT MAP'!$C$6:$C$44,MATCH($B50,'ACCOUNT MAP'!$A$6:$A$44,0)),"! UNMAPPED ACCOUNT")) | F50: Materials and plants | G50: =IF($F50="","",IFERROR(INDEX(CATEGORIES!$C$5:$C$49,MATCH($F50,CATEGORIES!$B$5:$B$49,0)),"! UNKNOWN CATEGORY")) | J50: =IF($A50="","",YEAR($A50)*100+MONTH($A50))
A51: 46114 | B51: EQ - Sole Prop Chequing | C51: Interac e-Transfer received from CAROL-ANN SAARI | D51: 4594.07 | E51: =IF($B51="","",IFERROR(INDEX('ACCOUNT MAP'!$C$6:$C$44,MATCH($B51,'ACCOUNT MAP'!$A$6:$A$44,0)),"! UNMAPPED ACCOUNT")) | F51: Client payment received | G51: =IF($F51="","",IFERROR(INDEX(CATEGORIES!$C$5:$C$49,MATCH($F51,CATEGORIES!$B$5:$B$49,0)),"! UNKNOWN CATEGORY")) | I51: 218.77 | J51: =IF($A51="","",YEAR($A51)*100+MONTH($A51))
A52: 46118 | B52: EQ - Sole Prop Chequing | C52: Interac e-Transfer received from Ramsay P Attisha | D52: 1200 | E52: =IF($B52="","",IFERROR(INDEX('ACCOUNT MAP'!$C$6:$C$44,MATCH($B52,'ACCOUNT MAP'!$A$6:$A$44,0)),"! UNMAPPED ACCOUNT")) | F52: Client payment received | G52: =IF($F52="","",IFERROR(INDEX(CATEGORIES!$C$5:$C$49,MATCH($F52,CATEGORIES!$B$5:$B$49,0)),"! UNKNOWN CATEGORY")) | I52: 57.14 | J52: =IF($A52="","",YEAR($A52)*100+MONTH($A52))
A53: 46118 | B53: EQ - Sole Prop Chequing | C53: Interac e-Transfer received from CHRISTINE ADKINS | D53: 1212.75 | E53: =IF($B53="","",IFERROR(INDEX('ACCOUNT MAP'!$C$6:$C$44,MATCH($B53,'ACCOUNT MAP'!$A$6:$A$44,0)),"! UNMAPPED ACCOUNT")) | F53: Client payment received | G53: =IF($F53="","",IFERROR(INDEX(CATEGORIES!$C$5:$C$49,MATCH($F53,CATEGORIES!$B$5:$B$49,0)),"! UNKNOWN CATEGORY")) | I53: 57.75 | J53: =IF($A53="","",YEAR($A53)*100+MONTH($A53))
A54: 46118 | B54: EQ - Sole Prop Chequing | C54: Auto-withdrawal by AMEX BILL PYMT | D54: -2037.93 | E54: =IF($B54="","",IFERROR(INDEX('ACCOUNT MAP'!$C$6:$C$44,MATCH($B54,'ACCOUNT MAP'!$A$6:$A$44,0)),"! UNMAPPED ACCOUNT")) | F54: ! UNCLEAR - NEEDS REVIEW | G54: =IF($F54="","",IFERROR(INDEX(CATEGORIES!$C$5:$C$49,MATCH($F54,CATEGORIES!$B$5:$B$49,0)),"! UNKNOWN CATEGORY")) | J54: =IF($A54="","",YEAR($A54)*100+MONTH($A54)) | K54: Credit card payment — AMEX BILL PYMT
A55: 46118 | B55: EQ - Sole Prop Chequing | C55: Interac e-Transfer received from CHRISTINE ADRIENNE SCHWARTZ | D55: 183.75 | E55: =IF($B55="","",IFERROR(INDEX('ACCOUNT MAP'!$C$6:$C$44,MATCH($B55,'ACCOUNT MAP'!$A$6:$A$44,0)),"! UNMAPPED ACCOUNT")) | F55: Client payment received | G55: =IF($F55="","",IFERROR(INDEX(CATEGORIES!$C$5:$C$49,MATCH($F55,CATEGORIES!$B$5:$B$49,0)),"! UNKNOWN CATEGORY")) | I55: 8.75 | J55: =IF($A55="","",YEAR($A55)*100+MONTH($A55))
A56: 46122 | B56: EQ - Sole Prop Chequing | C56: Interac e-Transfer received from Filomena Giulione | D56: 425.25 | E56: =IF($B56="","",IFERROR(INDEX('ACCOUNT MAP'!$C$6:$C$44,MATCH($B56,'ACCOUNT MAP'!$A$6:$A$44,0)),"! UNMAPPED ACCOUNT")) | F56: Client payment received | G56: =IF($F56="","",IFERROR(INDEX(CATEGORIES!$C$5:$C$49,MATCH($F56,CATEGORIES!$B$5:$B$49,0)),"! UNKNOWN CATEGORY")) | I56: 20.25 | J56: =IF($A56="","",YEAR($A56)*100+MONTH($A56))
A57: 46123 | B57: EQ - Sole Prop Chequing | C57: Interac e-Transfer sent to Kevin | D57: -625 | E57: =IF($B57="","",IFERROR(INDEX('ACCOUNT MAP'!$C$6:$C$44,MATCH($B57,'ACCOUNT MAP'!$A$6:$A$44,0)),"! UNMAPPED ACCOUNT")) | F57: ! UNCLEAR - NEEDS REVIEW | G57: =IF($F57="","",IFERROR(INDEX(CATEGORIES!$C$5:$C$49,MATCH($F57,CATEGORIES!$B$5:$B$49,0)),"! UNKNOWN CATEGORY")) | J57: =IF($A57="","",YEAR($A57)*100+MONTH($A57)) | K57: ? Crew or sub — Kevin
A58: 46123 | B58: EQ - Sole Prop Chequing | C58: Interac e-Transfer sent to Kierran Kivinen | D58: -208.16 | E58: =IF($B58="","",IFERROR(INDEX('ACCOUNT MAP'!$C$6:$C$44,MATCH($B58,'ACCOUNT MAP'!$A$6:$A$44,0)),"! UNMAPPED ACCOUNT")) | F58: Crew wages (net pay out) | G58: =IF($F58="","",IFERROR(INDEX(CATEGORIES!$C$5:$C$49,MATCH($F58,CATEGORIES!$B$5:$B$49,0)),"! UNKNOWN CATEGORY")) | J58: =IF($A58="","",YEAR($A58)*100+MONTH($A58))
A59: 46124 | B59: EQ - Sole Prop Chequing | C59: Interac e-Transfer received from YUHUAN BAI | D59: 567 | E59: =IF($B59="","",IFERROR(INDEX('ACCOUNT MAP'!$C$6:$C$44,MATCH($B59,'ACCOUNT MAP'!$A$6:$A$44,0)),"! UNMAPPED ACCOUNT")) | F59: Client payment received | G59: =IF($F59="","",IFERROR(INDEX(CATEGORIES!$C$5:$C$49,MATCH($F59,CATEGORIES!$B$5:$B$49,0)),"! UNKNOWN CATEGORY")) | I59: 27 | J59: =IF($A59="","",YEAR($A59)*100+MONTH($A59))
A60: 46124 | B60: EQ - Sole Prop Chequing | C60: Interac e-Transfer received from CHRISTINE ADKINS | D60: 1400 | E60: =IF($B60="","",IFERROR(INDEX('ACCOUNT MAP'!$C$6:$C$44,MATCH($B60,'ACCOUNT MAP'!$A$6:$A$44,0)),"! UNMAPPED ACCOUNT")) | F60: Client payment received | G60: =IF($F60="","",IFERROR(INDEX(CATEGORIES!$C$5:$C$49,MATCH($F60,CATEGORIES!$B$5:$B$49,0)),"! UNKNOWN CATEGORY")) | I60: 66.67 | J60: =IF($A60="","",YEAR($A60)*100+MONTH($A60))
A61: 46125 | B61: EQ - Sole Prop Chequing | C61: Interac e-Transfer received from CHRISTINE ADKINS | D61: 863.52 | E61: =IF($B61="","",IFERROR(INDEX('ACCOUNT MAP'!$C$6:$C$44,MATCH($B61,'ACCOUNT MAP'!$A$6:$A$44,0)),"! UNMAPPED ACCOUNT")) | F61: Client payment received | G61: =IF($F61="","",IFERROR(INDEX(CATEGORIES!$C$5:$C$49,MATCH($F61,CATEGORIES!$B$5:$B$49,0)),"! UNKNOWN CATEGORY")) | I61: 41.12 | J61: =IF($A61="","",YEAR($A61)*100+MONTH($A61))
A62: 46125 | B62: EQ - Sole Prop Chequing | C62: Interac e-Transfer sent to Kierran Kivinen | D62: -1605.8 | E62: =IF($B62="","",IFERROR(INDEX('ACCOUNT MAP'!$C$6:$C$44,MATCH($B62,'ACCOUNT MAP'!$A$6:$A$44,0)),"! UNMAPPED ACCOUNT")) | F62: Crew wages (net pay out) | G62: =IF($F62="","",IFERROR(INDEX(CATEGORIES!$C$5:$C$49,MATCH($F62,CATEGORIES!$B$5:$B$49,0)),"! UNKNOWN CATEGORY")) | J62: =IF($A62="","",YEAR($A62)*100+MONTH($A62))
A63: 46125 | B63: EQ - Sole Prop Chequing | C63: Interac e-Transfer sent to Booker, Daniel | D63: -744.85 | E63: =IF($B63="","",IFERROR(INDEX('ACCOUNT MAP'!$C$6:$C$44,MATCH($B63,'ACCOUNT MAP'!$A$6:$A$44,0)),"! UNMAPPED ACCOUNT")) | F63: ! UNCLEAR - NEEDS REVIEW | G63: =IF($F63="","",IFERROR(INDEX(CATEGORIES!$C$5:$C$49,MATCH($F63,CATEGORIES!$B$5:$B$49,0)),"! UNKNOWN CATEGORY")) | J63: =IF($A63="","",YEAR($A63)*100+MONTH($A63)) | K63: ? Booker, Daniel — UNIDENTIFIED
A64: 46128 | B64: EQ - Sole Prop Chequing | C64: Interac e-Transfer sent to Booker, Daniel | D64: -100 | E64: =IF($B64="","",IFERROR(INDEX('ACCOUNT MAP'!$C$6:$C$44,MATCH($B64,'ACCOUNT MAP'!$A$6:$A$44,0)),"! UNMAPPED ACCOUNT")) | F64: ! UNCLEAR - NEEDS REVIEW | G64: =IF($F64="","",IFERROR(INDEX(CATEGORIES!$C$5:$C$49,MATCH($F64,CATEGORIES!$B$5:$B$49,0)),"! UNKNOWN CATEGORY")) | J64: =IF($A64="","",YEAR($A64)*100+MONTH($A64)) | K64: ? Booker, Daniel — UNIDENTIFIED
A65: 46129 | B65: EQ - Sole Prop Chequing | C65: Interac e-Transfer received from WILLIAM SANDERSON | D65: 446.25 | E65: =IF($B65="","",IFERROR(INDEX('ACCOUNT MAP'!$C$6:$C$44,MATCH($B65,'ACCOUNT MAP'!$A$6:$A$44,0)),"! UNMAPPED ACCOUNT")) | F65: Client payment received | G65: =IF($F65="","",IFERROR(INDEX(CATEGORIES!$C$5:$C$49,MATCH($F65,CATEGORIES!$B$5:$B$49,0)),"! UNKNOWN CATEGORY")) | I65: 21.25 | J65: =IF($A65="","",YEAR($A65)*100+MONTH($A65))
A66: 46129 | B66: EQ - Sole Prop Chequing | C66: Interac e-Transfer received from DAVID C NEWSOME | D66: 763.88 | E66: =IF($B66="","",IFERROR(INDEX('ACCOUNT MAP'!$C$6:$C$44,MATCH($B66,'ACCOUNT MAP'!$A$6:$A$44,0)),"! UNMAPPED ACCOUNT")) | F66: Client payment received | G66: =IF($F66="","",IFERROR(INDEX(CATEGORIES!$C$5:$C$49,MATCH($F66,CATEGORIES!$B$5:$B$49,0)),"! UNKNOWN CATEGORY")) | I66: 36.38 | J66: =IF($A66="","",YEAR($A66)*100+MONTH($A66))
A67: 46129 | B67: EQ - Sole Prop Chequing | C67: Auto-withdrawal by Gore Mutual | D67: -93.62 | E67: =IF($B67="","",IFERROR(INDEX('ACCOUNT MAP'!$C$6:$C$44,MATCH($B67,'ACCOUNT MAP'!$A$6:$A$44,0)),"! UNMAPPED ACCOUNT")) | F67: Liability insurance | G67: =IF($F67="","",IFERROR(INDEX(CATEGORIES!$C$5:$C$49,MATCH($F67,CATEGORIES!$B$5:$B$49,0)),"! UNKNOWN CATEGORY")) | J67: =IF($A67="","",YEAR($A67)*100+MONTH($A67))
A68: 46131 | B68: EQ - Sole Prop Chequing | C68: Interac e-Transfer received from DAVID ROBIN GREEN | D68: 2638.04 | E68: =IF($B68="","",IFERROR(INDEX('ACCOUNT MAP'!$C$6:$C$44,MATCH($B68,'ACCOUNT MAP'!$A$6:$A$44,0)),"! UNMAPPED ACCOUNT")) | F68: Client payment received | G68: =IF($F68="","",IFERROR(INDEX(CATEGORIES!$C$5:$C$49,MATCH($F68,CATEGORIES!$B$5:$B$49,0)),"! UNKNOWN CATEGORY")) | I68: 125.62 | J68: =IF($A68="","",YEAR($A68)*100+MONTH($A68))
A69: 46132 | B69: EQ - Sole Prop Chequing | C69: Interac e-Transfer received from Mark A | D69: 1690 | E69: =IF($B69="","",IFERROR(INDEX('ACCOUNT MAP'!$C$6:$C$44,MATCH($B69,'ACCOUNT MAP'!$A$6:$A$44,0)),"! UNMAPPED ACCOUNT")) | F69: Client payment received | G69: =IF($F69="","",IFERROR(INDEX(CATEGORIES!$C$5:$C$49,MATCH($F69,CATEGORIES!$B$5:$B$49,0)),"! UNKNOWN CATEGORY")) | I69: 80.48 | J69: =IF($A69="","",YEAR($A69)*100+MONTH($A69))
A70: 46133 | B70: EQ - Sole Prop Chequing | C70: Interac e-Transfer received from BRUCE D REID | D70: 393.75 | E70: =IF($B70="","",IFERROR(INDEX('ACCOUNT MAP'!$C$6:$C$44,MATCH($B70,'ACCOUNT MAP'!$A$6:$A$44,0)),"! UNMAPPED ACCOUNT")) | F70: Client payment received | G70: =IF($F70="","",IFERROR(INDEX(CATEGORIES!$C$5:$C$49,MATCH($F70,CATEGORIES!$B$5:$B$49,0)),"! UNKNOWN CATEGORY")) | I70: 18.75 | J70: =IF($A70="","",YEAR($A70)*100+MONTH($A70))
A71: 46134 | B71: EQ - Sole Prop Chequing | C71: Mobile cheque deposit | D71: 14962.5 | E71: =IF($B71="","",IFERROR(INDEX('ACCOUNT MAP'!$C$6:$C$44,MATCH($B71,'ACCOUNT MAP'!$A$6:$A$44,0)),"! UNMAPPED ACCOUNT")) | F71: Client payment received | G71: =IF($F71="","",IFERROR(INDEX(CATEGORIES!$C$5:$C$49,MATCH($F71,CATEGORIES!$B$5:$B$49,0)),"! UNKNOWN CATEGORY")) | I71: 712.5 | J71: =IF($A71="","",YEAR($A71)*100+MONTH($A71))
A72: 46134 | B72: EQ - Sole Prop Chequing | C72: Mobile cheque deposit | D72: 8887.98 | E72: =IF($B72="","",IFERROR(INDEX('ACCOUNT MAP'!$C$6:$C$44,MATCH($B72,'ACCOUNT MAP'!$A$6:$A$44,0)),"! UNMAPPED ACCOUNT")) | F72: Client payment received | G72: =IF($F72="","",IFERROR(INDEX(CATEGORIES!$C$5:$C$49,MATCH($F72,CATEGORIES!$B$5:$B$49,0)),"! UNKNOWN CATEGORY")) | I72: 423.24 | J72: =IF($A72="","",YEAR($A72)*100+MONTH($A72))
A73: 46137 | B73: EQ - Sole Prop Chequing | C73: Interac e-Transfer received from Robert Niven | D73: 2500 | E73: =IF($B73="","",IFERROR(INDEX('ACCOUNT MAP'!$C$6:$C$44,MATCH($B73,'ACCOUNT MAP'!$A$6:$A$44,0)),"! UNMAPPED ACCOUNT")) | F73: Client payment received | G73: =IF($F73="","",IFERROR(INDEX(CATEGORIES!$C$5:$C$49,MATCH($F73,CATEGORIES!$B$5:$B$49,0)),"! UNKNOWN CATEGORY")) | I73: 119.05 | J73: =IF($A73="","",YEAR($A73)*100+MONTH($A73))
A74: 46138 | B74: EQ - Sole Prop Chequing | C74: Interac e-Transfer received from Robert Niven | D74: 2500 | E74: =IF($B74="","",IFERROR(INDEX('ACCOUNT MAP'!$C$6:$C$44,MATCH($B74,'ACCOUNT MAP'!$A$6:$A$44,0)),"! UNMAPPED ACCOUNT")) | F74: Client payment received | G74: =IF($F74="","",IFERROR(INDEX(CATEGORIES!$C$5:$C$49,MATCH($F74,CATEGORIES!$B$5:$B$49,0)),"! UNKNOWN CATEGORY")) | I74: 119.05 | J74: =IF($A74="","",YEAR($A74)*100+MONTH($A74))
A75: 46139 | B75: EQ - Sole Prop Chequing | C75: Interac e-Transfer received from Robert Niven | D75: 2146.9 | E75: =IF($B75="","",IFERROR(INDEX('ACCOUNT MAP'!$C$6:$C$44,MATCH($B75,'ACCOUNT MAP'!$A$6:$A$44,0)),"! UNMAPPED ACCOUNT")) | F75: Client payment received | G75: =IF($F75="","",IFERROR(INDEX(CATEGORIES!$C$5:$C$49,MATCH($F75,CATEGORIES!$B$5:$B$49,0)),"! UNKNOWN CATEGORY")) | I75: 102.23 | J75: =IF($A75="","",YEAR($A75)*100+MONTH($A75))
A76: 46139 | B76: EQ - Sole Prop Chequing | C76: Interac e-Transfer received from Ramsay P Attisha | D76: 1200 | E76: =IF($B76="","",IFERROR(INDEX('ACCOUNT MAP'!$C$6:$C$44,MATCH($B76,'ACCOUNT MAP'!$A$6:$A$44,0)),"! UNMAPPED ACCOUNT")) | F76: Client payment received | G76: =IF($F76="","",IFERROR(INDEX(CATEGORIES!$C$5:$C$49,MATCH($F76,CATEGORIES!$B$5:$B$49,0)),"! UNKNOWN CATEGORY")) | I76: 57.14 | J76: =IF($A76="","",YEAR($A76)*100+MONTH($A76))
A77: 46139 | B77: EQ - Sole Prop Chequing | C77: Interac e-Transfer sent to Kierran Kivinen | D77: -1706.48 | E77: =IF($B77="","",IFERROR(INDEX('ACCOUNT MAP'!$C$6:$C$44,MATCH($B77,'ACCOUNT MAP'!$A$6:$A$44,0)),"! UNMAPPED ACCOUNT")) | F77: Crew wages (net pay out) | G77: =IF($F77="","",IFERROR(INDEX(CATEGORIES!$C$5:$C$49,MATCH($F77,CATEGORIES!$B$5:$B$49,0)),"! UNKNOWN CATEGORY")) | J77: =IF($A77="","",YEAR($A77)*100+MONTH($A77))
A78: 46139 | B78: EQ - Sole Prop Chequing | C78: Interac e-Transfer sent to Booker, Daniel | D78: -1082.6 | E78: =IF($B78="","",IFERROR(INDEX('ACCOUNT MAP'!$C$6:$C$44,MATCH($B78,'ACCOUNT MAP'!$A$6:$A$44,0)),"! UNMAPPED ACCOUNT")) | F78: ! UNCLEAR - NEEDS REVIEW | G78: =IF($F78="","",IFERROR(INDEX(CATEGORIES!$C$5:$C$49,MATCH($F78,CATEGORIES!$B$5:$B$49,0)),"! UNKNOWN CATEGORY")) | J78: =IF($A78="","",YEAR($A78)*100+MONTH($A78)) | K78: ? Booker, Daniel — UNIDENTIFIED
A79: 46139 | B79: EQ - Sole Prop Chequing | C79: Interac e-Transfer sent to Booker, Daniel | D79: -100 | E79: =IF($B79="","",IFERROR(INDEX('ACCOUNT MAP'!$C$6:$C$44,MATCH($B79,'ACCOUNT MAP'!$A$6:$A$44,0)),"! UNMAPPED ACCOUNT")) | F79: ! UNCLEAR - NEEDS REVIEW | G79: =IF($F79="","",IFERROR(INDEX(CATEGORIES!$C$5:$C$49,MATCH($F79,CATEGORIES!$B$5:$B$49,0)),"! UNKNOWN CATEGORY")) | J79: =IF($A79="","",YEAR($A79)*100+MONTH($A79)) | K79: ? Booker, Daniel — UNIDENTIFIED
A80: 46140 | B80: EQ - Sole Prop Chequing | C80: Interac e-Transfer sent to PND | D80: -711.2 | E80: =IF($B80="","",IFERROR(INDEX('ACCOUNT MAP'!$C$6:$C$44,MATCH($B80,'ACCOUNT MAP'!$A$6:$A$44,0)),"! UNMAPPED ACCOUNT")) | F80: Materials and plants | G80: =IF($F80="","",IFERROR(INDEX(CATEGORIES!$C$5:$C$49,MATCH($F80,CATEGORIES!$B$5:$B$49,0)),"! UNKNOWN CATEGORY")) | J80: =IF($A80="","",YEAR($A80)*100+MONTH($A80))
A81: 46140 | B81: EQ - Sole Prop Chequing | C81: Interac e-Transfer sent to Canadian Tire Bank | D81: -545.37 | E81: =IF($B81="","",IFERROR(INDEX('ACCOUNT MAP'!$C$6:$C$44,MATCH($B81,'ACCOUNT MAP'!$A$6:$A$44,0)),"! UNMAPPED ACCOUNT")) | F81: ! UNCLEAR - NEEDS REVIEW | G81: =IF($F81="","",IFERROR(INDEX(CATEGORIES!$C$5:$C$49,MATCH($F81,CATEGORIES!$B$5:$B$49,0)),"! UNKNOWN CATEGORY")) | J81: =IF($A81="","",YEAR($A81)*100+MONTH($A81)) | K81: Credit card payment — Canadian Tire Bank
A82: 46140 | B82: EQ - Sole Prop Chequing | C82: Interac e-Transfer received from PACIFIC CITY DEVELOPMENTS INC. | D82: 4201 | E82: =IF($B82="","",IFERROR(INDEX('ACCOUNT MAP'!$C$6:$C$44,MATCH($B82,'ACCOUNT MAP'!$A$6:$A$44,0)),"! UNMAPPED ACCOUNT")) | F82: Client payment received | G82: =IF($F82="","",IFERROR(INDEX(CATEGORIES!$C$5:$C$49,MATCH($F82,CATEGORIES!$B$5:$B$49,0)),"! UNKNOWN CATEGORY")) | I82: 200.05 | J82: =IF($A82="","",YEAR($A82)*100+MONTH($A82))
A83: 46142 | B83: EQ - Sole Prop Chequing | C83: Interac e-Transfer sent to Booker, Daniel | D83: -94.38 | E83: =IF($B83="","",IFERROR(INDEX('ACCOUNT MAP'!$C$6:$C$44,MATCH($B83,'ACCOUNT MAP'!$A$6:$A$44,0)),"! UNMAPPED ACCOUNT")) | F83: ! UNCLEAR - NEEDS REVIEW | G83: =IF($F83="","",IFERROR(INDEX(CATEGORIES!$C$5:$C$49,MATCH($F83,CATEGORIES!$B$5:$B$49,0)),"! UNKNOWN CATEGORY")) | J83: =IF($A83="","",YEAR($A83)*100+MONTH($A83)) | K83: ? Booker, Daniel — UNIDENTIFIED
A84: 46142 | B84: EQ - Sole Prop Chequing | C84: Interest received | D84: 80.07 | E84: =IF($B84="","",IFERROR(INDEX('ACCOUNT MAP'!$C$6:$C$44,MATCH($B84,'ACCOUNT MAP'!$A$6:$A$44,0)),"! UNMAPPED ACCOUNT")) | F84: Other business income | G84: =IF($F84="","",IFERROR(INDEX(CATEGORIES!$C$5:$C$49,MATCH($F84,CATEGORIES!$B$5:$B$49,0)),"! UNKNOWN CATEGORY")) | J84: =IF($A84="","",YEAR($A84)*100+MONTH($A84))
A85: 46143 | B85: EQ - Sole Prop Chequing | C85: Interac e-Transfer sent to Booker, Daniel | D85: -100 | E85: =IF($B85="","",IFERROR(INDEX('ACCOUNT MAP'!$C$6:$C$44,MATCH($B85,'ACCOUNT MAP'!$A$6:$A$44,0)),"! UNMAPPED ACCOUNT")) | F85: ! UNCLEAR - NEEDS REVIEW | G85: =IF($F85="","",IFERROR(INDEX(CATEGORIES!$C$5:$C$49,MATCH($F85,CATEGORIES!$B$5:$B$49,0)),"! UNKNOWN CATEGORY")) | J85: =IF($A85="","",YEAR($A85)*100+MONTH($A85)) | K85: ? Booker, Daniel — UNIDENTIFIED
A86: 46143 | B86: EQ - Sole Prop Chequing | C86: Interac e-Transfer received from LYNN KATHLEEN MARINI | D86: 315 | E86: =IF($B86="","",IFERROR(INDEX('ACCOUNT MAP'!$C$6:$C$44,MATCH($B86,'ACCOUNT MAP'!$A$6:$A$44,0)),"! UNMAPPED ACCOUNT")) | F86: Client payment received | G86: =IF($F86="","",IFERROR(INDEX(CATEGORIES!$C$5:$C$49,MATCH($F86,CATEGORIES!$B$5:$B$49,0)),"! UNKNOWN CATEGORY")) | I86: 15 | J86: =IF($A86="","",YEAR($A86)*100+MONTH($A86))
A87: 46145 | B87: EQ - Sole Prop Chequing | C87: Mobile cheque deposit | D87: 689.07 | E87: =IF($B87="","",IFERROR(INDEX('ACCOUNT MAP'!$C$6:$C$44,MATCH($B87,'ACCOUNT MAP'!$A$6:$A$44,0)),"! UNMAPPED ACCOUNT")) | F87: Client payment received | G87: =IF($F87="","",IFERROR(INDEX(CATEGORIES!$C$5:$C$49,MATCH($F87,CATEGORIES!$B$5:$B$49,0)),"! UNKNOWN CATEGORY")) | I87: 32.81 | J87: =IF($A87="","",YEAR($A87)*100+MONTH($A87))
A88: 46145 | B88: EQ - Sole Prop Chequing | C88: Mobile cheque deposit | D88: 2932.17 | E88: =IF($B88="","",IFERROR(INDEX('ACCOUNT MAP'!$C$6:$C$44,MATCH($B88,'ACCOUNT MAP'!$A$6:$A$44,0)),"! UNMAPPED ACCOUNT")) | F88: Client payment received | G88: =IF($F88="","",IFERROR(INDEX(CATEGORIES!$C$5:$C$49,MATCH($F88,CATEGORIES!$B$5:$B$49,0)),"! UNKNOWN CATEGORY")) | I88: 139.63 | J88: =IF($A88="","",YEAR($A88)*100+MONTH($A88))
A89: 46147 | B89: EQ - Sole Prop Chequing | C89: Interac e-Transfer sent to Booker, Daniel | D89: -204.05 | E89: =IF($B89="","",IFERROR(INDEX('ACCOUNT MAP'!$C$6:$C$44,MATCH($B89,'ACCOUNT MAP'!$A$6:$A$44,0)),"! UNMAPPED ACCOUNT")) | F89: ! UNCLEAR - NEEDS REVIEW | G89: =IF($F89="","",IFERROR(INDEX(CATEGORIES!$C$5:$C$49,MATCH($F89,CATEGORIES!$B$5:$B$49,0)),"! UNKNOWN CATEGORY")) | J89: =IF($A89="","",YEAR($A89)*100+MONTH($A89)) | K89: ? Booker, Daniel — UNIDENTIFIED
A90: 46147 | B90: EQ - Sole Prop Chequing | C90: Interac e-Transfer sent to Dean (black box) | D90: -2431.78 | E90: =IF($B90="","",IFERROR(INDEX('ACCOUNT MAP'!$C$6:$C$44,MATCH($B90,'ACCOUNT MAP'!$A$6:$A$44,0)),"! UNMAPPED ACCOUNT")) | F90: Materials and plants | G90: =IF($F90="","",IFERROR(INDEX(CATEGORIES!$C$5:$C$49,MATCH($F90,CATEGORIES!$B$5:$B$49,0)),"! UNKNOWN CATEGORY")) | J90: =IF($A90="","",YEAR($A90)*100+MONTH($A90))
A91: 46147 | B91: EQ - Sole Prop Chequing | C91: Interac e-Transfer sent to Canadian Tire Bank | D91: -545.37 | E91: =IF($B91="","",IFERROR(INDEX('ACCOUNT MAP'!$C$6:$C$44,MATCH($B91,'ACCOUNT MAP'!$A$6:$A$44,0)),"! UNMAPPED ACCOUNT")) | F91: ! UNCLEAR - NEEDS REVIEW | G91: =IF($F91="","",IFERROR(INDEX(CATEGORIES!$C$5:$C$49,MATCH($F91,CATEGORIES!$B$5:$B$49,0)),"! UNKNOWN CATEGORY")) | J91: =IF($A91="","",YEAR($A91)*100+MONTH($A91)) | K91: Credit card payment — Canadian Tire Bank
A92: 46147 | B92: EQ - Sole Prop Chequing | C92: Interac e-Transfer sent to Kyle (Personal Account) | D92: -1600 | E92: =IF($B92="","",IFERROR(INDEX('ACCOUNT MAP'!$C$6:$C$44,MATCH($B92,'ACCOUNT MAP'!$A$6:$A$44,0)),"! UNMAPPED ACCOUNT")) | F92: Owner draw (sole prop) | G92: =IF($F92="","",IFERROR(INDEX(CATEGORIES!$C$5:$C$49,MATCH($F92,CATEGORIES!$B$5:$B$49,0)),"! UNKNOWN CATEGORY")) | J92: =IF($A92="","",YEAR($A92)*100+MONTH($A92))
A93: 46148 | B93: EQ - Sole Prop Chequing | C93: Interac e-Transfer received from John Woods | D93: 441 | E93: =IF($B93="","",IFERROR(INDEX('ACCOUNT MAP'!$C$6:$C$44,MATCH($B93,'ACCOUNT MAP'!$A$6:$A$44,0)),"! UNMAPPED ACCOUNT")) | F93: Client payment received | G93: =IF($F93="","",IFERROR(INDEX(CATEGORIES!$C$5:$C$49,MATCH($F93,CATEGORIES!$B$5:$B$49,0)),"! UNKNOWN CATEGORY")) | I93: 21 | J93: =IF($A93="","",YEAR($A93)*100+MONTH($A93))
A94: 46148 | B94: EQ - Sole Prop Chequing | C94: Auto-withdrawal by AMEX BILL PYMT | D94: -1326.78 | E94: =IF($B94="","",IFERROR(INDEX('ACCOUNT MAP'!$C$6:$C$44,MATCH($B94,'ACCOUNT MAP'!$A$6:$A$44,0)),"! UNMAPPED ACCOUNT")) | F94: ! UNCLEAR - NEEDS REVIEW | G94: =IF($F94="","",IFERROR(INDEX(CATEGORIES!$C$5:$C$49,MATCH($F94,CATEGORIES!$B$5:$B$49,0)),"! UNKNOWN CATEGORY")) | J94: =IF($A94="","",YEAR($A94)*100+MONTH($A94)) | K94: Credit card payment — AMEX BILL PYMT
A95: 46149 | B95: EQ - Sole Prop Chequing | C95: Mobile cheque deposit | D95: 32500 | E95: =IF($B95="","",IFERROR(INDEX('ACCOUNT MAP'!$C$6:$C$44,MATCH($B95,'ACCOUNT MAP'!$A$6:$A$44,0)),"! UNMAPPED ACCOUNT")) | F95: Client payment received | G95: =IF($F95="","",IFERROR(INDEX(CATEGORIES!$C$5:$C$49,MATCH($F95,CATEGORIES!$B$5:$B$49,0)),"! UNKNOWN CATEGORY")) | I95: 1547.62 | J95: =IF($A95="","",YEAR($A95)*100+MONTH($A95))
A96: 46149 | B96: EQ - Sole Prop Chequing | C96: Mobile cheque deposit | D96: 10000 | E96: =IF($B96="","",IFERROR(INDEX('ACCOUNT MAP'!$C$6:$C$44,MATCH($B96,'ACCOUNT MAP'!$A$6:$A$44,0)),"! UNMAPPED ACCOUNT")) | F96: Client payment received | G96: =IF($F96="","",IFERROR(INDEX(CATEGORIES!$C$5:$C$49,MATCH($F96,CATEGORIES!$B$5:$B$49,0)),"! UNKNOWN CATEGORY")) | I96: 476.19 | J96: =IF($A96="","",YEAR($A96)*100+MONTH($A96))
A97: 46149 | B97: EQ - Sole Prop Chequing | C97: Interac e-Transfer sent to Kevin | D97: -625 | E97: =IF($B97="","",IFERROR(INDEX('ACCOUNT MAP'!$C$6:$C$44,MATCH($B97,'ACCOUNT MAP'!$A$6:$A$44,0)),"! UNMAPPED ACCOUNT")) | F97: ! UNCLEAR - NEEDS REVIEW | G97: =IF($F97="","",IFERROR(INDEX(CATEGORIES!$C$5:$C$49,MATCH($F97,CATEGORIES!$B$5:$B$49,0)),"! UNKNOWN CATEGORY")) | J97: =IF($A97="","",YEAR($A97)*100+MONTH($A97)) | K97: ? Crew or sub — Kevin
A98: 46149 | B98: EQ - Sole Prop Chequing | C98: Mobile cheque deposit | D98: -10000 | E98: =IF($B98="","",IFERROR(INDEX('ACCOUNT MAP'!$C$6:$C$44,MATCH($B98,'ACCOUNT MAP'!$A$6:$A$44,0)),"! UNMAPPED ACCOUNT")) | F98: Client payment received | G98: =IF($F98="","",IFERROR(INDEX(CATEGORIES!$C$5:$C$49,MATCH($F98,CATEGORIES!$B$5:$B$49,0)),"! UNKNOWN CATEGORY")) | J98: =IF($A98="","",YEAR($A98)*100+MONTH($A98))
A99: 46150 | B99: EQ - Sole Prop Chequing | C99: Mobile cheque deposit | D99: 10000 | E99: =IF($B99="","",IFERROR(INDEX('ACCOUNT MAP'!$C$6:$C$44,MATCH($B99,'ACCOUNT MAP'!$A$6:$A$44,0)),"! UNMAPPED ACCOUNT")) | F99: Client payment received | G99: =IF($F99="","",IFERROR(INDEX(CATEGORIES!$C$5:$C$49,MATCH($F99,CATEGORIES!$B$5:$B$49,0)),"! UNKNOWN CATEGORY")) | I99: 476.19 | J99: =IF($A99="","",YEAR($A99)*100+MONTH($A99))
A100: 46150 | B100: EQ - Sole Prop Chequing | C100: Interac e-Transfer sent to PND | D100: -764.05 | E100: =IF($B100="","",IFERROR(INDEX('ACCOUNT MAP'!$C$6:$C$44,MATCH($B100,'ACCOUNT MAP'!$A$6:$A$44,0)),"! UNMAPPED ACCOUNT")) | F100: Materials and plants | G100: =IF($F100="","",IFERROR(INDEX(CATEGORIES!$C$5:$C$49,MATCH($F100,CATEGORIES!$B$5:$B$49,0)),"! UNKNOWN CATEGORY")) | J100: =IF($A100="","",YEAR($A100)*100+MONTH($A100))
...

Sheet CASH RECONCILIATION
A1: Cash Reconciliation — Feb 1, 2026 to Jan 31, 2027
A2: Opening + inflows - outflows = closing, per entity. If the difference row is not zero, the data is incomplete. Do not force it — the gap is the finding.
A4: Line | B4: Personal | C4: Sole Prop | D4: Corporation | E4: TOTAL
A5: Opening cash immediately before Feb 1 | B5: ='ACCOUNT MAP'!$E$47 | C5: ='ACCOUNT MAP'!$E$48 | D5: ='ACCOUNT MAP'!$E$49 | E5: =SUM(B5:D5)
A6: Revenue collected (gross, includes GST) | B6: =SUMIFS(TRANSACTIONS!$D$5:$D$244,TRANSACTIONS!$E$5:$E$244,"Personal",TRANSACTIONS!$G$5:$G$244,"Revenue") | C6: =SUMIFS(TRANSACTIONS!$D$5:$D$244,TRANSACTIONS!$E$5:$E$244,"Sole Prop",TRANSACTIONS!$G$5:$G$244,"Revenue") | D6: =SUMIFS(TRANSACTIONS!$D$5:$D$244,TRANSACTIONS!$E$5:$E$244,"Corporation",TRANSACTIONS!$G$5:$G$244,"Revenue") | E6: =SUM(B6:D6)
A7: Personal income received | B7: =SUMIFS(TRANSACTIONS!$D$5:$D$244,TRANSACTIONS!$E$5:$E$244,"Personal",TRANSACTIONS!$G$5:$G$244,"Personal Income") | C7: =SUMIFS(TRANSACTIONS!$D$5:$D$244,TRANSACTIONS!$E$5:$E$244,"Sole Prop",TRANSACTIONS!$G$5:$G$244,"Personal Income") | D7: =SUMIFS(TRANSACTIONS!$D$5:$D$244,TRANSACTIONS!$E$5:$E$244,"Corporation",TRANSACTIONS!$G$5:$G$244,"Personal Income") | E7: =SUM(B7:D7)
A8: Financing proceeds / capital contributed | B8: =SUMIFS(TRANSACTIONS!$D$5:$D$244,TRANSACTIONS!$E$5:$E$244,"Personal",TRANSACTIONS!$G$5:$G$244,"Financing") | C8: =SUMIFS(TRANSACTIONS!$D$5:$D$244,TRANSACTIONS!$E$5:$E$244,"Sole Prop",TRANSACTIONS!$G$5:$G$244,"Financing") | D8: =SUMIFS(TRANSACTIONS!$D$5:$D$244,TRANSACTIONS!$E$5:$E$244,"Corporation",TRANSACTIONS!$G$5:$G$244,"Financing") | E8: =SUM(B8:D8)
A9: Investments bought and sold (net) | B9: =SUMIFS(TRANSACTIONS!$D$5:$D$244,TRANSACTIONS!$E$5:$E$244,"Personal",TRANSACTIONS!$G$5:$G$244,"Investment") | C9: =SUMIFS(TRANSACTIONS!$D$5:$D$244,TRANSACTIONS!$E$5:$E$244,"Sole Prop",TRANSACTIONS!$G$5:$G$244,"Investment") | D9: =SUMIFS(TRANSACTIONS!$D$5:$D$244,TRANSACTIONS!$E$5:$E$244,"Corporation",TRANSACTIONS!$G$5:$G$244,"Investment") | E9: =SUM(B9:D9)
A10: COGS and materials paid | B10: =SUMIFS(TRANSACTIONS!$D$5:$D$244,TRANSACTIONS!$E$5:$E$244,"Personal",TRANSACTIONS!$G$5:$G$244,"COGS") | C10: =SUMIFS(TRANSACTIONS!$D$5:$D$244,TRANSACTIONS!$E$5:$E$244,"Sole Prop",TRANSACTIONS!$G$5:$G$244,"COGS") | D10: =SUMIFS(TRANSACTIONS!$D$5:$D$244,TRANSACTIONS!$E$5:$E$244,"Corporation",TRANSACTIONS!$G$5:$G$244,"COGS") | E10: =SUM(B10:D10)
A11: Operating expenses paid | B11: =SUMIFS(TRANSACTIONS!$D$5:$D$244,TRANSACTIONS!$E$5:$E$244,"Personal",TRANSACTIONS!$G$5:$G$244,"Operating Expense") | C11: =SUMIFS(TRANSACTIONS!$D$5:$D$244,TRANSACTIONS!$E$5:$E$244,"Sole Prop",TRANSACTIONS!$G$5:$G$244,"Operating Expense") | D11: =SUMIFS(TRANSACTIONS!$D$5:$D$244,TRANSACTIONS!$E$5:$E$244,"Corporation",TRANSACTIONS!$G$5:$G$244,"Operating Expense") | E11: =SUM(B11:D11)
A12: Payroll paid | B12: =SUMIFS(TRANSACTIONS!$D$5:$D$244,TRANSACTIONS!$E$5:$E$244,"Personal",TRANSACTIONS!$G$5:$G$244,"Payroll") | C12: =SUMIFS(TRANSACTIONS!$D$5:$D$244,TRANSACTIONS!$E$5:$E$244,"Sole Prop",TRANSACTIONS!$G$5:$G$244,"Payroll") | D12: =SUMIFS(TRANSACTIONS!$D$5:$D$244,TRANSACTIONS!$E$5:$E$244,"Corporation",TRANSACTIONS!$G$5:$G$244,"Payroll") | E12: =SUM(B12:D12)
A13: Taxes and remittances paid | B13: =SUMIFS(TRANSACTIONS!$D$5:$D$244,TRANSACTIONS!$E$5:$E$244,"Personal",TRANSACTIONS!$G$5:$G$244,"Tax/Remittance") | C13: =SUMIFS(TRANSACTIONS!$D$5:$D$244,TRANSACTIONS!$E$5:$E$244,"Sole Prop",TRANSACTIONS!$G$5:$G$244,"Tax/Remittance") | D13: =SUMIFS(TRANSACTIONS!$D$5:$D$244,TRANSACTIONS!$E$5:$E$244,"Corporation",TRANSACTIONS!$G$5:$G$244,"Tax/Remittance") | E13: =SUM(B13:D13)
A14: Owner draws / compensation | B14: =SUMIFS(TRANSACTIONS!$D$5:$D$244,TRANSACTIONS!$E$5:$E$244,"Personal",TRANSACTIONS!$G$5:$G$244,"Owner Draw/Comp") | C14: =SUMIFS(TRANSACTIONS!$D$5:$D$244,TRANSACTIONS!$E$5:$E$244,"Sole Prop",TRANSACTIONS!$G$5:$G$244,"Owner Draw/Comp") | D14: =SUMIFS(TRANSACTIONS!$D$5:$D$244,TRANSACTIONS!$E$5:$E$244,"Corporation",TRANSACTIONS!$G$5:$G$244,"Owner Draw/Comp") | E14: =SUM(B14:D14)
A15: Capital purchases (vehicles, equipment) | B15: =SUMIFS(TRANSACTIONS!$D$5:$D$244,TRANSACTIONS!$E$5:$E$244,"Personal",TRANSACTIONS!$G$5:$G$244,"Capital Purchase") | C15: =SUMIFS(TRANSACTIONS!$D$5:$D$244,TRANSACTIONS!$E$5:$E$244,"Sole Prop",TRANSACTIONS!$G$5:$G$244,"Capital Purchase") | D15: =SUMIFS(TRANSACTIONS!$D$5:$D$244,TRANSACTIONS!$E$5:$E$244,"Corporation",TRANSACTIONS!$G$5:$G$244,"Capital Purchase") | E15: =SUM(B15:D15)
A16: Personal expenses paid | B16: =SUMIFS(TRANSACTIONS!$D$5:$D$244,TRANSACTIONS!$E$5:$E$244,"Personal",TRANSACTIONS!$G$5:$G$244,"Personal Expense") | C16: =SUMIFS(TRANSACTIONS!$D$5:$D$244,TRANSACTIONS!$E$5:$E$244,"Sole Prop",TRANSACTIONS!$G$5:$G$244,"Personal Expense") | D16: =SUMIFS(TRANSACTIONS!$D$5:$D$244,TRANSACTIONS!$E$5:$E$244,"Corporation",TRANSACTIONS!$G$5:$G$244,"Personal Expense") | E16: =SUM(B16:D16)
A17: INTER-ACCOUNT / INTER-ENTITY TRANSFERS (net) | B17: =SUMIFS(TRANSACTIONS!$D$5:$D$244,TRANSACTIONS!$E$5:$E$244,"Personal",TRANSACTIONS!$G$5:$G$244,"Transfer") | C17: =SUMIFS(TRANSACTIONS!$D$5:$D$244,TRANSACTIONS!$E$5:$E$244,"Sole Prop",TRANSACTIONS!$G$5:$G$244,"Transfer") | D17: =SUMIFS(TRANSACTIONS!$D$5:$D$244,TRANSACTIONS!$E$5:$E$244,"Corporation",TRANSACTIONS!$G$5:$G$244,"Transfer") | E17: =SUM(B17:D17)
A18: Unclassified — needs review | B18: =SUMIFS(TRANSACTIONS!$D$5:$D$244,TRANSACTIONS!$E$5:$E$244,"Personal",TRANSACTIONS!$G$5:$G$244,"Review") | C18: =SUMIFS(TRANSACTIONS!$D$5:$D$244,TRANSACTIONS!$E$5:$E$244,"Sole Prop",TRANSACTIONS!$G$5:$G$244,"Review") | D18: =SUMIFS(TRANSACTIONS!$D$5:$D$244,TRANSACTIONS!$E$5:$E$244,"Corporation",TRANSACTIONS!$G$5:$G$244,"Review") | E18: =SUM(B18:D18)
A19: CALCULATED ENDING CASH | B19: =SUM(B5:B18) | C19: =SUM(C5:C18) | D19: =SUM(D5:D18) | E19: =SUM(E5:E18)
A20: Actual bank balance at Jan 31 (you enter this) | C20: 67159.36 | D20: 32107.9 | E20: =SUM(B20:D20)
A21: DIFFERENCE — must be zero | B21: =B20-B19 | C21: =C20-C19 | D21: =D20-D19 | E21: =E20-E19
A23: A non-zero difference means one of: a missing statement month, a transaction you have not entered, an account missing from ACCOUNT MAP, or a wrong opening balance.
A24: Transfers net to roughly zero across the TOTAL column. If the total transfer line is materially non-zero, you have a transfer entered on one side only — that is the classic double-count.
A25: This reconciliation is the audit trail. Every figure elsewhere in this workbook depends on it balancing.

Sheet MONTH BY MONTH
A1: Month by Month — Feb 2026 through Jan 2027
A2: Signs are natural: money in is positive, money out is negative, so every row adds up to the net change. Transfers are excluded from the operating columns but included in ending cash.
A4: Month | B4: Month key | C4: Sole prop revenue (gross) | D4: less GST collected | E4: Sole prop revenue ex-GST | F4: Corp revenue (gross) | G4: less GST collected | H4: Corp revenue ex-GST | I4: COGS / materials | J4: Operating expenses | K4: Payroll | L4: Taxes and remittances | M4: Owner draws / comp | N4: Capital purchases | O4: Financing (net) | P4: Operating cash flow | Q4: Net business cash change | R4: Personal cash change | S4: Ending sole prop cash | T4: Ending corp cash | U4: Ending personal cash | V4: TOTAL LIQUID CASH
A5: Opening (Jan 31, 2026) | S5: ='ACCOUNT MAP'!$E$48 | T5: ='ACCOUNT MAP'!$E$49 | U5: ='ACCOUNT MAP'!$E$47 | V5: =SUM(S5:U5)
A6: Feb 2026 | B6: 202602 | C6: =SUMIFS(TRANSACTIONS!$D$5:$D$244,TRANSACTIONS!$E$5:$E$244,"Sole Prop",TRANSACTIONS!$G$5:$G$244,"Revenue",TRANSACTIONS!$J$5:$J$244,$B6) | D6: =-SUMIFS(TRANSACTIONS!$I$5:$I$244,TRANSACTIONS!$E$5:$E$244,"Sole Prop",TRANSACTIONS!$G$5:$G$244,"Revenue",TRANSACTIONS!$J$5:$J$244,$B6) | E6: =C6+D6 | F6: =SUMIFS(TRANSACTIONS!$D$5:$D$244,TRANSACTIONS!$E$5:$E$244,"Corporation",TRANSACTIONS!$G$5:$G$244,"Revenue",TRANSACTIONS!$J$5:$J$244,$B6) | G6: =-SUMIFS(TRANSACTIONS!$I$5:$I$244,TRANSACTIONS!$E$5:$E$244,"Corporation",TRANSACTIONS!$G$5:$G$244,"Revenue",TRANSACTIONS!$J$5:$J$244,$B6) | H6: =F6+G6 | I6: =(SUMIFS(TRANSACTIONS!$D$5:$D$244,TRANSACTIONS!$E$5:$E$244,"Sole Prop",TRANSACTIONS!$G$5:$G$244,"COGS",TRANSACTIONS!$J$5:$J$244,$B6)+SUMIFS(TRANSACTIONS!$D$5:$D$244,TRANSACTIONS!$E$5:$E$244,"Corporation",TRANSACTIONS!$G$5:$G$244,"COGS",TRANSACTIONS!$J$5:$J$244,$B6)) | J6: =(SUMIFS(TRANSACTIONS!$D$5:$D$244,TRANSACTIONS!$E$5:$E$244,"Sole Prop",TRANSACTIONS!$G$5:$G$244,"Operating Expense",TRANSACTIONS!$J$5:$J$244,$B6)+SUMIFS(TRANSACTIONS!$D$5:$D$244,TRANSACTIONS!$E$5:$E$244,"Corporation",TRANSACTIONS!$G$5:$G$244,"Operating Expense",TRANSACTIONS!$J$5:$J$244,$B6)) | K6: =(SUMIFS(TRANSACTIONS!$D$5:$D$244,TRANSACTIONS!$E$5:$E$244,"Sole Prop",TRANSACTIONS!$G$5:$G$244,"Payroll",TRANSACTIONS!$J$5:$J$244,$B6)+SUMIFS(TRANSACTIONS!$D$5:$D$244,TRANSACTIONS!$E$5:$E$244,"Corporation",TRANSACTIONS!$G$5:$G$244,"Payroll",TRANSACTIONS!$J$5:$J$244,$B6)) | L6: =(SUMIFS(TRANSACTIONS!$D$5:$D$244,TRANSACTIONS!$E$5:$E$244,"Sole Prop",TRANSACTIONS!$G$5:$G$244,"Tax/Remittance",TRANSACTIONS!$J$5:$J$244,$B6)+SUMIFS(TRANSACTIONS!$D$5:$D$244,TRANSACTIONS!$E$5:$E$244,"Corporation",TRANSACTIONS!$G$5:$G$244,"Tax/Remittance",TRANSACTIONS!$J$5:$J$244,$B6)) | M6: =(SUMIFS(TRANSACTIONS!$D$5:$D$244,TRANSACTIONS!$E$5:$E$244,"Sole Prop",TRANSACTIONS!$G$5:$G$244,"Owner Draw/Comp",TRANSACTIONS!$J$5:$J$244,$B6)+SUMIFS(TRANSACTIONS!$D$5:$D$244,TRANSACTIONS!$E$5:$E$244,"Corporation",TRANSACTIONS!$G$5:$G$244,"Owner Draw/Comp",TRANSACTIONS!$J$5:$J$244,$B6)) | N6: =(SUMIFS(TRANSACTIONS!$D$5:$D$244,TRANSACTIONS!$E$5:$E$244,"Sole Prop",TRANSACTIONS!$G$5:$G$244,"Capital Purchase",TRANSACTIONS!$J$5:$J$244,$B6)+SUMIFS(TRANSACTIONS!$D$5:$D$244,TRANSACTIONS!$E$5:$E$244,"Corporation",TRANSACTIONS!$G$5:$G$244,"Capital Purchase",TRANSACTIONS!$J$5:$J$244,$B6)) | O6: =(SUMIFS(TRANSACTIONS!$D$5:$D$244,TRANSACTIONS!$E$5:$E$244,"Sole Prop",TRANSACTIONS!$G$5:$G$244,"Financing",TRANSACTIONS!$J$5:$J$244,$B6)+SUMIFS(TRANSACTIONS!$D$5:$D$244,TRANSACTIONS!$E$5:$E$244,"Corporation",TRANSACTIONS!$G$5:$G$244,"Financing",TRANSACTIONS!$J$5:$J$244,$B6)) | P6: =C6+F6+I6+J6+K6+L6 | Q6: =SUMIFS(TRANSACTIONS!$D$5:$D$244,TRANSACTIONS!$E$5:$E$244,"Sole Prop",TRANSACTIONS!$J$5:$J$244,$B6)+SUMIFS(TRANSACTIONS!$D$5:$D$244,TRANSACTIONS!$E$5:$E$244,"Corporation",TRANSACTIONS!$J$5:$J$244,$B6) | R6: =SUMIFS(TRANSACTIONS!$D$5:$D$244,TRANSACTIONS!$E$5:$E$244,"Personal",TRANSACTIONS!$J$5:$J$244,$B6) | S6: =S5+SUMIFS(TRANSACTIONS!$D$5:$D$244,TRANSACTIONS!$E$5:$E$244,"Sole Prop",TRANSACTIONS!$J$5:$J$244,$B6) | T6: =T5+SUMIFS(TRANSACTIONS!$D$5:$D$244,TRANSACTIONS!$E$5:$E$244,"Corporation",TRANSACTIONS!$J$5:$J$244,$B6) | U6: =U5+R6 | V6: =S6+T6+U6
A7: Mar 2026 | B7: 202603 | C7: =SUMIFS(TRANSACTIONS!$D$5:$D$244,TRANSACTIONS!$E$5:$E$244,"Sole Prop",TRANSACTIONS!$G$5:$G$244,"Revenue",TRANSACTIONS!$J$5:$J$244,$B7) | D7: =-SUMIFS(TRANSACTIONS!$I$5:$I$244,TRANSACTIONS!$E$5:$E$244,"Sole Prop",TRANSACTIONS!$G$5:$G$244,"Revenue",TRANSACTIONS!$J$5:$J$244,$B7) | E7: =C7+D7 | F7: =SUMIFS(TRANSACTIONS!$D$5:$D$244,TRANSACTIONS!$E$5:$E$244,"Corporation",TRANSACTIONS!$G$5:$G$244,"Revenue",TRANSACTIONS!$J$5:$J$244,$B7) | G7: =-SUMIFS(TRANSACTIONS!$I$5:$I$244,TRANSACTIONS!$E$5:$E$244,"Corporation",TRANSACTIONS!$G$5:$G$244,"Revenue",TRANSACTIONS!$J$5:$J$244,$B7) | H7: =F7+G7 | I7: =(SUMIFS(TRANSACTIONS!$D$5:$D$244,TRANSACTIONS!$E$5:$E$244,"Sole Prop",TRANSACTIONS!$G$5:$G$244,"COGS",TRANSACTIONS!$J$5:$J$244,$B7)+SUMIFS(TRANSACTIONS!$D$5:$D$244,TRANSACTIONS!$E$5:$E$244,"Corporation",TRANSACTIONS!$G$5:$G$244,"COGS",TRANSACTIONS!$J$5:$J$244,$B7)) | J7: =(SUMIFS(TRANSACTIONS!$D$5:$D$244,TRANSACTIONS!$E$5:$E$244,"Sole Prop",TRANSACTIONS!$G$5:$G$244,"Operating Expense",TRANSACTIONS!$J$5:$J$244,$B7)+SUMIFS(TRANSACTIONS!$D$5:$D$244,TRANSACTIONS!$E$5:$E$244,"Corporation",TRANSACTIONS!$G$5:$G$244,"Operating Expense",TRANSACTIONS!$J$5:$J$244,$B7)) | K7: =(SUMIFS(TRANSACTIONS!$D$5:$D$244,TRANSACTIONS!$E$5:$E$244,"Sole Prop",TRANSACTIONS!$G$5:$G$244,"Payroll",TRANSACTIONS!$J$5:$J$244,$B7)+SUMIFS(TRANSACTIONS!$D$5:$D$244,TRANSACTIONS!$E$5:$E$244,"Corporation",TRANSACTIONS!$G$5:$G$244,"Payroll",TRANSACTIONS!$J$5:$J$244,$B7)) | L7: =(SUMIFS(TRANSACTIONS!$D$5:$D$244,TRANSACTIONS!$E$5:$E$244,"Sole Prop",TRANSACTIONS!$G$5:$G$244,"Tax/Remittance",TRANSACTIONS!$J$5:$J$244,$B7)+SUMIFS(TRANSACTIONS!$D$5:$D$244,TRANSACTIONS!$E$5:$E$244,"Corporation",TRANSACTIONS!$G$5:$G$244,"Tax/Remittance",TRANSACTIONS!$J$5:$J$244,$B7)) | M7: =(SUMIFS(TRANSACTIONS!$D$5:$D$244,TRANSACTIONS!$E$5:$E$244,"Sole Prop",TRANSACTIONS!$G$5:$G$244,"Owner Draw/Comp",TRANSACTIONS!$J$5:$J$244,$B7)+SUMIFS(TRANSACTIONS!$D$5:$D$244,TRANSACTIONS!$E$5:$E$244,"Corporation",TRANSACTIONS!$G$5:$G$244,"Owner Draw/Comp",TRANSACTIONS!$J$5:$J$244,$B7)) | N7: =(SUMIFS(TRANSACTIONS!$D$5:$D$244,TRANSACTIONS!$E$5:$E$244,"Sole Prop",TRANSACTIONS!$G$5:$G$244,"Capital Purchase",TRANSACTIONS!$J$5:$J$244,$B7)+SUMIFS(TRANSACTIONS!$D$5:$D$244,TRANSACTIONS!$E$5:$E$244,"Corporation",TRANSACTIONS!$G$5:$G$244,"Capital Purchase",TRANSACTIONS!$J$5:$J$244,$B7)) | O7: =(SUMIFS(TRANSACTIONS!$D$5:$D$244,TRANSACTIONS!$E$5:$E$244,"Sole Prop",TRANSACTIONS!$G$5:$G$244,"Financing",TRANSACTIONS!$J$5:$J$244,$B7)+SUMIFS(TRANSACTIONS!$D$5:$D$244,TRANSACTIONS!$E$5:$E$244,"Corporation",TRANSACTIONS!$G$5:$G$244,"Financing",TRANSACTIONS!$J$5:$J$244,$B7)) | P7: =C7+F7+I7+J7+K7+L7 | Q7: =SUMIFS(TRANSACTIONS!$D$5:$D$244,TRANSACTIONS!$E$5:$E$244,"Sole Prop",TRANSACTIONS!$J$5:$J$244,$B7)+SUMIFS(TRANSACTIONS!$D$5:$D$244,TRANSACTIONS!$E$5:$E$244,"Corporation",TRANSACTIONS!$J$5:$J$244,$B7) | R7: =SUMIFS(TRANSACTIONS!$D$5:$D$244,TRANSACTIONS!$E$5:$E$244,"Personal",TRANSACTIONS!$J$5:$J$244,$B7) | S7: =S6+SUMIFS(TRANSACTIONS!$D$5:$D$244,TRANSACTIONS!$E$5:$E$244,"Sole Prop",TRANSACTIONS!$J$5:$J$244,$B7) | T7: =T6+SUMIFS(TRANSACTIONS!$D$5:$D$244,TRANSACTIONS!$E$5:$E$244,"Corporation",TRANSACTIONS!$J$5:$J$244,$B7) | U7: =U6+R7 | V7: =S7+T7+U7
A8: Apr 2026 | B8: 202604 | C8: =SUMIFS(TRANSACTIONS!$D$5:$D$244,TRANSACTIONS!$E$5:$E$244,"Sole Prop",TRANSACTIONS!$G$5:$G$244,"Revenue",TRANSACTIONS!$J$5:$J$244,$B8) | D8: =-SUMIFS(TRANSACTIONS!$I$5:$I$244,TRANSACTIONS!$E$5:$E$244,"Sole Prop",TRANSACTIONS!$G$5:$G$244,"Revenue",TRANSACTIONS!$J$5:$J$244,$B8) | E8: =C8+D8 | F8: =SUMIFS(TRANSACTIONS!$D$5:$D$244,TRANSACTIONS!$E$5:$E$244,"Corporation",TRANSACTIONS!$G$5:$G$244,"Revenue",TRANSACTIONS!$J$5:$J$244,$B8) | G8: =-SUMIFS(TRANSACTIONS!$I$5:$I$244,TRANSACTIONS!$E$5:$E$244,"Corporation",TRANSACTIONS!$G$5:$G$244,"Revenue",TRANSACTIONS!$J$5:$J$244,$B8) | H8: =F8+G8 | I8: =(SUMIFS(TRANSACTIONS!$D$5:$D$244,TRANSACTIONS!$E$5:$E$244,"Sole Prop",TRANSACTIONS!$G$5:$G$244,"COGS",TRANSACTIONS!$J$5:$J$244,$B8)+SUMIFS(TRANSACTIONS!$D$5:$D$244,TRANSACTIONS!$E$5:$E$244,"Corporation",TRANSACTIONS!$G$5:$G$244,"COGS",TRANSACTIONS!$J$5:$J$244,$B8)) | J8: =(SUMIFS(TRANSACTIONS!$D$5:$D$244,TRANSACTIONS!$E$5:$E$244,"Sole Prop",TRANSACTIONS!$G$5:$G$244,"Operating Expense",TRANSACTIONS!$J$5:$J$244,$B8)+SUMIFS(TRANSACTIONS!$D$5:$D$244,TRANSACTIONS!$E$5:$E$244,"Corporation",TRANSACTIONS!$G$5:$G$244,"Operating Expense",TRANSACTIONS!$J$5:$J$244,$B8)) | K8: =(SUMIFS(TRANSACTIONS!$D$5:$D$244,TRANSACTIONS!$E$5:$E$244,"Sole Prop",TRANSACTIONS!$G$5:$G$244,"Payroll",TRANSACTIONS!$J$5:$J$244,$B8)+SUMIFS(TRANSACTIONS!$D$5:$D$244,TRANSACTIONS!$E$5:$E$244,"Corporation",TRANSACTIONS!$G$5:$G$244,"Payroll",TRANSACTIONS!$J$5:$J$244,$B8)) | L8: =(SUMIFS(TRANSACTIONS!$D$5:$D$244,TRANSACTIONS!$E$5:$E$244,"Sole Prop",TRANSACTIONS!$G$5:$G$244,"Tax/Remittance",TRANSACTIONS!$J$5:$J$244,$B8)+SUMIFS(TRANSACTIONS!$D$5:$D$244,TRANSACTIONS!$E$5:$E$244,"Corporation",TRANSACTIONS!$G$5:$G$244,"Tax/Remittance",TRANSACTIONS!$J$5:$J$244,$B8)) | M8: =(SUMIFS(TRANSACTIONS!$D$5:$D$244,TRANSACTIONS!$E$5:$E$244,"Sole Prop",TRANSACTIONS!$G$5:$G$244,"Owner Draw/Comp",TRANSACTIONS!$J$5:$J$244,$B8)+SUMIFS(TRANSACTIONS!$D$5:$D$244,TRANSACTIONS!$E$5:$E$244,"Corporation",TRANSACTIONS!$G$5:$G$244,"Owner Draw/Comp",TRANSACTIONS!$J$5:$J$244,$B8)) | N8: =(SUMIFS(TRANSACTIONS!$D$5:$D$244,TRANSACTIONS!$E$5:$E$244,"Sole Prop",TRANSACTIONS!$G$5:$G$244,"Capital Purchase",TRANSACTIONS!$J$5:$J$244,$B8)+SUMIFS(TRANSACTIONS!$D$5:$D$244,TRANSACTIONS!$E$5:$E$244,"Corporation",TRANSACTIONS!$G$5:$G$244,"Capital Purchase",TRANSACTIONS!$J$5:$J$244,$B8)) | O8: =(SUMIFS(TRANSACTIONS!$D$5:$D$244,TRANSACTIONS!$E$5:$E$244,"Sole Prop",TRANSACTIONS!$G$5:$G$244,"Financing",TRANSACTIONS!$J$5:$J$244,$B8)+SUMIFS(TRANSACTIONS!$D$5:$D$244,TRANSACTIONS!$E$5:$E$244,"Corporation",TRANSACTIONS!$G$5:$G$244,"Financing",TRANSACTIONS!$J$5:$J$244,$B8)) | P8: =C8+F8+I8+J8+K8+L8 | Q8: =SUMIFS(TRANSACTIONS!$D$5:$D$244,TRANSACTIONS!$E$5:$E$244,"Sole Prop",TRANSACTIONS!$J$5:$J$244,$B8)+SUMIFS(TRANSACTIONS!$D$5:$D$244,TRANSACTIONS!$E$5:$E$244,"Corporation",TRANSACTIONS!$J$5:$J$244,$B8) | R8: =SUMIFS(TRANSACTIONS!$D$5:$D$244,TRANSACTIONS!$E$5:$E$244,"Personal",TRANSACTIONS!$J$5:$J$244,$B8) | S8: =S7+SUMIFS(TRANSACTIONS!$D$5:$D$244,TRANSACTIONS!$E$5:$E$244,"Sole Prop",TRANSACTIONS!$J$5:$J$244,$B8) | T8: =T7+SUMIFS(TRANSACTIONS!$D$5:$D$244,TRANSACTIONS!$E$5:$E$244,"Corporation",TRANSACTIONS!$J$5:$J$244,$B8) | U8: =U7+R8 | V8: =S8+T8+U8
A9: May 2026 | B9: 202605 | C9: =SUMIFS(TRANSACTIONS!$D$5:$D$244,TRANSACTIONS!$E$5:$E$244,"Sole Prop",TRANSACTIONS!$G$5:$G$244,"Revenue",TRANSACTIONS!$J$5:$J$244,$B9) | D9: =-SUMIFS(TRANSACTIONS!$I$5:$I$244,TRANSACTIONS!$E$5:$E$244,"Sole Prop",TRANSACTIONS!$G$5:$G$244,"Revenue",TRANSACTIONS!$J$5:$J$244,$B9) | E9: =C9+D9 | F9: =SUMIFS(TRANSACTIONS!$D$5:$D$244,TRANSACTIONS!$E$5:$E$244,"Corporation",TRANSACTIONS!$G$5:$G$244,"Revenue",TRANSACTIONS!$J$5:$J$244,$B9) | G9: =-SUMIFS(TRANSACTIONS!$I$5:$I$244,TRANSACTIONS!$E$5:$E$244,"Corporation",TRANSACTIONS!$G$5:$G$244,"Revenue",TRANSACTIONS!$J$5:$J$244,$B9) | H9: =F9+G9 | I9: =(SUMIFS(TRANSACTIONS!$D$5:$D$244,TRANSACTIONS!$E$5:$E$244,"Sole Prop",TRANSACTIONS!$G$5:$G$244,"COGS",TRANSACTIONS!$J$5:$J$244,$B9)+SUMIFS(TRANSACTIONS!$D$5:$D$244,TRANSACTIONS!$E$5:$E$244,"Corporation",TRANSACTIONS!$G$5:$G$244,"COGS",TRANSACTIONS!$J$5:$J$244,$B9)) | J9: =(SUMIFS(TRANSACTIONS!$D$5:$D$244,TRANSACTIONS!$E$5:$E$244,"Sole Prop",TRANSACTIONS!$G$5:$G$244,"Operating Expense",TRANSACTIONS!$J$5:$J$244,$B9)+SUMIFS(TRANSACTIONS!$D$5:$D$244,TRANSACTIONS!$E$5:$E$244,"Corporation",TRANSACTIONS!$G$5:$G$244,"Operating Expense",TRANSACTIONS!$J$5:$J$244,$B9)) | K9: =(SUMIFS(TRANSACTIONS!$D$5:$D$244,TRANSACTIONS!$E$5:$E$244,"Sole Prop",TRANSACTIONS!$G$5:$G$244,"Payroll",TRANSACTIONS!$J$5:$J$244,$B9)+SUMIFS(TRANSACTIONS!$D$5:$D$244,TRANSACTIONS!$E$5:$E$244,"Corporation",TRANSACTIONS!$G$5:$G$244,"Payroll",TRANSACTIONS!$J$5:$J$244,$B9)) | L9: =(SUMIFS(TRANSACTIONS!$D$5:$D$244,TRANSACTIONS!$E$5:$E$244,"Sole Prop",TRANSACTIONS!$G$5:$G$244,"Tax/Remittance",TRANSACTIONS!$J$5:$J$244,$B9)+SUMIFS(TRANSACTIONS!$D$5:$D$244,TRANSACTIONS!$E$5:$E$244,"Corporation",TRANSACTIONS!$G$5:$G$244,"Tax/Remittance",TRANSACTIONS!$J$5:$J$244,$B9)) | M9: =(SUMIFS(TRANSACTIONS!$D$5:$D$244,TRANSACTIONS!$E$5:$E$244,"Sole Prop",TRANSACTIONS!$G$5:$G$244,"Owner Draw/Comp",TRANSACTIONS!$J$5:$J$244,$B9)+SUMIFS(TRANSACTIONS!$D$5:$D$244,TRANSACTIONS!$E$5:$E$244,"Corporation",TRANSACTIONS!$G$5:$G$244,"Owner Draw/Comp",TRANSACTIONS!$J$5:$J$244,$B9)) | N9: =(SUMIFS(TRANSACTIONS!$D$5:$D$244,TRANSACTIONS!$E$5:$E$244,"Sole Prop",TRANSACTIONS!$G$5:$G$244,"Capital Purchase",TRANSACTIONS!$J$5:$J$244,$B9)+SUMIFS(TRANSACTIONS!$D$5:$D$244,TRANSACTIONS!$E$5:$E$244,"Corporation",TRANSACTIONS!$G$5:$G$244,"Capital Purchase",TRANSACTIONS!$J$5:$J$244,$B9)) | O9: =(SUMIFS(TRANSACTIONS!$D$5:$D$244,TRANSACTIONS!$E$5:$E$244,"Sole Prop",TRANSACTIONS!$G$5:$G$244,"Financing",TRANSACTIONS!$J$5:$J$244,$B9)+SUMIFS(TRANSACTIONS!$D$5:$D$244,TRANSACTIONS!$E$5:$E$244,"Corporation",TRANSACTIONS!$G$5:$G$244,"Financing",TRANSACTIONS!$J$5:$J$244,$B9)) | P9: =C9+F9+I9+J9+K9+L9 | Q9: =SUMIFS(TRANSACTIONS!$D$5:$D$244,TRANSACTIONS!$E$5:$E$244,"Sole Prop",TRANSACTIONS!$J$5:$J$244,$B9)+SUMIFS(TRANSACTIONS!$D$5:$D$244,TRANSACTIONS!$E$5:$E$244,"Corporation",TRANSACTIONS!$J$5:$J$244,$B9) | R9: =SUMIFS(TRANSACTIONS!$D$5:$D$244,TRANSACTIONS!$E$5:$E$244,"Personal",TRANSACTIONS!$J$5:$J$244,$B9) | S9: =S8+SUMIFS(TRANSACTIONS!$D$5:$D$244,TRANSACTIONS!$E$5:$E$244,"Sole Prop",TRANSACTIONS!$J$5:$J$244,$B9) | T9: =T8+SUMIFS(TRANSACTIONS!$D$5:$D$244,TRANSACTIONS!$E$5:$E$244,"Corporation",TRANSACTIONS!$J$5:$J$244,$B9) | U9: =U8+R9 | V9: =S9+T9+U9
A10: Jun 2026 | B10: 202606 | C10: =SUMIFS(TRANSACTIONS!$D$5:$D$244,TRANSACTIONS!$E$5:$E$244,"Sole Prop",TRANSACTIONS!$G$5:$G$244,"Revenue",TRANSACTIONS!$J$5:$J$244,$B10) | D10: =-SUMIFS(TRANSACTIONS!$I$5:$I$244,TRANSACTIONS!$E$5:$E$244,"Sole Prop",TRANSACTIONS!$G$5:$G$244,"Revenue",TRANSACTIONS!$J$5:$J$244,$B10) | E10: =C10+D10 | F10: =SUMIFS(TRANSACTIONS!$D$5:$D$244,TRANSACTIONS!$E$5:$E$244,"Corporation",TRANSACTIONS!$G$5:$G$244,"Revenue",TRANSACTIONS!$J$5:$J$244,$B10) | G10: =-SUMIFS(TRANSACTIONS!$I$5:$I$244,TRANSACTIONS!$E$5:$E$244,"Corporation",TRANSACTIONS!$G$5:$G$244,"Revenue",TRANSACTIONS!$J$5:$J$244,$B10) | H10: =F10+G10 | I10: =(SUMIFS(TRANSACTIONS!$D$5:$D$244,TRANSACTIONS!$E$5:$E$244,"Sole Prop",TRANSACTIONS!$G$5:$G$244,"COGS",TRANSACTIONS!$J$5:$J$244,$B10)+SUMIFS(TRANSACTIONS!$D$5:$D$244,TRANSACTIONS!$E$5:$E$244,"Corporation",TRANSACTIONS!$G$5:$G$244,"COGS",TRANSACTIONS!$J$5:$J$244,$B10)) | J10: =(SUMIFS(TRANSACTIONS!$D$5:$D$244,TRANSACTIONS!$E$5:$E$244,"Sole Prop",TRANSACTIONS!$G$5:$G$244,"Operating Expense",TRANSACTIONS!$J$5:$J$244,$B10)+SUMIFS(TRANSACTIONS!$D$5:$D$244,TRANSACTIONS!$E$5:$E$244,"Corporation",TRANSACTIONS!$G$5:$G$244,"Operating Expense",TRANSACTIONS!$J$5:$J$244,$B10)) | K10: =(SUMIFS(TRANSACTIONS!$D$5:$D$244,TRANSACTIONS!$E$5:$E$244,"Sole Prop",TRANSACTIONS!$G$5:$G$244,"Payroll",TRANSACTIONS!$J$5:$J$244,$B10)+SUMIFS(TRANSACTIONS!$D$5:$D$244,TRANSACTIONS!$E$5:$E$244,"Corporation",TRANSACTIONS!$G$5:$G$244,"Payroll",TRANSACTIONS!$J$5:$J$244,$B10)) | L10: =(SUMIFS(TRANSACTIONS!$D$5:$D$244,TRANSACTIONS!$E$5:$E$244,"Sole Prop",TRANSACTIONS!$G$5:$G$244,"Tax/Remittance",TRANSACTIONS!$J$5:$J$244,$B10)+SUMIFS(TRANSACTIONS!$D$5:$D$244,TRANSACTIONS!$E$5:$E$244,"Corporation",TRANSACTIONS!$G$5:$G$244,"Tax/Remittance",TRANSACTIONS!$J$5:$J$244,$B10)) | M10: =(SUMIFS(TRANSACTIONS!$D$5:$D$244,TRANSACTIONS!$E$5:$E$244,"Sole Prop",TRANSACTIONS!$G$5:$G$244,"Owner Draw/Comp",TRANSACTIONS!$J$5:$J$244,$B10)+SUMIFS(TRANSACTIONS!$D$5:$D$244,TRANSACTIONS!$E$5:$E$244,"Corporation",TRANSACTIONS!$G$5:$G$244,"Owner Draw/Comp",TRANSACTIONS!$J$5:$J$244,$B10)) | N10: =(SUMIFS(TRANSACTIONS!$D$5:$D$244,TRANSACTIONS!$E$5:$E$244,"Sole Prop",TRANSACTIONS!$G$5:$G$244,"Capital Purchase",TRANSACTIONS!$J$5:$J$244,$B10)+SUMIFS(TRANSACTIONS!$D$5:$D$244,TRANSACTIONS!$E$5:$E$244,"Corporation",TRANSACTIONS!$G$5:$G$244,"Capital Purchase",TRANSACTIONS!$J$5:$J$244,$B10)) | O10: =(SUMIFS(TRANSACTIONS!$D$5:$D$244,TRANSACTIONS!$E$5:$E$244,"Sole Prop",TRANSACTIONS!$G$5:$G$244,"Financing",TRANSACTIONS!$J$5:$J$244,$B10)+SUMIFS(TRANSACTIONS!$D$5:$D$244,TRANSACTIONS!$E$5:$E$244,"Corporation",TRANSACTIONS!$G$5:$G$244,"Financing",TRANSACTIONS!$J$5:$J$244,$B10)) | P10: =C10+F10+I10+J10+K10+L10 | Q10: =SUMIFS(TRANSACTIONS!$D$5:$D$244,TRANSACTIONS!$E$5:$E$244,"Sole Prop",TRANSACTIONS!$J$5:$J$244,$B10)+SUMIFS(TRANSACTIONS!$D$5:$D$244,TRANSACTIONS!$E$5:$E$244,"Corporation",TRANSACTIONS!$J$5:$J$244,$B10) | R10: =SUMIFS(TRANSACTIONS!$D$5:$D$244,TRANSACTIONS!$E$5:$E$244,"Personal",TRANSACTIONS!$J$5:$J$244,$B10) | S10: =S9+SUMIFS(TRANSACTIONS!$D$5:$D$244,TRANSACTIONS!$E$5:$E$244,"Sole Prop",TRANSACTIONS!$J$5:$J$244,$B10) | T10: =T9+SUMIFS(TRANSACTIONS!$D$5:$D$244,TRANSACTIONS!$E$5:$E$244,"Corporation",TRANSACTIONS!$J$5:$J$244,$B10) | U10: =U9+R10 | V10: =S10+T10+U10
A11: Jul 2026 | B11: 202607 | C11: =SUMIFS(TRANSACTIONS!$D$5:$D$244,TRANSACTIONS!$E$5:$E$244,"Sole Prop",TRANSACTIONS!$G$5:$G$244,"Revenue",TRANSACTIONS!$J$5:$J$244,$B11) | D11: =-SUMIFS(TRANSACTIONS!$I$5:$I$244,TRANSACTIONS!$E$5:$E$244,"Sole Prop",TRANSACTIONS!$G$5:$G$244,"Revenue",TRANSACTIONS!$J$5:$J$244,$B11) | E11: =C11+D11 | F11: =SUMIFS(TRANSACTIONS!$D$5:$D$244,TRANSACTIONS!$E$5:$E$244,"Corporation",TRANSACTIONS!$G$5:$G$244,"Revenue",TRANSACTIONS!$J$5:$J$244,$B11) | G11: =-SUMIFS(TRANSACTIONS!$I$5:$I$244,TRANSACTIONS!$E$5:$E$244,"Corporation",TRANSACTIONS!$G$5:$G$244,"Revenue",TRANSACTIONS!$J$5:$J$244,$B11) | H11: =F11+G11 | I11: =(SUMIFS(TRANSACTIONS!$D$5:$D$244,TRANSACTIONS!$E$5:$E$244,"Sole Prop",TRANSACTIONS!$G$5:$G$244,"COGS",TRANSACTIONS!$J$5:$J$244,$B11)+SUMIFS(TRANSACTIONS!$D$5:$D$244,TRANSACTIONS!$E$5:$E$244,"Corporation",TRANSACTIONS!$G$5:$G$244,"COGS",TRANSACTIONS!$J$5:$J$244,$B11)) | J11: =(SUMIFS(TRANSACTIONS!$D$5:$D$244,TRANSACTIONS!$E$5:$E$244,"Sole Prop",TRANSACTIONS!$G$5:$G$244,"Operating Expense",TRANSACTIONS!$J$5:$J$244,$B11)+SUMIFS(TRANSACTIONS!$D$5:$D$244,TRANSACTIONS!$E$5:$E$244,"Corporation",TRANSACTIONS!$G$5:$G$244,"Operating Expense",TRANSACTIONS!$J$5:$J$244,$B11)) | K11: =(SUMIFS(TRANSACTIONS!$D$5:$D$244,TRANSACTIONS!$E$5:$E$244,"Sole Prop",TRANSACTIONS!$G$5:$G$244,"Payroll",TRANSACTIONS!$J$5:$J$244,$B11)+SUMIFS(TRANSACTIONS!$D$5:$D$244,TRANSACTIONS!$E$5:$E$244,"Corporation",TRANSACTIONS!$G$5:$G$244,"Payroll",TRANSACTIONS!$J$5:$J$244,$B11)) | L11: =(SUMIFS(TRANSACTIONS!$D$5:$D$244,TRANSACTIONS!$E$5:$E$244,"Sole Prop",TRANSACTIONS!$G$5:$G$244,"Tax/Remittance",TRANSACTIONS!$J$5:$J$244,$B11)+SUMIFS(TRANSACTIONS!$D$5:$D$244,TRANSACTIONS!$E$5:$E$244,"Corporation",TRANSACTIONS!$G$5:$G$244,"Tax/Remittance",TRANSACTIONS!$J$5:$J$244,$B11)) | M11: =(SUMIFS(TRANSACTIONS!$D$5:$D$244,TRANSACTIONS!$E$5:$E$244,"Sole Prop",TRANSACTIONS!$G$5:$G$244,"Owner Draw/Comp",TRANSACTIONS!$J$5:$J$244,$B11)+SUMIFS(TRANSACTIONS!$D$5:$D$244,TRANSACTIONS!$E$5:$E$244,"Corporation",TRANSACTIONS!$G$5:$G$244,"Owner Draw/Comp",TRANSACTIONS!$J$5:$J$244,$B11)) | N11: =(SUMIFS(TRANSACTIONS!$D$5:$D$244,TRANSACTIONS!$E$5:$E$244,"Sole Prop",TRANSACTIONS!$G$5:$G$244,"Capital Purchase",TRANSACTIONS!$J$5:$J$244,$B11)+SUMIFS(TRANSACTIONS!$D$5:$D$244,TRANSACTIONS!$E$5:$E$244,"Corporation",TRANSACTIONS!$G$5:$G$244,"Capital Purchase",TRANSACTIONS!$J$5:$J$244,$B11)) | O11: =(SUMIFS(TRANSACTIONS!$D$5:$D$244,TRANSACTIONS!$E$5:$E$244,"Sole Prop",TRANSACTIONS!$G$5:$G$244,"Financing",TRANSACTIONS!$J$5:$J$244,$B11)+SUMIFS(TRANSACTIONS!$D$5:$D$244,TRANSACTIONS!$E$5:$E$244,"Corporation",TRANSACTIONS!$G$5:$G$244,"Financing",TRANSACTIONS!$J$5:$J$244,$B11)) | P11: =C11+F11+I11+J11+K11+L11 | Q11: =SUMIFS(TRANSACTIONS!$D$5:$D$244,TRANSACTIONS!$E$5:$E$244,"Sole Prop",TRANSACTIONS!$J$5:$J$244,$B11)+SUMIFS(TRANSACTIONS!$D$5:$D$244,TRANSACTIONS!$E$5:$E$244,"Corporation",TRANSACTIONS!$J$5:$J$244,$B11) | R11: =SUMIFS(TRANSACTIONS!$D$5:$D$244,TRANSACTIONS!$E$5:$E$244,"Personal",TRANSACTIONS!$J$5:$J$244,$B11) | S11: =S10+SUMIFS(TRANSACTIONS!$D$5:$D$244,TRANSACTIONS!$E$5:$E$244,"Sole Prop",TRANSACTIONS!$J$5:$J$244,$B11) | T11: =T10+SUMIFS(TRANSACTIONS!$D$5:$D$244,TRANSACTIONS!$E$5:$E$244,"Corporation",TRANSACTIONS!$J$5:$J$244,$B11) | U11: =U10+R11 | V11: =S11+T11+U11
A12: Aug 2026 | B12: 202608 | C12: =SUMIFS(TRANSACTIONS!$D$5:$D$244,TRANSACTIONS!$E$5:$E$244,"Sole Prop",TRANSACTIONS!$G$5:$G$244,"Revenue",TRANSACTIONS!$J$5:$J$244,$B12) | D12: =-SUMIFS(TRANSACTIONS!$I$5:$I$244,TRANSACTIONS!$E$5:$E$244,"Sole Prop",TRANSACTIONS!$G$5:$G$244,"Revenue",TRANSACTIONS!$J$5:$J$244,$B12) | E12: =C12+D12 | F12: =SUMIFS(TRANSACTIONS!$D$5:$D$244,TRANSACTIONS!$E$5:$E$244,"Corporation",TRANSACTIONS!$G$5:$G$244,"Revenue",TRANSACTIONS!$J$5:$J$244,$B12) | G12: =-SUMIFS(TRANSACTIONS!$I$5:$I$244,TRANSACTIONS!$E$5:$E$244,"Corporation",TRANSACTIONS!$G$5:$G$244,"Revenue",TRANSACTIONS!$J$5:$J$244,$B12) | H12: =F12+G12 | I12: =(SUMIFS(TRANSACTIONS!$D$5:$D$244,TRANSACTIONS!$E$5:$E$244,"Sole Prop",TRANSACTIONS!$G$5:$G$244,"COGS",TRANSACTIONS!$J$5:$J$244,$B12)+SUMIFS(TRANSACTIONS!$D$5:$D$244,TRANSACTIONS!$E$5:$E$244,"Corporation",TRANSACTIONS!$G$5:$G$244,"COGS",TRANSACTIONS!$J$5:$J$244,$B12)) | J12: =(SUMIFS(TRANSACTIONS!$D$5:$D$244,TRANSACTIONS!$E$5:$E$244,"Sole Prop",TRANSACTIONS!$G$5:$G$244,"Operating Expense",TRANSACTIONS!$J$5:$J$244,$B12)+SUMIFS(TRANSACTIONS!$D$5:$D$244,TRANSACTIONS!$E$5:$E$244,"Corporation",TRANSACTIONS!$G$5:$G$244,"Operating Expense",TRANSACTIONS!$J$5:$J$244,$B12)) | K12: =(SUMIFS(TRANSACTIONS!$D$5:$D$244,TRANSACTIONS!$E$5:$E$244,"Sole Prop",TRANSACTIONS!$G$5:$G$244,"Payroll",TRANSACTIONS!$J$5:$J$244,$B12)+SUMIFS(TRANSACTIONS!$D$5:$D$244,TRANSACTIONS!$E$5:$E$244,"Corporation",TRANSACTIONS!$G$5:$G$244,"Payroll",TRANSACTIONS!$J$5:$J$244,$B12)) | L12: =(SUMIFS(TRANSACTIONS!$D$5:$D$244,TRANSACTIONS!$E$5:$E$244,"Sole Prop",TRANSACTIONS!$G$5:$G$244,"Tax/Remittance",TRANSACTIONS!$J$5:$J$244,$B12)+SUMIFS(TRANSACTIONS!$D$5:$D$244,TRANSACTIONS!$E$5:$E$244,"Corporation",TRANSACTIONS!$G$5:$G$244,"Tax/Remittance",TRANSACTIONS!$J$5:$J$244,$B12)) | M12: =(SUMIFS(TRANSACTIONS!$D$5:$D$244,TRANSACTIONS!$E$5:$E$244,"Sole Prop",TRANSACTIONS!$G$5:$G$244,"Owner Draw/Comp",TRANSACTIONS!$J$5:$J$244,$B12)+SUMIFS(TRANSACTIONS!$D$5:$D$244,TRANSACTIONS!$E$5:$E$244,"Corporation",TRANSACTIONS!$G$5:$G$244,"Owner Draw/Comp",TRANSACTIONS!$J$5:$J$244,$B12)) | N12: =(SUMIFS(TRANSACTIONS!$D$5:$D$244,TRANSACTIONS!$E$5:$E$244,"Sole Prop",TRANSACTIONS!$G$5:$G$244,"Capital Purchase",TRANSACTIONS!$J$5:$J$244,$B12)+SUMIFS(TRANSACTIONS!$D$5:$D$244,TRANSACTIONS!$E$5:$E$244,"Corporation",TRANSACTIONS!$G$5:$G$244,"Capital Purchase",TRANSACTIONS!$J$5:$J$244,$B12)) | O12: =(SUMIFS(TRANSACTIONS!$D$5:$D$244,TRANSACTIONS!$E$5:$E$244,"Sole Prop",TRANSACTIONS!$G$5:$G$244,"Financing",TRANSACTIONS!$J$5:$J$244,$B12)+SUMIFS(TRANSACTIONS!$D$5:$D$244,TRANSACTIONS!$E$5:$E$244,"Corporation",TRANSACTIONS!$G$5:$G$244,"Financing",TRANSACTIONS!$J$5:$J$244,$B12)) | P12: =C12+F12+I12+J12+K12+L12 | Q12: =SUMIFS(TRANSACTIONS!$D$5:$D$244,TRANSACTIONS!$E$5:$E$244,"Sole Prop",TRANSACTIONS!$J$5:$J$244,$B12)+SUMIFS(TRANSACTIONS!$D$5:$D$244,TRANSACTIONS!$E$5:$E$244,"Corporation",TRANSACTIONS!$J$5:$J$244,$B12) | R12: =SUMIFS(TRANSACTIONS!$D$5:$D$244,TRANSACTIONS!$E$5:$E$244,"Personal",TRANSACTIONS!$J$5:$J$244,$B12) | S12: =S11+SUMIFS(TRANSACTIONS!$D$5:$D$244,TRANSACTIONS!$E$5:$E$244,"Sole Prop",TRANSACTIONS!$J$5:$J$244,$B12) | T12: =T11+SUMIFS(TRANSACTIONS!$D$5:$D$244,TRANSACTIONS!$E$5:$E$244,"Corporation",TRANSACTIONS!$J$5:$J$244,$B12) | U12: =U11+R12 | V12: =S12+T12+U12
A13: Sep 2026 | B13: 202609 | C13: =SUMIFS(TRANSACTIONS!$D$5:$D$244,TRANSACTIONS!$E$5:$E$244,"Sole Prop",TRANSACTIONS!$G$5:$G$244,"Revenue",TRANSACTIONS!$J$5:$J$244,$B13) | D13: =-SUMIFS(TRANSACTIONS!$I$5:$I$244,TRANSACTIONS!$E$5:$E$244,"Sole Prop",TRANSACTIONS!$G$5:$G$244,"Revenue",TRANSACTIONS!$J$5:$J$244,$B13) | E13: =C13+D13 | F13: =SUMIFS(TRANSACTIONS!$D$5:$D$244,TRANSACTIONS!$E$5:$E$244,"Corporation",TRANSACTIONS!$G$5:$G$244,"Revenue",TRANSACTIONS!$J$5:$J$244,$B13) | G13: =-SUMIFS(TRANSACTIONS!$I$5:$I$244,TRANSACTIONS!$E$5:$E$244,"Corporation",TRANSACTIONS!$G$5:$G$244,"Revenue",TRANSACTIONS!$J$5:$J$244,$B13) | H13: =F13+G13 | I13: =(SUMIFS(TRANSACTIONS!$D$5:$D$244,TRANSACTIONS!$E$5:$E$244,"Sole Prop",TRANSACTIONS!$G$5:$G$244,"COGS",TRANSACTIONS!$J$5:$J$244,$B13)+SUMIFS(TRANSACTIONS!$D$5:$D$244,TRANSACTIONS!$E$5:$E$244,"Corporation",TRANSACTIONS!$G$5:$G$244,"COGS",TRANSACTIONS!$J$5:$J$244,$B13)) | J13: =(SUMIFS(TRANSACTIONS!$D$5:$D$244,TRANSACTIONS!$E$5:$E$244,"Sole Prop",TRANSACTIONS!$G$5:$G$244,"Operating Expense",TRANSACTIONS!$J$5:$J$244,$B13)+SUMIFS(TRANSACTIONS!$D$5:$D$244,TRANSACTIONS!$E$5:$E$244,"Corporation",TRANSACTIONS!$G$5:$G$244,"Operating Expense",TRANSACTIONS!$J$5:$J$244,$B13)) | K13: =(SUMIFS(TRANSACTIONS!$D$5:$D$244,TRANSACTIONS!$E$5:$E$244,"Sole Prop",TRANSACTIONS!$G$5:$G$244,"Payroll",TRANSACTIONS!$J$5:$J$244,$B13)+SUMIFS(TRANSACTIONS!$D$5:$D$244,TRANSACTIONS!$E$5:$E$244,"Corporation",TRANSACTIONS!$G$5:$G$244,"Payroll",TRANSACTIONS!$J$5:$J$244,$B13)) | L13: =(SUMIFS(TRANSACTIONS!$D$5:$D$244,TRANSACTIONS!$E$5:$E$244,"Sole Prop",TRANSACTIONS!$G$5:$G$244,"Tax/Remittance",TRANSACTIONS!$J$5:$J$244,$B13)+SUMIFS(TRANSACTIONS!$D$5:$D$244,TRANSACTIONS!$E$5:$E$244,"Corporation",TRANSACTIONS!$G$5:$G$244,"Tax/Remittance",TRANSACTIONS!$J$5:$J$244,$B13)) | M13: =(SUMIFS(TRANSACTIONS!$D$5:$D$244,TRANSACTIONS!$E$5:$E$244,"Sole Prop",TRANSACTIONS!$G$5:$G$244,"Owner Draw/Comp",TRANSACTIONS!$J$5:$J$244,$B13)+SUMIFS(TRANSACTIONS!$D$5:$D$244,TRANSACTIONS!$E$5:$E$244,"Corporation",TRANSACTIONS!$G$5:$G$244,"Owner Draw/Comp",TRANSACTIONS!$J$5:$J$244,$B13)) | N13: =(SUMIFS(TRANSACTIONS!$D$5:$D$244,TRANSACTIONS!$E$5:$E$244,"Sole Prop",TRANSACTIONS!$G$5:$G$244,"Capital Purchase",TRANSACTIONS!$J$5:$J$244,$B13)+SUMIFS(TRANSACTIONS!$D$5:$D$244,TRANSACTIONS!$E$5:$E$244,"Corporation",TRANSACTIONS!$G$5:$G$244,"Capital Purchase",TRANSACTIONS!$J$5:$J$244,$B13)) | O13: =(SUMIFS(TRANSACTIONS!$D$5:$D$244,TRANSACTIONS!$E$5:$E$244,"Sole Prop",TRANSACTIONS!$G$5:$G$244,"Financing",TRANSACTIONS!$J$5:$J$244,$B13)+SUMIFS(TRANSACTIONS!$D$5:$D$244,TRANSACTIONS!$E$5:$E$244,"Corporation",TRANSACTIONS!$G$5:$G$244,"Financing",TRANSACTIONS!$J$5:$J$244,$B13)) | P13: =C13+F13+I13+J13+K13+L13 | Q13: =SUMIFS(TRANSACTIONS!$D$5:$D$244,TRANSACTIONS!$E$5:$E$244,"Sole Prop",TRANSACTIONS!$J$5:$J$244,$B13)+SUMIFS(TRANSACTIONS!$D$5:$D$244,TRANSACTIONS!$E$5:$E$244,"Corporation",TRANSACTIONS!$J$5:$J$244,$B13) | R13: =SUMIFS(TRANSACTIONS!$D$5:$D$244,TRANSACTIONS!$E$5:$E$244,"Personal",TRANSACTIONS!$J$5:$J$244,$B13) | S13: =S12+SUMIFS(TRANSACTIONS!$D$5:$D$244,TRANSACTIONS!$E$5:$E$244,"Sole Prop",TRANSACTIONS!$J$5:$J$244,$B13) | T13: =T12+SUMIFS(TRANSACTIONS!$D$5:$D$244,TRANSACTIONS!$E$5:$E$244,"Corporation",TRANSACTIONS!$J$5:$J$244,$B13) | U13: =U12+R13 | V13: =S13+T13+U13
A14: Oct 2026 | B14: 202610 | C14: =SUMIFS(TRANSACTIONS!$D$5:$D$244,TRANSACTIONS!$E$5:$E$244,"Sole Prop",TRANSACTIONS!$G$5:$G$244,"Revenue",TRANSACTIONS!$J$5:$J$244,$B14) | D14: =-SUMIFS(TRANSACTIONS!$I$5:$I$244,TRANSACTIONS!$E$5:$E$244,"Sole Prop",TRANSACTIONS!$G$5:$G$244,"Revenue",TRANSACTIONS!$J$5:$J$244,$B14) | E14: =C14+D14 | F14: =SUMIFS(TRANSACTIONS!$D$5:$D$244,TRANSACTIONS!$E$5:$E$244,"Corporation",TRANSACTIONS!$G$5:$G$244,"Revenue",TRANSACTIONS!$J$5:$J$244,$B14) | G14: =-SUMIFS(TRANSACTIONS!$I$5:$I$244,TRANSACTIONS!$E$5:$E$244,"Corporation",TRANSACTIONS!$G$5:$G$244,"Revenue",TRANSACTIONS!$J$5:$J$244,$B14) | H14: =F14+G14 | I14: =(SUMIFS(TRANSACTIONS!$D$5:$D$244,TRANSACTIONS!$E$5:$E$244,"Sole Prop",TRANSACTIONS!$G$5:$G$244,"COGS",TRANSACTIONS!$J$5:$J$244,$B14)+SUMIFS(TRANSACTIONS!$D$5:$D$244,TRANSACTIONS!$E$5:$E$244,"Corporation",TRANSACTIONS!$G$5:$G$244,"COGS",TRANSACTIONS!$J$5:$J$244,$B14)) | J14: =(SUMIFS(TRANSACTIONS!$D$5:$D$244,TRANSACTIONS!$E$5:$E$244,"Sole Prop",TRANSACTIONS!$G$5:$G$244,"Operating Expense",TRANSACTIONS!$J$5:$J$244,$B14)+SUMIFS(TRANSACTIONS!$D$5:$D$244,TRANSACTIONS!$E$5:$E$244,"Corporation",TRANSACTIONS!$G$5:$G$244,"Operating Expense",TRANSACTIONS!$J$5:$J$244,$B14)) | K14: =(SUMIFS(TRANSACTIONS!$D$5:$D$244,TRANSACTIONS!$E$5:$E$244,"Sole Prop",TRANSACTIONS!$G$5:$G$244,"Payroll",TRANSACTIONS!$J$5:$J$244,$B14)+SUMIFS(TRANSACTIONS!$D$5:$D$244,TRANSACTIONS!$E$5:$E$244,"Corporation",TRANSACTIONS!$G$5:$G$244,"Payroll",TRANSACTIONS!$J$5:$J$244,$B14)) | L14: =(SUMIFS(TRANSACTIONS!$D$5:$D$244,TRANSACTIONS!$E$5:$E$244,"Sole Prop",TRANSACTIONS!$G$5:$G$244,"Tax/Remittance",TRANSACTIONS!$J$5:$J$244,$B14)+SUMIFS(TRANSACTIONS!$D$5:$D$244,TRANSACTIONS!$E$5:$E$244,"Corporation",TRANSACTIONS!$G$5:$G$244,"Tax/Remittance",TRANSACTIONS!$J$5:$J$244,$B14)) | M14: =(SUMIFS(TRANSACTIONS!$D$5:$D$244,TRANSACTIONS!$E$5:$E$244,"Sole Prop",TRANSACTIONS!$G$5:$G$244,"Owner Draw/Comp",TRANSACTIONS!$J$5:$J$244,$B14)+SUMIFS(TRANSACTIONS!$D$5:$D$244,TRANSACTIONS!$E$5:$E$244,"Corporation",TRANSACTIONS!$G$5:$G$244,"Owner Draw/Comp",TRANSACTIONS!$J$5:$J$244,$B14)) | N14: =(SUMIFS(TRANSACTIONS!$D$5:$D$244,TRANSACTIONS!$E$5:$E$244,"Sole Prop",TRANSACTIONS!$G$5:$G$244,"Capital Purchase",TRANSACTIONS!$J$5:$J$244,$B14)+SUMIFS(TRANSACTIONS!$D$5:$D$244,TRANSACTIONS!$E$5:$E$244,"Corporation",TRANSACTIONS!$G$5:$G$244,"Capital Purchase",TRANSACTIONS!$J$5:$J$244,$B14)) | O14: =(SUMIFS(TRANSACTIONS!$D$5:$D$244,TRANSACTIONS!$E$5:$E$244,"Sole Prop",TRANSACTIONS!$G$5:$G$244,"Financing",TRANSACTIONS!$J$5:$J$244,$B14)+SUMIFS(TRANSACTIONS!$D$5:$D$244,TRANSACTIONS!$E$5:$E$244,"Corporation",TRANSACTIONS!$G$5:$G$244,"Financing",TRANSACTIONS!$J$5:$J$244,$B14)) | P14: =C14+F14+I14+J14+K14+L14 | Q14: =SUMIFS(TRANSACTIONS!$D$5:$D$244,TRANSACTIONS!$E$5:$E$244,"Sole Prop",TRANSACTIONS!$J$5:$J$244,$B14)+SUMIFS(TRANSACTIONS!$D$5:$D$244,TRANSACTIONS!$E$5:$E$244,"Corporation",TRANSACTIONS!$J$5:$J$244,$B14) | R14: =SUMIFS(TRANSACTIONS!$D$5:$D$244,TRANSACTIONS!$E$5:$E$244,"Personal",TRANSACTIONS!$J$5:$J$244,$B14) | S14: =S13+SUMIFS(TRANSACTIONS!$D$5:$D$244,TRANSACTIONS!$E$5:$E$244,"Sole Prop",TRANSACTIONS!$J$5:$J$244,$B14) | T14: =T13+SUMIFS(TRANSACTIONS!$D$5:$D$244,TRANSACTIONS!$E$5:$E$244,"Corporation",TRANSACTIONS!$J$5:$J$244,$B14) | U14: =U13+R14 | V14: =S14+T14+U14
A15: Nov 2026 | B15: 202611 | C15: =SUMIFS(TRANSACTIONS!$D$5:$D$244,TRANSACTIONS!$E$5:$E$244,"Sole Prop",TRANSACTIONS!$G$5:$G$244,"Revenue",TRANSACTIONS!$J$5:$J$244,$B15) | D15: =-SUMIFS(TRANSACTIONS!$I$5:$I$244,TRANSACTIONS!$E$5:$E$244,"Sole Prop",TRANSACTIONS!$G$5:$G$244,"Revenue",TRANSACTIONS!$J$5:$J$244,$B15) | E15: =C15+D15 | F15: =SUMIFS(TRANSACTIONS!$D$5:$D$244,TRANSACTIONS!$E$5:$E$244,"Corporation",TRANSACTIONS!$G$5:$G$244,"Revenue",TRANSACTIONS!$J$5:$J$244,$B15) | G15: =-SUMIFS(TRANSACTIONS!$I$5:$I$244,TRANSACTIONS!$E$5:$E$244,"Corporation",TRANSACTIONS!$G$5:$G$244,"Revenue",TRANSACTIONS!$J$5:$J$244,$B15) | H15: =F15+G15 | I15: =(SUMIFS(TRANSACTIONS!$D$5:$D$244,TRANSACTIONS!$E$5:$E$244,"Sole Prop",TRANSACTIONS!$G$5:$G$244,"COGS",TRANSACTIONS!$J$5:$J$244,$B15)+SUMIFS(TRANSACTIONS!$D$5:$D$244,TRANSACTIONS!$E$5:$E$244,"Corporation",TRANSACTIONS!$G$5:$G$244,"COGS",TRANSACTIONS!$J$5:$J$244,$B15)) | J15: =(SUMIFS(TRANSACTIONS!$D$5:$D$244,TRANSACTIONS!$E$5:$E$244,"Sole Prop",TRANSACTIONS!$G$5:$G$244,"Operating Expense",TRANSACTIONS!$J$5:$J$244,$B15)+SUMIFS(TRANSACTIONS!$D$5:$D$244,TRANSACTIONS!$E$5:$E$244,"Corporation",TRANSACTIONS!$G$5:$G$244,"Operating Expense",TRANSACTIONS!$J$5:$J$244,$B15)) | K15: =(SUMIFS(TRANSACTIONS!$D$5:$D$244,TRANSACTIONS!$E$5:$E$244,"Sole Prop",TRANSACTIONS!$G$5:$G$244,"Payroll",TRANSACTIONS!$J$5:$J$244,$B15)+SUMIFS(TRANSACTIONS!$D$5:$D$244,TRANSACTIONS!$E$5:$E$244,"Corporation",TRANSACTIONS!$G$5:$G$244,"Payroll",TRANSACTIONS!$J$5:$J$244,$B15)) | L15: =(SUMIFS(TRANSACTIONS!$D$5:$D$244,TRANSACTIONS!$E$5:$E$244,"Sole Prop",TRANSACTIONS!$G$5:$G$244,"Tax/Remittance",TRANSACTIONS!$J$5:$J$244,$B15)+SUMIFS(TRANSACTIONS!$D$5:$D$244,TRANSACTIONS!$E$5:$E$244,"Corporation",TRANSACTIONS!$G$5:$G$244,"Tax/Remittance",TRANSACTIONS!$J$5:$J$244,$B15)) | M15: =(SUMIFS(TRANSACTIONS!$D$5:$D$244,TRANSACTIONS!$E$5:$E$244,"Sole Prop",TRANSACTIONS!$G$5:$G$244,"Owner Draw/Comp",TRANSACTIONS!$J$5:$J$244,$B15)+SUMIFS(TRANSACTIONS!$D$5:$D$244,TRANSACTIONS!$E$5:$E$244,"Corporation",TRANSACTIONS!$G$5:$G$244,"Owner Draw/Comp",TRANSACTIONS!$J$5:$J$244,$B15)) | N15: =(SUMIFS(TRANSACTIONS!$D$5:$D$244,TRANSACTIONS!$E$5:$E$244,"Sole Prop",TRANSACTIONS!$G$5:$G$244,"Capital Purchase",TRANSACTIONS!$J$5:$J$244,$B15)+SUMIFS(TRANSACTIONS!$D$5:$D$244,TRANSACTIONS!$E$5:$E$244,"Corporation",TRANSACTIONS!$G$5:$G$244,"Capital Purchase",TRANSACTIONS!$J$5:$J$244,$B15)) | O15: =(SUMIFS(TRANSACTIONS!$D$5:$D$244,TRANSACTIONS!$E$5:$E$244,"Sole Prop",TRANSACTIONS!$G$5:$G$244,"Financing",TRANSACTIONS!$J$5:$J$244,$B15)+SUMIFS(TRANSACTIONS!$D$5:$D$244,TRANSACTIONS!$E$5:$E$244,"Corporation",TRANSACTIONS!$G$5:$G$244,"Financing",TRANSACTIONS!$J$5:$J$244,$B15)) | P15: =C15+F15+I15+J15+K15+L15 | Q15: =SUMIFS(TRANSACTIONS!$D$5:$D$244,TRANSACTIONS!$E$5:$E$244,"Sole Prop",TRANSACTIONS!$J$5:$J$244,$B15)+SUMIFS(TRANSACTIONS!$D$5:$D$244,TRANSACTIONS!$E$5:$E$244,"Corporation",TRANSACTIONS!$J$5:$J$244,$B15) | R15: =SUMIFS(TRANSACTIONS!$D$5:$D$244,TRANSACTIONS!$E$5:$E$244,"Personal",TRANSACTIONS!$J$5:$J$244,$B15) | S15: =S14+SUMIFS(TRANSACTIONS!$D$5:$D$244,TRANSACTIONS!$E$5:$E$244,"Sole Prop",TRANSACTIONS!$J$5:$J$244,$B15) | T15: =T14+SUMIFS(TRANSACTIONS!$D$5:$D$244,TRANSACTIONS!$E$5:$E$244,"Corporation",TRANSACTIONS!$J$5:$J$244,$B15) | U15: =U14+R15 | V15: =S15+T15+U15
A16: Dec 2026 | B16: 202612 | C16: =SUMIFS(TRANSACTIONS!$D$5:$D$244,TRANSACTIONS!$E$5:$E$244,"Sole Prop",TRANSACTIONS!$G$5:$G$244,"Revenue",TRANSACTIONS!$J$5:$J$244,$B16) | D16: =-SUMIFS(TRANSACTIONS!$I$5:$I$244,TRANSACTIONS!$E$5:$E$244,"Sole Prop",TRANSACTIONS!$G$5:$G$244,"Revenue",TRANSACTIONS!$J$5:$J$244,$B16) | E16: =C16+D16 | F16: =SUMIFS(TRANSACTIONS!$D$5:$D$244,TRANSACTIONS!$E$5:$E$244,"Corporation",TRANSACTIONS!$G$5:$G$244,"Revenue",TRANSACTIONS!$J$5:$J$244,$B16) | G16: =-SUMIFS(TRANSACTIONS!$I$5:$I$244,TRANSACTIONS!$E$5:$E$244,"Corporation",TRANSACTIONS!$G$5:$G$244,"Revenue",TRANSACTIONS!$J$5:$J$244,$B16) | H16: =F16+G16 | I16: =(SUMIFS(TRANSACTIONS!$D$5:$D$244,TRANSACTIONS!$E$5:$E$244,"Sole Prop",TRANSACTIONS!$G$5:$G$244,"COGS",TRANSACTIONS!$J$5:$J$244,$B16)+SUMIFS(TRANSACTIONS!$D$5:$D$244,TRANSACTIONS!$E$5:$E$244,"Corporation",TRANSACTIONS!$G$5:$G$244,"COGS",TRANSACTIONS!$J$5:$J$244,$B16)) | J16: =(SUMIFS(TRANSACTIONS!$D$5:$D$244,TRANSACTIONS!$E$5:$E$244,"Sole Prop",TRANSACTIONS!$G$5:$G$244,"Operating Expense",TRANSACTIONS!$J$5:$J$244,$B16)+SUMIFS(TRANSACTIONS!$D$5:$D$244,TRANSACTIONS!$E$5:$E$244,"Corporation",TRANSACTIONS!$G$5:$G$244,"Operating Expense",TRANSACTIONS!$J$5:$J$244,$B16)) | K16: =(SUMIFS(TRANSACTIONS!$D$5:$D$244,TRANSACTIONS!$E$5:$E$244,"Sole Prop",TRANSACTIONS!$G$5:$G$244,"Payroll",TRANSACTIONS!$J$5:$J$244,$B16)+SUMIFS(TRANSACTIONS!$D$5:$D$244,TRANSACTIONS!$E$5:$E$244,"Corporation",TRANSACTIONS!$G$5:$G$244,"Payroll",TRANSACTIONS!$J$5:$J$244,$B16)) | L16: =(SUMIFS(TRANSACTIONS!$D$5:$D$244,TRANSACTIONS!$E$5:$E$244,"Sole Prop",TRANSACTIONS!$G$5:$G$244,"Tax/Remittance",TRANSACTIONS!$J$5:$J$244,$B16)+SUMIFS(TRANSACTIONS!$D$5:$D$244,TRANSACTIONS!$E$5:$E$244,"Corporation",TRANSACTIONS!$G$5:$G$244,"Tax/Remittance",TRANSACTIONS!$J$5:$J$244,$B16)) | M16: =(SUMIFS(TRANSACTIONS!$D$5:$D$244,TRANSACTIONS!$E$5:$E$244,"Sole Prop",TRANSACTIONS!$G$5:$G$244,"Owner Draw/Comp",TRANSACTIONS!$J$5:$J$244,$B16)+SUMIFS(TRANSACTIONS!$D$5:$D$244,TRANSACTIONS!$E$5:$E$244,"Corporation",TRANSACTIONS!$G$5:$G$244,"Owner Draw/Comp",TRANSACTIONS!$J$5:$J$244,$B16)) | N16: =(SUMIFS(TRANSACTIONS!$D$5:$D$244,TRANSACTIONS!$E$5:$E$244,"Sole Prop",TRANSACTIONS!$G$5:$G$244,"Capital Purchase",TRANSACTIONS!$J$5:$J$244,$B16)+SUMIFS(TRANSACTIONS!$D$5:$D$244,TRANSACTIONS!$E$5:$E$244,"Corporation",TRANSACTIONS!$G$5:$G$244,"Capital Purchase",TRANSACTIONS!$J$5:$J$244,$B16)) | O16: =(SUMIFS(TRANSACTIONS!$D$5:$D$244,TRANSACTIONS!$E$5:$E$244,"Sole Prop",TRANSACTIONS!$G$5:$G$244,"Financing",TRANSACTIONS!$J$5:$J$244,$B16)+SUMIFS(TRANSACTIONS!$D$5:$D$244,TRANSACTIONS!$E$5:$E$244,"Corporation",TRANSACTIONS!$G$5:$G$244,"Financing",TRANSACTIONS!$J$5:$J$244,$B16)) | P16: =C16+F16+I16+J16+K16+L16 | Q16: =SUMIFS(TRANSACTIONS!$D$5:$D$244,TRANSACTIONS!$E$5:$E$244,"Sole Prop",TRANSACTIONS!$J$5:$J$244,$B16)+SUMIFS(TRANSACTIONS!$D$5:$D$244,TRANSACTIONS!$E$5:$E$244,"Corporation",TRANSACTIONS!$J$5:$J$244,$B16) | R16: =SUMIFS(TRANSACTIONS!$D$5:$D$244,TRANSACTIONS!$E$5:$E$244,"Personal",TRANSACTIONS!$J$5:$J$244,$B16) | S16: =S15+SUMIFS(TRANSACTIONS!$D$5:$D$244,TRANSACTIONS!$E$5:$E$244,"Sole Prop",TRANSACTIONS!$J$5:$J$244,$B16) | T16: =T15+SUMIFS(TRANSACTIONS!$D$5:$D$244,TRANSACTIONS!$E$5:$E$244,"Corporation",TRANSACTIONS!$J$5:$J$244,$B16) | U16: =U15+R16 | V16: =S16+T16+U16
A17: Jan 2027 | B17: 202701 | C17: =SUMIFS(TRANSACTIONS!$D$5:$D$244,TRANSACTIONS!$E$5:$E$244,"Sole Prop",TRANSACTIONS!$G$5:$G$244,"Revenue",TRANSACTIONS!$J$5:$J$244,$B17) | D17: =-SUMIFS(TRANSACTIONS!$I$5:$I$244,TRANSACTIONS!$E$5:$E$244,"Sole Prop",TRANSACTIONS!$G$5:$G$244,"Revenue",TRANSACTIONS!$J$5:$J$244,$B17) | E17: =C17+D17 | F17: =SUMIFS(TRANSACTIONS!$D$5:$D$244,TRANSACTIONS!$E$5:$E$244,"Corporation",TRANSACTIONS!$G$5:$G$244,"Revenue",TRANSACTIONS!$J$5:$J$244,$B17) | G17: =-SUMIFS(TRANSACTIONS!$I$5:$I$244,TRANSACTIONS!$E$5:$E$244,"Corporation",TRANSACTIONS!$G$5:$G$244,"Revenue",TRANSACTIONS!$J$5:$J$244,$B17) | H17: =F17+G17 | I17: =(SUMIFS(TRANSACTIONS!$D$5:$D$244,TRANSACTIONS!$E$5:$E$244,"Sole Prop",TRANSACTIONS!$G$5:$G$244,"COGS",TRANSACTIONS!$J$5:$J$244,$B17)+SUMIFS(TRANSACTIONS!$D$5:$D$244,TRANSACTIONS!$E$5:$E$244,"Corporation",TRANSACTIONS!$G$5:$G$244,"COGS",TRANSACTIONS!$J$5:$J$244,$B17)) | J17: =(SUMIFS(TRANSACTIONS!$D$5:$D$244,TRANSACTIONS!$E$5:$E$244,"Sole Prop",TRANSACTIONS!$G$5:$G$244,"Operating Expense",TRANSACTIONS!$J$5:$J$244,$B17)+SUMIFS(TRANSACTIONS!$D$5:$D$244,TRANSACTIONS!$E$5:$E$244,"Corporation",TRANSACTIONS!$G$5:$G$244,"Operating Expense",TRANSACTIONS!$J$5:$J$244,$B17)) | K17: =(SUMIFS(TRANSACTIONS!$D$5:$D$244,TRANSACTIONS!$E$5:$E$244,"Sole Prop",TRANSACTIONS!$G$5:$G$244,"Payroll",TRANSACTIONS!$J$5:$J$244,$B17)+SUMIFS(TRANSACTIONS!$D$5:$D$244,TRANSACTIONS!$E$5:$E$244,"Corporation",TRANSACTIONS!$G$5:$G$244,"Payroll",TRANSACTIONS!$J$5:$J$244,$B17)) | L17: =(SUMIFS(TRANSACTIONS!$D$5:$D$244,TRANSACTIONS!$E$5:$E$244,"Sole Prop",TRANSACTIONS!$G$5:$G$244,"Tax/Remittance",TRANSACTIONS!$J$5:$J$244,$B17)+SUMIFS(TRANSACTIONS!$D$5:$D$244,TRANSACTIONS!$E$5:$E$244,"Corporation",TRANSACTIONS!$G$5:$G$244,"Tax/Remittance",TRANSACTIONS!$J$5:$J$244,$B17)) | M17: =(SUMIFS(TRANSACTIONS!$D$5:$D$244,TRANSACTIONS!$E$5:$E$244,"Sole Prop",TRANSACTIONS!$G$5:$G$244,"Owner Draw/Comp",TRANSACTIONS!$J$5:$J$244,$B17)+SUMIFS(TRANSACTIONS!$D$5:$D$244,TRANSACTIONS!$E$5:$E$244,"Corporation",TRANSACTIONS!$G$5:$G$244,"Owner Draw/Comp",TRANSACTIONS!$J$5:$J$244,$B17)) | N17: =(SUMIFS(TRANSACTIONS!$D$5:$D$244,TRANSACTIONS!$E$5:$E$244,"Sole Prop",TRANSACTIONS!$G$5:$G$244,"Capital Purchase",TRANSACTIONS!$J$5:$J$244,$B17)+SUMIFS(TRANSACTIONS!$D$5:$D$244,TRANSACTIONS!$E$5:$E$244,"Corporation",TRANSACTIONS!$G$5:$G$244,"Capital Purchase",TRANSACTIONS!$J$5:$J$244,$B17)) | O17: =(SUMIFS(TRANSACTIONS!$D$5:$D$244,TRANSACTIONS!$E$5:$E$244,"Sole Prop",TRANSACTIONS!$G$5:$G$244,"Financing",TRANSACTIONS!$J$5:$J$244,$B17)+SUMIFS(TRANSACTIONS!$D$5:$D$244,TRANSACTIONS!$E$5:$E$244,"Corporation",TRANSACTIONS!$G$5:$G$244,"Financing",TRANSACTIONS!$J$5:$J$244,$B17)) | P17: =C17+F17+I17+J17+K17+L17 | Q17: =SUMIFS(TRANSACTIONS!$D$5:$D$244,TRANSACTIONS!$E$5:$E$244,"Sole Prop",TRANSACTIONS!$J$5:$J$244,$B17)+SUMIFS(TRANSACTIONS!$D$5:$D$244,TRANSACTIONS!$E$5:$E$244,"Corporation",TRANSACTIONS!$J$5:$J$244,$B17) | R17: =SUMIFS(TRANSACTIONS!$D$5:$D$244,TRANSACTIONS!$E$5:$E$244,"Personal",TRANSACTIONS!$J$5:$J$244,$B17) | S17: =S16+SUMIFS(TRANSACTIONS!$D$5:$D$244,TRANSACTIONS!$E$5:$E$244,"Sole Prop",TRANSACTIONS!$J$5:$J$244,$B17) | T17: =T16+SUMIFS(TRANSACTIONS!$D$5:$D$244,TRANSACTIONS!$E$5:$E$244,"Corporation",TRANSACTIONS!$J$5:$J$244,$B17) | U17: =U16+R17 | V17: =S17+T17+U17
A18: FULL YEAR | C18: =SUM(C6:C17) | D18: =SUM(D6:D17) | E18: =SUM(E6:E17) | F18: =SUM(F6:F17) | G18: =SUM(G6:G17) | H18: =SUM(H6:H17) | I18: =SUM(I6:I17) | J18: =SUM(J6:J17) | ... R18: =SUM(R6:R17) | S18: =S17 | T18: =T17 | U18: =U17 | V18: =V17
A20: Sole prop period is Feb-Jun; corporation is Jul-Jan. If sole prop revenue appears after June, or corporate revenue before July, check the entity on those transactions.

Sheet BUSINESS PERFORMANCE
A1: Business Performance — the two entities, never combined
A2: Cash basis: this is money that actually moved. It is not accrual profit. GST is stripped out of revenue because it was never yours.
A4: Line | B4: Sole Proprietorship Feb 1 - Jun 30 | C4: Corporation Jul 1 - Jan 31 | D4: Combined (memo only)
A5: Gross revenue collected (includes GST) | B5: =SUMIFS(TRANSACTIONS!$D$5:$D$244,TRANSACTIONS!$E$5:$E$244,"Sole Prop",TRANSACTIONS!$G$5:$G$244,"Revenue") | C5: =SUMIFS(TRANSACTIONS!$D$5:$D$244,TRANSACTIONS!$E$5:$E$244,"Corporation",TRANSACTIONS!$G$5:$G$244,"Revenue") | D5: =B5+C5
A6: Less: GST collected (belongs to CRA) | B6: =-SUMIFS(TRANSACTIONS!$I$5:$I$244,TRANSACTIONS!$E$5:$E$244,"Sole Prop",TRANSACTIONS!$G$5:$G$244,"Revenue") | C6: =-SUMIFS(TRANSACTIONS!$I$5:$I$244,TRANSACTIONS!$E$5:$E$244,"Corporation",TRANSACTIONS!$G$5:$G$244,"Revenue") | D6: =B6+C6
A7: REVENUE EXCLUDING GST | B7: =B5+B6 | C7: =C5+C6 | D7: =B7+C7
A8: COGS — materials and plants | B8: =SUMIFS(TRANSACTIONS!$D$5:$D$244,TRANSACTIONS!$E$5:$E$244,"Sole Prop",TRANSACTIONS!$F$5:$F$244,"Materials and plants") | C8: =SUMIFS(TRANSACTIONS!$D$5:$D$244,TRANSACTIONS!$E$5:$E$244,"Corporation",TRANSACTIONS!$F$5:$F$244,"Materials and plants") | D8: =B8+C8
A9: COGS — subcontractors | B9: =SUMIFS(TRANSACTIONS!$D$5:$D$244,TRANSACTIONS!$E$5:$E$244,"Sole Prop",TRANSACTIONS!$F$5:$F$244,"Subcontractor") | C9: =SUMIFS(TRANSACTIONS!$D$5:$D$244,TRANSACTIONS!$E$5:$E$244,"Corporation",TRANSACTIONS!$F$5:$F$244,"Subcontractor") | D9: =B9+C9
A10: COGS — equipment rental | B10: =SUMIFS(TRANSACTIONS!$D$5:$D$244,TRANSACTIONS!$E$5:$E$244,"Sole Prop",TRANSACTIONS!$F$5:$F$244,"Equipment rental") | C10: =SUMIFS(TRANSACTIONS!$D$5:$D$244,TRANSACTIONS!$E$5:$E$244,"Corporation",TRANSACTIONS!$F$5:$F$244,"Equipment rental") | D10: =B10+C10
A11: COGS — disposal and dump fees | B11: =SUMIFS(TRANSACTIONS!$D$5:$D$244,TRANSACTIONS!$E$5:$E$244,"Sole Prop",TRANSACTIONS!$F$5:$F$244,"Disposal and dump fees") | C11: =SUMIFS(TRANSACTIONS!$D$5:$D$244,TRANSACTIONS!$E$5:$E$244,"Corporation",TRANSACTIONS!$F$5:$F$244,"Disposal and dump fees") | D11: =B11+C11
A12: GROSS MARGIN | B12: =B7+SUM(B8:B11) | C12: =C7+SUM(C8:C11) | D12: =B12+C12
A13: Gross margin % | B13: =IF(B7=0,"",B12/B7) | C13: =IF(C7=0,"",C12/C7) | D13: =IF(D7=0,"",D12/D7)
A14: Payroll (crew wages and payroll fees) | B14: =SUMIFS(TRANSACTIONS!$D$5:$D$244,TRANSACTIONS!$E$5:$E$244,"Sole Prop",TRANSACTIONS!$G$5:$G$244,"Payroll") | C14: =SUMIFS(TRANSACTIONS!$D$5:$D$244,TRANSACTIONS!$E$5:$E$244,"Corporation",TRANSACTIONS!$G$5:$G$244,"Payroll") | D14: =B14+C14
A15: Vehicle running costs (fuel, repairs, insurance) | B15: =SUMIFS(TRANSACTIONS!$D$5:$D$244,TRANSACTIONS!$E$5:$E$244,"Sole Prop",TRANSACTIONS!$F$5:$F$244,"Fuel")+SUMIFS(TRANSACTIONS!$D$5:$D$244,TRANSACTIONS!$E$5:$E$244,"Sole Prop",TRANSACTIONS!$F$5:$F$244,"Vehicle repairs and maintenance")+SUMIFS(TRANSACTIONS!$D$5:$D$244,TRANSACTIONS!$E$5:$E$244,"Sole Prop",TRANSACTIONS!$F$5:$F$244,"Vehicle insurance") | C15: =SUMIFS(TRANSACTIONS!$D$5:$D$244,TRANSACTIONS!$E$5:$E$244,"Corporation",TRANSACTIONS!$F$5:$F$244,"Fuel")+SUMIFS(TRANSACTIONS!$D$5:$D$244,TRANSACTIONS!$E$5:$E$244,"Corporation",TRANSACTIONS!$F$5:$F$244,"Vehicle repairs and maintenance")+SUMIFS(TRANSACTIONS!$D$5:$D$244,TRANSACTIONS!$E$5:$E$244,"Corporation",TRANSACTIONS!$F$5:$F$244,"Vehicle insurance") | D15: =B15+C15
A16: All other operating expenses | B16: =(SUMIFS(TRANSACTIONS!$D$5:$D$244,TRANSACTIONS!$E$5:$E$244,"Sole Prop",TRANSACTIONS!$G$5:$G$244,"Operating Expense")-(SUMIFS(TRANSACTIONS!$D$5:$D$244,TRANSACTIONS!$E$5:$E$244,"Sole Prop",TRANSACTIONS!$F$5:$F$244,"Fuel")+SUMIFS(TRANSACTIONS!$D$5:$D$244,TRANSACTIONS!$E$5:$E$244,"Sole Prop",TRANSACTIONS!$F$5:$F$244,"Vehicle repairs and maintenance")+SUMIFS(TRANSACTIONS!$D$5:$D$244,TRANSACTIONS!$E$5:$E$244,"Sole Prop",TRANSACTIONS!$F$5:$F$244,"Vehicle insurance"))) | C16: =(SUMIFS(TRANSACTIONS!$D$5:$D$244,TRANSACTIONS!$E$5:$E$244,"Corporation",TRANSACTIONS!$G$5:$G$244,"Operating Expense")-(SUMIFS(TRANSACTIONS!$D$5:$D$244,TRANSACTIONS!$E$5:$E$244,"Corporation",TRANSACTIONS!$F$5:$F$244,"Fuel")+SUMIFS(TRANSACTIONS!$D$5:$D$244,TRANSACTIONS!$E$5:$E$244,"Corporation",TRANSACTIONS!$F$5:$F$244,"Vehicle repairs and maintenance")+SUMIFS(TRANSACTIONS!$D$5:$D$244,TRANSACTIONS!$E$5:$E$244,"Corporation",TRANSACTIONS!$F$5:$F$244,"Vehicle insurance"))) | D16: =B16+C16
A17: APPROXIMATE OPERATING PROFIT (cash basis) | B17: =B12+SUM(B14:B16) | C17: =C12+SUM(C14:C16) | D17: =B17+C17
A18: Operating margin % | B18: =IF(B7=0,"",B17/B7) | C18: =IF(C7=0,"",C17/C7) | D18: =IF(D7=0,"",D17/D7)
A20: Reconciliation from profit to cash
A21: Capital purchases (vehicles, equipment) | B21: =SUMIFS(TRANSACTIONS!$D$5:$D$244,TRANSACTIONS!$E$5:$E$244,"Sole Prop",TRANSACTIONS!$G$5:$G$244,"Capital Purchase") | C21: =SUMIFS(TRANSACTIONS!$D$5:$D$244,TRANSACTIONS!$E$5:$E$244,"Corporation",TRANSACTIONS!$G$5:$G$244,"Capital Purchase") | D21: =B21+C21
A22: Financing — loans, leases, contributions (net) | B22: =SUMIFS(TRANSACTIONS!$D$5:$D$244,TRANSACTIONS!$E$5:$E$244,"Sole Prop",TRANSACTIONS!$G$5:$G$244,"Financing") | C22: =SUMIFS(TRANSACTIONS!$D$5:$D$244,TRANSACTIONS!$E$5:$E$244,"Corporation",TRANSACTIONS!$G$5:$G$244,"Financing") | D22: =B22+C22
A23: Taxes and remittances paid (incl. GST remitted) | B23: =SUMIFS(TRANSACTIONS!$D$5:$D$244,TRANSACTIONS!$E$5:$E$244,"Sole Prop",TRANSACTIONS!$G$5:$G$244,"Tax/Remittance") | C23: =SUMIFS(TRANSACTIONS!$D$5:$D$244,TRANSACTIONS!$E$5:$E$244,"Corporation",TRANSACTIONS!$G$5:$G$244,"Tax/Remittance") | D23: =B23+C23
A24: Owner draws / compensation | B24: =SUMIFS(TRANSACTIONS!$D$5:$D$244,TRANSACTIONS!$E$5:$E$244,"Sole Prop",TRANSACTIONS!$G$5:$G$244,"Owner Draw/Comp") | C24: =SUMIFS(TRANSACTIONS!$D$5:$D$244,TRANSACTIONS!$E$5:$E$244,"Corporation",TRANSACTIONS!$G$5:$G$244,"Owner Draw/Comp") | D24: =B24+C24
A25: GST collected but not yet remitted (add back) | B25: =-B6 | C25: =-C6 | D25: =B25+C25
A26: Net transfers in / out | B26: =SUMIFS(TRANSACTIONS!$D$5:$D$244,TRANSACTIONS!$E$5:$E$244,"Sole Prop",TRANSACTIONS!$G$5:$G$244,"Transfer") | C26: =SUMIFS(TRANSACTIONS!$D$5:$D$244,TRANSACTIONS!$E$5:$E$244,"Corporation",TRANSACTIONS!$G$5:$G$244,"Transfer") | D26: =B26+C26
A27: Unclassified | B27: =SUMIFS(TRANSACTIONS!$D$5:$D$244,TRANSACTIONS!$E$5:$E$244,"Sole Prop",TRANSACTIONS!$G$5:$G$244,"Review") | C27: =SUMIFS(TRANSACTIONS!$D$5:$D$244,TRANSACTIONS!$E$5:$E$244,"Corporation",TRANSACTIONS!$G$5:$G$244,"Review") | D27: =B27+C27
A28: CASH GENERATED / (USED) | B28: =B17+SUM(B21:B27) | C28: =C17+SUM(C21:C27) | D28: =B28+C28
A29: Opening cash | B29: ='ACCOUNT MAP'!$E$48 | C29: ='ACCOUNT MAP'!$E$49 | D29: =B29+C29
A30: ENDING CASH | B30: =B28+B29 | C30: =C28+C29 | D30: =B30+C30
A32: Cross-check: this ending cash vs CASH RECONCILIATION (must be zero) | B32: =B30-'CASH RECONCILIATION'!C19 | C32: =C30-'CASH RECONCILIATION'!D19
A34: Operating profit here is CASH received less CASH paid. It is not accrual profit: unpaid invoices are not in it, and unpaid bills are not either.
A35: The reconciliation block below the profit line is the cash-versus-profit bridge. Capital purchases, loan principal, owner draws and GST timing are the usual reasons a profitable season leaves you with no money.
A36: The Combined column is a memo total only. The two entities are separate taxpayers and must never be combined for tax or legal purposes.

Sheet CRA LIABILITY
A1: CRA Liability — money in your account that is not yours
A2: You confirmed no GST and no payroll remittances have been made this year. This tab sizes what is owed. Treat it as the first claim on cash, ahead of every other use.
A4: 1. GST — collected but not remitted
A5: GST collected on all revenue (from TRANSACTIONS column I) | B5: =SUMIFS(TRANSACTIONS!$I$5:$I$244,TRANSACTIONS!$E$5:$E$244,"Sole Prop")+SUMIFS(TRANSACTIONS!$I$5:$I$244,TRANSACTIONS!$E$5:$E$244,"Corporation") | E5: If you did not track GST per deposit, enter it manually below instead.
A6: OR: manual override — total GST collected | E6: Use this if column I is blank. Rough method: revenue that included GST divided by 1.05, times 0.05.
A7: Input tax credits — GST you paid on supplies, fuel, equipment | E7: Enter as a POSITIVE number. This reduces what you owe. Roughly 5% of GST-bearing business purchases. Worth reconstructing from receipts — it is real money back.
A8: NET GST OWING (estimate) | B8: =MAX(0,IF(B6>0,B6,B5)-B7) | E8: Sole prop and corporation file separately. If the corporation did not register for its own GST number, that is a separate problem — flag it with your accountant.
A9: Estimated late-filing penalty and interest | B9: =B8*ASSUMPTIONS!$C$17 | E9: ESTIMATE. GST late-filing penalty is calculated on a formula tied to how late you are, plus interest. This is an order-of-magnitude placeholder, not a computed amount.
A11: 2. Payroll source deductions — withheld but not remitted
A12: Gross wages paid to employees, year to date | B12: 16381.73 | E12: GROSS, before deductions. If you have been paying Kierran the full $27/hr with nothing withheld, then no deductions were actually taken and the whole employer+employee amount is owed out of business cash.
A13: CPP — employee and employer combined | B13: =MAX(0,B12-ASSUMPTIONS!$C$13)*ASSUMPTIONS!$C$12*2 | E13: ESTIMATE. Employer must match the employee portion dollar for dollar.
A14: EI — employee and employer combined | B14: =B12*ASSUMPTIONS!$C$14*(1+ASSUMPTIONS!$C$15) | E14: ESTIMATE. Employer pays 1.4x the employee premium.
A15: Income tax that should have been withheld | B15: =B12*ASSUMPTIONS!$C$16 | E15: ESTIMATE at the assumed blended rate. Replace with a real payroll calculation.
A16: TOTAL PAYROLL REMITTANCE OWING (estimate) | B16: =SUM(B13:B15)
A17: Estimated penalty | B17: =B16*ASSUMPTIONS!$C$17 | E17: 10% on a first failure, 20% if repeated or grossly negligent, plus interest. Source deductions are trust funds — CRA treats these far more seriously than an unpaid tax bill.
A19: 3. Income tax not yet paid
A20: Sole prop net income, Feb-Jun (from BUSINESS PERFORMANCE) | B20: ='BUSINESS PERFORMANCE'!B17 | E20: Cash-basis operating profit. Your actual taxable income will differ once receivables, payables and depreciation are counted.
A21: Personal tax reserve on sole prop income | B21: =MAX(0,B20)*ASSUMPTIONS!$C$19 | E21: ESTIMATE at the reserve rate on ASSUMPTIONS. This is YOUR personal tax, payable April 30, 2027.
A22: Corporate net income, Jul-Jan (from BUSINESS PERFORMANCE) | B22: ='BUSINESS PERFORMANCE'!C17
A23: Corporate tax reserve | B23: =MAX(0,B22)*ASSUMPTIONS!$C$18 | E23: ESTIMATE. Due roughly 3 months after the Jan 31 year end. Owner salary, if declared, reduces this — but creates payroll remittances instead.
A25: 4. Total
A26: TOTAL OWED TO CRA (estimate, including penalties) | B26: =B8+B9+B16+B17+B21+B23 | E26: This is the amount that must come out of your cash before you can call anything deployable.
A27: Total business cash on hand | B27: ='CASH RECONCILIATION'!C19+'CASH RECONCILIATION'!D19 | E27: Sole prop plus corporation.
A28: BUSINESS CASH AFTER CRA IS PAID | B28: =B27-B26 | E28: If this is negative, you have a solvency problem, not a planning problem. Deal with CRA first.
A31: DIRECTOR LIABILITY: as a director of the corporation you are personally liable for unremitted source deductions and GST. Incorporating does not protect you from these two specific debts. It does protect you from most ordinary trade debt.
A32: The sole proprietorship's GST and payroll obligations are yours personally in any case — a sole prop is not a separate legal person.
A33: Voluntary disclosure: filing and paying before CRA contacts you generally produces a far better outcome than waiting. Talk to an accountant about the Voluntary Disclosures Program before you file, not after.
A34: Every figure on this tab is an ESTIMATE built on the rates in ASSUMPTIONS. It is sized to tell you the order of magnitude and to stop you spending money that is not yours. It is not a filing.

Sheet CASH QUALITY
A1: Cash Quality — what the bank balance actually means
A2: A balance is not the same as available money. This tab strips out what is already committed.
A5: A | B5: Total business cash on hand (sole prop + corporation) | C5: ='CASH RECONCILIATION'!C19+'CASH RECONCILIATION'!D19 | D5: From the reconciliation. Only counts if the difference row there is zero.
A6: B | B6: Less: total owed to CRA (GST, payroll, income tax, penalties) | C6: =-'CRA LIABILITY'!B26 | D6: Not your money. This comes off before anything else.
A7: C | B7: Cash after CRA is settled | C7: =C5+C6 | D7: The real starting point for every decision below.
A8: D | B8: Average monthly operating cost (opex + payroll) | C8: =ABS('MONTH BY MONTH'!J18+'MONTH BY MONTH'!K18)/12 | D8: Full-year average. Seasonal businesses run well above this in summer and below it in winter.
A9: E | B9: Recommended operating reserve | C9: =C8*ASSUMPTIONS!$C$20 | D9: Months of reserve set on ASSUMPTIONS. For a seasonal trade with a winter revenue gap, three months is a floor, not a target.
A10: F | B10: DEPLOYABLE CAPITAL | C10: =MAX(0,C7-C9) | D10: What you could actually spend on vehicles, equipment, hiring or growth without putting the business under pressure. If this is zero, the answer to every spending question is no.
A12: 1 | B12: How much cash is truly available for business use? | C12: =C10 | D12: Deployable capital, line F.
A13: 2 | B13: How much should be reserved for taxes? | C13: ='CRA LIABILITY'!B26 | D13: Everything on the CRA LIABILITY tab. Move it to a separate savings account today — money in the operating account gets spent.
A14: 3 | B14: How much should stay as an operating emergency reserve? | C14: =C9 | D14: Held in cash, not invested, not in a term deposit you cannot break.
A15: 4 | B15: How much could go into vehicles and equipment? | C15: =MAX(0,C10*0.5) | D15: Half of deployable capital as a working rule, so a single purchase does not consume the entire buffer. See VEHICLE SCENARIOS.
A16: 5 | B16: How much could be taken personally? | C16: =MAX(0,C10*0.3) | D16: Roughly a third of deployable capital, AFTER the CRA reserve is funded. Note this is on top of the $4,000/month you are already drawing.
A17: 6 | B17: How many months of operating expenses does the business hold? | C17: =IF(C8=0,"",C7/C8) | D17: Counts cash after CRA. Under 3 is fragile for a seasonal business facing a winter with no revenue.
A18: 7 | B18: Approximate monthly cash burn | C18: =C8 | D18: What leaves the account each month on average for opex and payroll.
A19: 8 | B19: Average monthly revenue, excluding GST | C19: =IF(ASSUMPTIONS!$C$21=0,"",('BUSINESS PERFORMANCE'!B7+'BUSINESS PERFORMANCE'!C7)/ASSUMPTIONS!$C$21) | D19: Averaged over revenue-generating months only, not all 12. Set that month count on ASSUMPTIONS.
A20: 9 | B20: Average monthly operating cost | C20: =C8 | D20: Same as line D.
A21: 10 | B21: Approximate monthly free cash generation | C21: =IF(ASSUMPTIONS!$C$21=0,"",('BUSINESS PERFORMANCE'!D17)/ASSUMPTIONS!$C$21) | D21: Operating profit per active month. This is what funds everything: your pay, reserves, equipment, growth.
A23: W | B23: Winter burn — cost of the non-revenue months | C23: =C8*(12-ASSUMPTIONS!$C$21) | D23: What it costs to keep the business alive from the end of the season to the start of the next one. This must be sitting in cash before winter, not hoped for.
A24: X | B24: Owner draws taken from the corporation, annualised | C24: =ASSUMPTIONS!$C$10*7 | D24: $4,000/month across the seven corporate months. Currently a shareholder loan, not salary or dividend.

Sheet VEHICLE SCENARIOS
A1: Vehicle Purchase — what each price does to your reserves
A2: Every column starts from deployable capital on CASH QUALITY. A verdict of NO means the purchase would eat the operating reserve.
A4: Line | B4: $20,000 | C4: $30,000 | D4: $40,000 | E4: $50,000
A5: Vehicle price before tax
A6: GST at 5% | B6: =B5*ASSUMPTIONS!$C$11 | C6: =C5*ASSUMPTIONS!$C$11 | D6: =D5*ASSUMPTIONS!$C$11 | E6: =E5*ASSUMPTIONS!$C$11
A7: Total cash out if purchased outright | B7: =B5+B6 | C7: =C5+C6 | D7: =D5+D6 | E7: =E5+E6
A9: PAID IN CASH
A10: Deployable capital before purchase | B10: ='CASH QUALITY'!$C$10 | C10: ='CASH QUALITY'!$C$10 | D10: ='CASH QUALITY'!$C$10 | E10: ='CASH QUALITY'!$C$10
A11: Deployable capital after purchase | B11: =B10-B7 | C11: =C10-C7 | D11: =D10-D7 | E11: =E10-E7
A12: Months of operating cost still covered | B12: =IF('CASH QUALITY'!$C$8=0,"",('CASH QUALITY'!$C$7-B7)/'CASH QUALITY'!$C$8) | C12: =IF('CASH QUALITY'!$C$8=0,"",('CASH QUALITY'!$C$7-C7)/'CASH QUALITY'!$C$8) | D12: =IF('CASH QUALITY'!$C$8=0,"",('CASH QUALITY'!$C$7-D7)/'CASH QUALITY'!$C$8) | E12: =IF('CASH QUALITY'!$C$8=0,"",('CASH QUALITY'!$C$7-E7)/'CASH QUALITY'!$C$8)
A13: Verdict | B13: =IF(B11<0,"NO - eats the reserve",IF(B11<B7,"TIGHT - review","OK")) | C13: =IF(C11<0,"NO - eats the reserve",IF(C11<C7,"TIGHT - review","OK")) | D13: =IF(D11<0,"NO - eats the reserve",IF(D11<D7,"TIGHT - review","OK")) | E13: =IF(E11<0,"NO - eats the reserve",IF(E11<E7,"TIGHT - review","OK"))
A15: FINANCED
A16: Down payment at 15% | B16: =B7*0.15 | C16: =C7*0.15 | D16: =D7*0.15 | E16: =E7*0.15
A17: Amount financed | B17: =B7-B16 | C17: =C7-C16 | D17: =D7-D16 | E17: =E7-E16
A18: Estimated monthly payment (60 months, 9%) | B18: =-PMT(0.09/12,60,B17) | C18: =-PMT(0.09/12,60,C17) | D18: =-PMT(0.09/12,60,D17) | E18: =-PMT(0.09/12,60,E17)
A19: Annual payment burden | B19: =B18*12 | C19: =C18*12 | D19: =D18*12 | E19: =E18*12
A20: Payment as % of average monthly revenue | B20: =IF('CASH QUALITY'!$C$19=0,"",B18/'CASH QUALITY'!$C$19) | C20: =IF('CASH QUALITY'!$C$19=0,"",C18/'CASH QUALITY'!$C$19) | D20: =IF('CASH QUALITY'!$C$19=0,"",D18/'CASH QUALITY'!$C$19) | E20: =IF('CASH QUALITY'!$C$19=0,"",E18/'CASH QUALITY'!$C$19)
A21: Deployable capital after down payment | B21: ='CASH QUALITY'!$C$10-B16 | C21: ='CASH QUALITY'!$C$10-C16 | D21: ='CASH QUALITY'!$C$10-D16 | E21: ='CASH QUALITY'!$C$10-E16
A22: Verdict | B22: =IF(B21<0,"NO",IF(B20>0.08,"HEAVY - payment too large","OK")) | C22: =IF(C21<0,"NO",IF(C20>0.08,"HEAVY - payment too large","OK")) | D22: =IF(D21<0,"NO",IF(D20>0.08,"HEAVY - payment too large","OK")) | E22: =IF(E21<0,"NO",IF(E20>0.08,"HEAVY - payment too large","OK"))
A24: Financing rate and term are placeholders (9%, 60 months). Replace them with a real quote before deciding.
A25: A financed vehicle preserves cash but adds a fixed monthly payment that does not care whether it rained all month. For a seasonal business that matters more than the interest rate.
A26: GST paid on a business vehicle is generally recoverable as an input tax credit, which improves the real cost — but only once you are filing GST again.
A27: A used vehicle bought privately carries no GST but no warranty either. Neither is captured here.

Sheet SCENARIOS
A1: Next Season — three scenarios
A2: Column E is what actually happened this year, pulled from your data. B, C and D scale off it using the blue multipliers. Change a multiplier and the scenario moves.
A4: Line | B4: Conservative | C4: Base | D4: Aggressive | E4: Actual this year | F4: Note
A5: DRIVERS — change these
A6: Revenue multiplier vs this year | B6: 0.8 | C6: 1 | D6: 1.35 | F6: Conservative assumes a weaker season. Aggressive assumes you add capacity and it sells.
A7: Cost inflation multiplier | B7: 1.08 | C7: 1.03 | D7: 1.05 | F7: Applied to fixed operating costs.
A8: Crew members (excluding you) | B8: 1 | C8: 1 | D8: 2 | F8: You currently have Kierran. Aggressive assumes a second hire.
A9: Paid hours per crew member per year | B9: 1200 | C9: 1400 | D9: 1500 | F9: Nine active months at roughly 35-40 hours a week. Adjust to what you actually ran.
A10: Employer burden on wages | B10: 0.13 | C10: 0.13 | D10: 0.13 | F10: Employer CPP and EI plus WorkSafeBC. Roughly 13%. This is the cost above the hourly rate.
A12: PROFIT AND LOSS
A13: Revenue excluding GST | B13: =$E13*B6 | C13: =$E13*C6 | D13: =$E13*D6 | E13: ='BUSINESS PERFORMANCE'!D7 | F13: Scales off what you actually collected, GST removed.
A14: COGS as % of revenue | B14: =$E14 | C14: =$E14 | D14: =$E14*0.97 | E14: =IF('BUSINESS PERFORMANCE'!D7=0,0.35,ABS('MONTH BY MONTH'!I18)/'BUSINESS PERFORMANCE'!D7) | F14: Your actual materials-and-subs ratio. Aggressive assumes a small buying advantage at volume. Defaults to 35% until you have data.
A15: COGS — materials, plants, subs, rentals | B15: =-B13*B14 | C15: =-C13*C14 | D15: =-D13*D14 | E15: =-ABS('MONTH BY MONTH'!I18)
A16: GROSS MARGIN | B16: =B13+B15 | C16: =C13+C15 | D16: =D13+D15 | E16: =E13+E15
A17: Gross margin % | B17: =IF(B13=0,"",B16/B13) | C17: =IF(C13=0,"",C16/C13) | D17: =IF(D13=0,"",D16/D13) | E17: =IF(E13=0,"",E16/E13)
A18: Crew payroll including employer burden | B18: =-B8*B9*ASSUMPTIONS!$C$9*(1+B10) | C18: =-C8*C9*ASSUMPTIONS!$C$9*(1+C10) | D18: =-D8*D9*ASSUMPTIONS!$C$9*(1+D10) | E18: =-ABS('MONTH BY MONTH'!K18) | F18: Crew x hours x $27.00 x 1.13. The burden is the part people forget.
A19: Fixed and operating costs | B19: =-$E19*B7 | C19: =-$E19*C7 | D19: =-$E19*D7 | E19: =ABS('MONTH BY MONTH'!J18) | F19: Insurance, fuel, vehicle, phone, software, accounting, WorkSafeBC, marketing.
A20: OPERATING PROFIT (before your pay) | B20: =B16+B18+B19 | C20: =C16+C18+C19 | D20: =D16+D18+D19 | E20: =E16+E18+E19 | F20: This is what has to cover your own compensation, tax, reserves and growth.
A21: Operating margin % | B21: =IF(B13=0,"",B20/B13) | C21: =IF(C13=0,"",C20/C13) | D21: =IF(D13=0,"",D20/D13) | E21: =IF(E13=0,"",E20/E13)
A23: WHAT IS LEFT
A24: Your compensation (salary or dividend) | B24: =-ASSUMPTIONS!$C$10*12 | C24: =-ASSUMPTIONS!$C$10*12 | D24: =-ASSUMPTIONS!$C$10*12 | E24: =-ASSUMPTIONS!$C$10*7 | F24: Currently $4,000/month. Actual column shows the seven corporate months. Decide salary vs dividend with your accountant before year end.
A25: Income before tax | B25: =B20+B24 | C25: =C20+C24 | D25: =D20+D24 | E25: =E20+E24
A26: Estimated tax | B26: =-MAX(0,B25)*ASSUMPTIONS!$C$18 | C26: =-MAX(0,C25)*ASSUMPTIONS!$C$18 | D26: =-MAX(0,D25)*ASSUMPTIONS!$C$18 | E26: =-MAX(0,E25)*ASSUMPTIONS!$C$18 | F26: ESTIMATE at the small-business rate on ASSUMPTIONS. Salary paid to you reduces this but creates payroll remittances.
A27: FREE CASH GENERATED | B27: =B25+B26 | C27: =C25+C26 | D27: =D25+D26 | E27: =E25+E26 | F27: Cash the business keeps after paying you and setting tax aside.
A28: Ending business cash (starting + free cash) | B28: ='CASH QUALITY'!$C$7+B27 | C28: ='CASH QUALITY'!$C$7+C27 | D28: ='CASH QUALITY'!$C$7+D27 | F28: Starts from cash after CRA is settled, not from the raw bank balance.
A29: Less: operating reserve to hold back | B29: =-'CASH QUALITY'!$C$9 | C29: =-'CASH QUALITY'!$C$9 | D29: =-'CASH QUALITY'!$C$9
A30: AVAILABLE FOR REINVESTMENT | B30: =MAX(0,B28+B29) | C30: =MAX(0,C28+C29) | D30: =MAX(0,D28+D29) | F30: Vehicles, equipment, a second hire, or a bigger buffer. Not all three.
A32: Additional payroll the business could support | B32: =MAX(0,B27*0.5) | C32: =MAX(0,C27*0.5) | D32: =MAX(0,D27*0.5) | F32: Half of free cash as a ceiling, so a hire cannot consume all the slack. At $27/hr plus 13% burden that is roughly this many hours:
A33: equivalent paid hours at $27.00 + burden | B33: =B32/(ASSUMPTIONS!$C$9*1.13) | C33: =C32/(ASSUMPTIONS!$C$9*1.13) | D33: =D32/(ASSUMPTIONS!$C$9*1.13)

Sheet FLAGS
A1: Flags — everything that needs your answer before these numbers are reliable
A2: Counts update as you enter data. A number above zero means the analysis is not yet trustworthy in that respect.
A4: # | B4: What the model found | C4: Count / amount | D4: Why it matters | E4: What to provide
A5: 1 | B5: Transactions with no category chosen | C5: =COUNTIFS(TRANSACTIONS!$A$5:$A$244,"<>",TRANSACTIONS!$F$5:$F$244,"") | D5: An uncategorised row is invisible to every revenue, expense and profit figure, but still moves cash. It is the commonest source of a reconciliation that will not balance. | E5: Go through TRANSACTIONS column F and pick a category on every row.
A6: 2 | B6: Transactions marked UNCLEAR | C6: =COUNTIFS(TRANSACTIONS!$F$5:$F$244,"! UNCLEAR - NEEDS REVIEW") | D6: You flagged these yourself. Each one could be revenue, an expense, a transfer or personal. | E6: Tell me the date, amount and what you remember about each.
A7: 3 | B7: Value of unclear transactions | C7: =SUMIFS(TRANSACTIONS!$D$5:$D$244,TRANSACTIONS!$F$5:$F$244,"! UNCLEAR - NEEDS REVIEW") | D7: This is how much money is currently unexplained. If it is large relative to your cash, nothing downstream is reliable. | E7: Same as above.
A8: 4 | B8: Accounts used in TRANSACTIONS but missing from ACCOUNT MAP | C8: =SUMPRODUCT(--(TRANSACTIONS!$B$5:$B$244<>""),--(ISNA(MATCH(TRANSACTIONS!$B$5:$B$244,'ACCOUNT MAP'!$A$6:$A$44,0)))) | D8: A transaction on an unmapped account has no entity, so it is excluded from every entity total while still being real money. | E8: Add the account to ACCOUNT MAP, or fix the spelling so it matches exactly.
A9: 5 | B9: Accounts on ACCOUNT MAP marked UNSURE | C9: =COUNTIFS('ACCOUNT MAP'!$C$6:$C$44,"UNSURE - FLAG IT") | D9: An account assigned to the wrong entity moves money between the sole prop, the corporation and you personally — which has tax consequences. | E9: Tell me whose name the account is in and what it is used for.
A10: 6 | B10: Transfers with no matching pair id | C10: =COUNTIFS(TRANSACTIONS!$G$5:$G$244,"Transfer",TRANSACTIONS!$H$5:$H$244,"") | D10: An unpaired transfer usually means only one side was entered. That is exactly how $10,000 moved between accounts gets counted as $10,000 of new income. | E10: Put the same id (T1, T2...) on both the money-out row and the money-in row.
A11: 7 | B11: Net value of all transfers (should be near zero) | C11: =SUMIFS(TRANSACTIONS!$D$5:$D$244,TRANSACTIONS!$G$5:$G$244,"Transfer") | D11: Across all your accounts, transfers must net to roughly zero. A large number means a missing side or an account you have not loaded. | E11: Find the missing counterpart transaction.
A12: 8 | B12: Revenue rows with no GST recorded | C12: =COUNTIFS(TRANSACTIONS!$G$5:$G$244,"Revenue",TRANSACTIONS!$I$5:$I$244,"") | D12: If GST was charged but not recorded here, revenue is overstated by 5% and the CRA liability is understated. | E12: Enter the GST portion in column I, or use the manual override on CRA LIABILITY.
A13: 9 | B13: Sole prop activity dated after June 30 | C13: =COUNTIFS(TRANSACTIONS!$E$5:$E$244,"Sole Prop",TRANSACTIONS!$A$5:$A$244,">"&DATE(2026,6,30)) | D13: The sole prop ceased June 30. Activity after that is either a late-settling job, a wrongly mapped account, or income that belongs to the corporation. | E13: Confirm which jobs straddled the transition and which entity earned them.
A14: 10 | B14: Corporate activity dated before July 1 | C14: =COUNTIFS(TRANSACTIONS!$E$5:$E$244,"Corporation",TRANSACTIONS!$A$5:$A$244,"<"&DATE(2026,7,1)) | D14: The corporation did not exist yet. This is usually pre-funding, or a wrongly mapped account. | E14: Confirm the incorporation date and when the corporate account opened.
A15: 11 | B15: Business cash reconciliation difference | C15: ='CASH RECONCILIATION'!E21 | D15: Beginning cash plus inflows minus outflows must equal your real bank balance. It does not. | E15: A missing statement month, an account not loaded, or a wrong opening balance.
A16: 12 | B16: Owner draws recorded from the corporation | C16: =SUMIFS(TRANSACTIONS!$D$5:$D$244,TRANSACTIONS!$E$5:$E$244,"Corporation",TRANSACTIONS!$G$5:$G$244,"Owner Draw/Comp") | D16: You said $4,000/month since July 1. If the recorded total does not match roughly $28,000 across seven months, some draws are miscategorised as expenses. | E16: Confirm every payment to yourself and how each was categorised.
A17: 13 | B17: Business expenses that may be personal | C17: =SUMIFS(TRANSACTIONS!$D$5:$D$244,TRANSACTIONS!$E$5:$E$244,"Corporation",TRANSACTIONS!$F$5:$F$244,"Personal expense")+SUMIFS(TRANSACTIONS!$D$5:$D$244,TRANSACTIONS!$E$5:$E$244,"Sole Prop",TRANSACTIONS!$F$5:$F$244,"Personal expense") | D17: Personal spending from a business account is a shareholder benefit or a draw, not a deduction. CRA reassesses these. | E17: Identify them so they can be recorded as draws instead.
A18: 14 | B18: Personal money spent on the business | C18: =SUMIFS(TRANSACTIONS!$D$5:$D$244,TRANSACTIONS!$E$5:$E$244,"Personal",TRANSACTIONS!$F$5:$F$244,"Materials and plants")+SUMIFS(TRANSACTIONS!$D$5:$D$244,TRANSACTIONS!$E$5:$E$244,"Personal",TRANSACTIONS!$F$5:$F$244,"Subcontractor") | D18: Business costs paid personally are deductible and recoverable, but only if identified. This is money you are owed. | E18: Receipts for anything business-related bought on a personal card.
B20: CONFIRMED ISSUES — from what you have already told me
A21: A | B21: GST returns not filed and not paid, year to date | C21: CONFIRMED | D21: You confirmed this. GST collected is money held for CRA, not revenue. Penalties and interest accrue, and you are personally liable. | E21: How much revenue included GST, and any receipts supporting input tax credits.
A22: B | B22: Payroll source deductions never remitted | C22: CONFIRMED | D22: CPP, EI and income tax on Kierran's wages are trust funds. Penalty is 10% on a first failure, 20% if repeated, plus interest. Directors are personally liable. | E22: Total gross wages paid to date, and whether anything was actually withheld from his pay.
A23: C | B23: Owner draws of $4,000/month with no salary or dividend declared | C23: CONFIRMED | D23: This is a shareholder loan. Under s.15(2) it must be repaid within one year of the fiscal year end or it is added to your personal income. With a Jan 31, 2027 year end, that deadline is Jan 31, 2028. | E23: Your accountant's decision on salary versus dividend, before year end.
A24: D | B24: Wealthsimple account liquidity | C24: CONFIRMED | D24: Investments only count as liquid if you would actually sell them. Selling may also trigger capital gains. | E24: Balance, whether it is registered (TFSA/RRSP) or not, and whether you would genuinely draw on it.
A25: E | B25: No opening balance for personal cash at Feb 1 | C25: CONFIRMED | D25: Personal ending cash cannot be calculated without it. The business opening balance is zero because operations began Feb 2026 — personal is not. | E25: Your TD chequing balance on Jan 31, 2026, and the Wealthsimple balance on the same date.
